Workbook
Name UPDATE: 'Data Sheet'!$E$1

Sheet Alyman's Z Score
B4: ='Data Sheet'!B1 -> AVENUE SUPERMARTS LTD
B7: =CONCATENATE(" ","INR "&'Data Sheet'!B8) -> INR 4358.2
B8: 52 Week (High- INR 5,484.85 & Low - INR 3,340.00)
B10: Altman's Z Score Analysis
B11: Avenue Supermarts Limited, DMart, is an Indian retail corporation that operates a chain of supermarkets and hypermarkets. The company was founded by Radhakishan Damani and is based in Mumbai. As of March 2025, DMart has 415 stores across 12 states and union territories in India] In March 2024, the company had a total of 13,971 permanent employees and 59,961 employees hired on contractual basis
B17: Summery
B42: =B46 -> Working Capital/Total Asset
C43: ='Raw FS'!F2 -> 42795 | D43: ='Raw FS'!G2 -> 43160 | E43: ='Raw FS'!H2 -> 43525 | F43: ='Raw FS'!I2 -> 43891 | G43: ='Raw FS'!J2 -> 44256 | H43: ='Raw FS'!K2 -> 44621 | I43: ='Raw FS'!L2 -> 44986 | J43: ='Raw FS'!M2 -> 45352 | K43: ='Raw FS'!N2 -> 45717
B44: Working Capital | C44: ='Data Sheet'!C65-'Data Sheet'!C60 -> 2582.77 | D44: ='Data Sheet'!D65-'Data Sheet'!D60 -> 1493.08 | E44: ='Data Sheet'!E65-'Data Sheet'!E60 -> 1493.86 | F44: ='Data Sheet'!F65-'Data Sheet'!F60 -> 5085.82 | G44: ='Data Sheet'!G65-'Data Sheet'!G60 -> 4545.08 | H44: ='Data Sheet'!H65-'Data Sheet'!H60 -> 3929.28 | I44: ='Data Sheet'!I65-'Data Sheet'!I60 -> 4349.84 | J44: ='Data Sheet'!J65-'Data Sheet'!J60 -> 4833.09 | K44: ='Data Sheet'!K65-'Data Sheet'!K60 -> 4938.3
B45: Total Asset | C45: ='Data Sheet'!C61 -> 5819.28 | D45: ='Data Sheet'!D61 -> 5648.22 | E45: ='Data Sheet'!E61 -> 7005.5 | F45: ='Data Sheet'!F61 -> 12076.16 | G45: ='Data Sheet'!G61 -> 13655.05 | H45: ='Data Sheet'!H61 -> 15470.98 | I45: ='Data Sheet'!I61 -> 18104.52 | J45: ='Data Sheet'!J61 -> 21172.48 | K45: ='Data Sheet'!K61 -> 24312.78
B46: Working Capital/Total Asset | C46: =C44/C45 -> 0.44382982 | D46: =D44/D45 -> 0.26434523 | E46: =E44/E45 -> 0.21324102 | F46: =F44/F45 -> 0.42114546 | G46: =G44/G45 -> 0.33284975 | H46: =H44/H45 -> 0.25397745 | I46: =I44/I45 -> 0.24026265 | J46: =J44/J45 -> 0.22827227 | K46: =K44/K45 -> 0.2031154
B48: =B52 -> Reatain Earning / Total Asset
C49: =C43 -> 42795 | D49: =D43 -> 43160 | E49: =E43 -> 43525 | F49: =F43 -> 43891 | G49: =G43 -> 44256 | H49: =H43 -> 44621 | I49: =I43 -> 44986 | J49: =J43 -> 45352 | K49: =K43 -> 45717
B50: Retain Earning | C50: =HistoricaIFS!D35*HistoricaIFS!D37*HistoricaIFS!D43 -> 478.75 | D50: =HistoricaIFS!E35*HistoricaIFS!E37*HistoricaIFS!E43 -> 806.26 | E50: =HistoricaIFS!F35*HistoricaIFS!F37*HistoricaIFS!F43 -> 902.54 | F50: =HistoricaIFS!G35*HistoricaIFS!G37*HistoricaIFS!G43 -> 1301.08 | G50: =HistoricaIFS!H35*HistoricaIFS!H37*HistoricaIFS!H43 -> 1099.49 | H50: =HistoricaIFS!I35*HistoricaIFS!I37*HistoricaIFS!I43 -> 1492.55 | I50: =HistoricaIFS!J35*HistoricaIFS!J37*HistoricaIFS!J43 -> 2378.51 | J50: =HistoricaIFS!K35*HistoricaIFS!K37*HistoricaIFS!K43 -> 2536.17 | K50: =HistoricaIFS!L35*HistoricaIFS!L37*HistoricaIFS!L43 -> 2708.02
B51: Total Asset | C51: =C45 -> 5819.28 | D51: =D45 -> 5648.22 | E51: =E45 -> 7005.5 | F51: =F45 -> 12076.16 | G51: =G45 -> 13655.05 | H51: =H45 -> 15470.98 | I51: =I45 -> 18104.52 | J51: =J45 -> 21172.48 | K51: =K45 -> 24312.78
B52: Reatain Earning / Total Asset | C52: =C50/C51 -> 0.082269628 | D52: =D50/D51 -> 0.14274586 | E52: =E50/E51 -> 0.12883306 | F52: =F50/F51 -> 0.10773955 | G52: =G50/G51 -> 0.080518929 | H52: =H50/H51 -> 0.096474173 | I52: =I50/I51 -> 0.13137658 | J52: =J50/J51 -> 0.11978616 | K52: =K50/K51 -> 0.11138257
B54: EBIT / Total Asset
B56: EBIT | C56: ='Data Sheet'!C28+'Data Sheet'!C27 -> 869.06 | D56: ='Data Sheet'!D28+'Data Sheet'!D27 -> 1281.61 | E56: ='Data Sheet'!E28+'Data Sheet'!E27 -> 1469.15 | F56: ='Data Sheet'!F28+'Data Sheet'!F27 -> 1813.89 | G56: ='Data Sheet'!G28+'Data Sheet'!G27 -> 1525.1 | H56: ='Data Sheet'!H28+'Data Sheet'!H27 -> 2117.91 | I56: ='Data Sheet'!I28+'Data Sheet'!I27 -> 3127.5 | J56: ='Data Sheet'!J28+'Data Sheet'!J27 -> 3519.46 | K56: ='Data Sheet'!K28+'Data Sheet'!K27 -> 3742.12
B57: Total Asset | C57: =C45 -> 5819.28 | D57: =D45 -> 5648.22 | E57: =E45 -> 7005.5 | F57: =F45 -> 12076.16 | G57: =G45 -> 13655.05 | H57: =H45 -> 15470.98 | I57: =I45 -> 18104.52 | J57: =J45 -> 21172.48 | K57: =K45 -> 24312.78
B58: EBIT/ Total Asset | C58: =C56/C57 -> 0.1493415 | D58: =D56/D57 -> 0.22690511 | E58: =E56/E57 -> 0.2097138 | F58: =F56/F57 -> 0.1502042 | G58: =G56/G57 -> 0.11168762 | H58: =H56/H57 -> 0.13689566 | I58: =I56/I57 -> 0.17274692 | J58: =J56/J57 -> 0.16622805 | K58: =K56/K57 -> 0.15391576
B60: Market Cap /Long Term Liablities
B62: Market Cap(Cr) | C62: =('Data Sheet'!C90*'Data Sheet'!C70)/10000000 -> 39807.229 | D62: =('Data Sheet'!D90*'Data Sheet'!D70)/10000000 -> 82678.713 | E62: =('Data Sheet'!E90*'Data Sheet'!E70)/10000000 -> 91809.069 | F62: =('Data Sheet'!F90*'Data Sheet'!F70)/10000000 -> 141700.71 | G62: =('Data Sheet'!G90*'Data Sheet'!G70)/10000000 -> 185202.02 | H62: =('Data Sheet'!H90*'Data Sheet'!H70)/10000000 -> 259326.88 | I62: =('Data Sheet'!I90*'Data Sheet'!I70)/10000000 -> 220477.82 | J62: =('Data Sheet'!J90*'Data Sheet'!J70)/10000000 -> 294495.76 | K62: =('Data Sheet'!K90*'Data Sheet'!K70)/10000000 -> 265707.33
B63: Long term Liablities | C63: ='Data Sheet'!C59 -> 1497.32 | D63: ='Data Sheet'!D59 -> 439.25 | E63: ='Data Sheet'!E59 -> 700.15 | F63: ='Data Sheet'!F59 -> 333.19 | G63: ='Data Sheet'!G59 -> 392.71 | H63: ='Data Sheet'!H59 -> 646.94 | I63: ='Data Sheet'!I59 -> 642.98 | J63: ='Data Sheet'!J59 -> 592.16 | K63: ='Data Sheet'!K59 -> 819.62
B64: =B60 -> Market Cap /Long Term Liablities | C64: =C62/C63 -> 26.585652 | D64: =D62/D63 -> 188.22701 | E64: =E62/E63 -> 131.12771 | F64: =F62/F63 -> 425.28501 | G64: =G62/G63 -> 471.59997 | H64: =H62/H63 -> 400.85152 | I64: =I62/I63 -> 342.89997 | J64: =J62/J63 -> 497.32464 | K64: =K62/K63 -> 324.18356
B68: Total Sales/ Total Asset
C69: =C43 -> 42795 | D69: =D43 -> 43160 | E69: =E43 -> 43525 | F69: =F43 -> 43891 | G69: =G43 -> 44256 | H69: =H43 -> 44621 | I69: =I43 -> 44986 | J69: =J43 -> 45352 | K69: =K43 -> 45717
B70: Sales | C70: ='Data Sheet'!C17 -> 11897.7 | D70: ='Data Sheet'!D17 -> 15033.2 | E70: ='Data Sheet'!E17 -> 20004.52 | F70: ='Data Sheet'!F17 -> 24870.2 | G70: ='Data Sheet'!G17 -> 24143.06 | H70: ='Data Sheet'!H17 -> 30976.27 | I70: ='Data Sheet'!I17 -> 42839.56 | J70: ='Data Sheet'!J17 -> 50788.83 | K70: ='Data Sheet'!K17 -> 59358.05
B71: =B57 -> Total Asset | C71: =C45 -> 5819.28 | D71: =D45 -> 5648.22 | E71: =E45 -> 7005.5 | F71: =F45 -> 12076.16 | G71: =G45 -> 13655.05 | H71: =H45 -> 15470.98 | I71: =I45 -> 18104.52 | J71: =J45 -> 21172.48 | K71: =K45 -> 24312.78
B72: =B68 -> Total Sales/ Total Asset | C72: =C70/C71 -> 2.0445313 | D72: =D70/D71 -> 2.6615819 | E72: =E70/E71 -> 2.8555449 | F72: =F70/F71 -> 2.059446 | G72: =G70/G71 -> 1.7680682 | H72: =H70/H71 -> 2.0022177 | I72: =I70/I71 -> 2.3662356 | J72: =J70/J71 -> 2.3988135 | K72: =K70/K71 -> 2.4414341
B74: Altman's Z Score
C75: =C69 -> 42795 | D75: =D69 -> 43160 | E75: =E69 -> 43525 | F75: =F69 -> 43891 | G75: =G69 -> 44256 | H75: =H69 -> 44621 | I75: =I69 -> 44986 | J75: =J69 -> 45352 | K75: =K69 -> 45717
B76: Final Score | C76: =(C46*1.2)+(C52*1.4)+(C58*3.3)+(C64*0.6)+(C72*1) -> 19.136523 | D76: =(D46*1.2)+(D52*1.4)+(D58*3.3)+(D64*0.6)+(D72*1) -> 116.86363 | E76: =(E46*1.2)+(E52*1.4)+(E58*3.3)+(E64*0.6)+(E72*1) -> 82.660484 | F76: =(F46*1.2)+(F52*1.4)+(F58*3.3)+(F64*0.6)+(F72*1) -> 258.38234 | G76: =(G46*1.2)+(G52*1.4)+(G58*3.3)+(G64*0.6)+(G72*1) -> 285.60876 | H76: =(H46*1.2)+(H52*1.4)+(H58*3.3)+(H64*0.6)+(H72*1) -> 243.40472 | I76: =(I46*1.2)+(I52*1.4)+(I58*3.3)+(I64*0.6)+(I72*1) -> 209.14852 | J76: =(J46*1.2)+(J52*1.4)+(J58*3.3)+(J64*0.6)+(J72*1) -> 301.78378 | K76: =(K46*1.2)+(K52*1.4)+(K58*3.3)+(K64*0.6)+(K72*1) -> 197.85916
B77: Finacial Stability | C77: =IF(C76<1.8,"Distressed",IF(C76>3,"Strong","GreyZone")) -> Strong | D77: =IF(D76<1.8,"Distressed",IF(D76>3,"Strong","GreyZone")) -> Strong | E77: =IF(E76<1.8,"Distressed",IF(E76>3,"Strong","GreyZone")) -> Strong | F77: =IF(F76<1.8,"Distressed",IF(F76>3,"Strong","GreyZone")) -> Strong | G77: =IF(G76<1.8,"Distressed",IF(G76>3,"Strong","GreyZone")) -> Strong | H77: =IF(H76<1.8,"Distressed",IF(H76>3,"Strong","GreyZone")) -> Strong | I77: =IF(I76<1.8,"Distressed",IF(I76>3,"Strong","GreyZone")) -> Strong | J77: =IF(J76<1.8,"Distressed",IF(J76>3,"Strong","GreyZone")) -> Strong | K77: =IF(K76<1.8,"Distressed",IF(K76>3,"Strong","GreyZone")) -> Strong

Sheet Profit & Loss
A1: ='Data Sheet'!B1 -> AVENUE SUPERMARTS LTD | H1: =UPDATE | M1: SCREENER.IN
A3: Narration | B3: ='Data Sheet'!B16 -> 42460 | C3: ='Data Sheet'!C16 -> 42825 | D3: ='Data Sheet'!D16 -> 43190 | E3: ='Data Sheet'!E16 -> 43555 | F3: ='Data Sheet'!F16 -> 43921 | G3: ='Data Sheet'!G16 -> 44286 | H3: ='Data Sheet'!H16 -> 44651 | I3: ='Data Sheet'!I16 -> 45016 | ... K3: ='Data Sheet'!K16 -> 45747 | L3: Trailing | M3: Best Case | N3: Worst Case
A4: Sales | B4: ='Data Sheet'!B17 -> 8583.76 | C4: ='Data Sheet'!C17 -> 11897.7 | D4: ='Data Sheet'!D17 -> 15033.2 | E4: ='Data Sheet'!E17 -> 20004.52 | F4: ='Data Sheet'!F17 -> 24870.2 | G4: ='Data Sheet'!G17 -> 24143.06 | H4: ='Data Sheet'!H17 -> 30976.27 | I4: ='Data Sheet'!I17 -> 42839.56 | ... K4: ='Data Sheet'!K17 -> 59358.05 | L4: =SUM(Quarters!H4:K4) -> 61648.61 | M4: =$K4+M23*K4 -> 73727.548 | N4: =$K4+N23*L4 -> 69759.56
A5: Expenses | B5: =SUM('Data Sheet'!B18,'Data Sheet'!B20:B24, -1*'Data Sheet'!B19) -> 7919.3 | C5: =SUM('Data Sheet'!C18,'Data Sheet'!C20:C24, -1*'Data Sheet'!C19) -> 10928.52 | D5: =SUM('Data Sheet'!D18,'Data Sheet'!D20:D24, -1*'Data Sheet'!D19) -> 13680.34 | E5: =SUM('Data Sheet'!E18,'Data Sheet'!E20:E24, -1*'Data Sheet'!E19) -> 18371.21 | F5: =SUM('Data Sheet'!F18,'Data Sheet'!F20:F24, -1*'Data Sheet'!F19) -> 22741.89 | G5: =SUM('Data Sheet'!G18,'Data Sheet'!G20:G24, -1*'Data Sheet'!G19) -> 22398.23 | H5: =SUM('Data Sheet'!H18,'Data Sheet'!H20:H24, -1*'Data Sheet'!H19) -> 28473.92 | I5: =SUM('Data Sheet'!I18,'Data Sheet'!I20:I24, -1*'Data Sheet'!I19) -> 39200.79 | ... K5: =SUM('Data Sheet'!K18,'Data Sheet'!K20:K24, -1*'Data Sheet'!K19) -> 54863.54 | L5: =SUM(Quarters!H5:K5) -> 57083.49 | M5: =M4-M6 -> 67829.342 | N5: =N4-N6 -> 64593.818
A6: Operating Profit | B6: =B4-B5 -> 664.46 | C6: =C4-C5 -> 969.18 | D6: =D4-D5 -> 1352.86 | E6: =E4-E5 -> 1633.31 | F6: =F4-F5 -> 2128.31 | G6: =G4-G5 -> 1744.83 | H6: =H4-H5 -> 2502.35 | I6: =I4-I5 -> 3638.77 | ... K6: =K4-K5 -> 4494.51 | L6: =SUM(Quarters!H6:K6) -> 4565.12 | M6: =M4*M24 -> 5898.2062 | N6: =N4*N24 -> 5165.7411
A7: Other Income | B7: ='Data Sheet'!B25 -> 17.02 | C7: ='Data Sheet'!C25 -> 27.7 | D7: ='Data Sheet'!D25 -> 87.75 | E7: ='Data Sheet'!E25 -> 48.33 | F7: ='Data Sheet'!F25 -> 59.99 | G7: ='Data Sheet'!G25 -> 194.43 | H7: ='Data Sheet'!H25 -> 113.64 | I7: ='Data Sheet'!I25 -> 127.6 | ... K7: ='Data Sheet'!K25 -> 117.13 | L7: =SUM(Quarters!H7:K7) -> 102.14 | M7: 0 | N7: 0
A8: Depreciation | B8: ='Data Sheet'!B26 -> 98.43 | C8: ='Data Sheet'!C26 -> 127.82 | D8: ='Data Sheet'!D26 -> 159 | E8: ='Data Sheet'!E26 -> 212.49 | F8: ='Data Sheet'!F26 -> 374.41 | G8: ='Data Sheet'!G26 -> 414.16 | H8: ='Data Sheet'!H26 -> 498.08 | I8: ='Data Sheet'!I26 -> 638.87 | ... K8: ='Data Sheet'!K26 -> 869.52 | L8: =SUM(Quarters!H8:K8) -> 908.46 | M8: =+$L8 -> 908.46 | N8: =+$L8 -> 908.46
A9: Interest | B9: ='Data Sheet'!B27 -> 91.34 | C9: ='Data Sheet'!C27 -> 121.98 | D9: ='Data Sheet'!D27 -> 59.54 | E9: ='Data Sheet'!E27 -> 47.21 | F9: ='Data Sheet'!F27 -> 69.12 | G9: ='Data Sheet'!G27 -> 41.65 | H9: ='Data Sheet'!H27 -> 53.79 | I9: ='Data Sheet'!I27 -> 67.41 | ... K9: ='Data Sheet'!K27 -> 69.45 | L9: =SUM(Quarters!H9:K9) -> 82.79 | M9: =+$L9 -> 82.79 | N9: =+$L9 -> 82.79
A10: Profit before tax | B10: ='Data Sheet'!B28 -> 491.71 | C10: ='Data Sheet'!C28 -> 747.08 | D10: ='Data Sheet'!D28 -> 1222.07 | E10: ='Data Sheet'!E28 -> 1421.94 | F10: ='Data Sheet'!F28 -> 1744.77 | G10: ='Data Sheet'!G28 -> 1483.45 | H10: ='Data Sheet'!H28 -> 2064.12 | I10: ='Data Sheet'!I28 -> 3060.09 | ... K10: ='Data Sheet'!K28 -> 3672.67 | L10: =SUM(Quarters!H10:K10) -> 3676.01 | M10: =M6+M7-SUM(M8:M9) -> 4906.9562 | N10: =N6+N7-SUM(N8:N9) -> 4174.4911
A11: Tax | B11: ='Data Sheet'!B29 -> 171.47 | C11: ='Data Sheet'!C29 -> 268.28 | D11: ='Data Sheet'!D29 -> 415.79 | E11: ='Data Sheet'!E29 -> 519.48 | F11: ='Data Sheet'!F29 -> 443.79 | G11: ='Data Sheet'!G29 -> 384.02 | H11: ='Data Sheet'!H29 -> 571.72 | I11: ='Data Sheet'!I29 -> 681.75 | ... K11: ='Data Sheet'!K29 -> 965.22 | L11: =SUM(Quarters!H11:K11) -> 969.43 | M11: =IF($L10>0,$L11/$L10,0) -> 0.263718 | N11: =IF($L10>0,$L11/$L10,0) -> 0.263718
A12: Net profit | B12: ='Data Sheet'!B30 -> 320.24 | C12: ='Data Sheet'!C30 -> 478.75 | D12: ='Data Sheet'!D30 -> 806.26 | E12: ='Data Sheet'!E30 -> 902.54 | F12: ='Data Sheet'!F30 -> 1301.08 | G12: ='Data Sheet'!G30 -> 1099.49 | H12: ='Data Sheet'!H30 -> 1492.55 | I12: ='Data Sheet'!I30 -> 2378.51 | ... K12: ='Data Sheet'!K30 -> 2708.02 | L12: =SUM(Quarters!H12:K12) -> 2707.17 | M12: =M10-M11*M10 -> 3612.9035 | N12: =N10-N11*N10 -> 3073.6027
A13: EPS | B13: =IF('Data Sheet'!B93>0,B12/'Data Sheet'!B93,0) -> 5.7032947 | C13: =IF('Data Sheet'!C93>0,C12/'Data Sheet'!C93,0) -> 7.6710463 | D13: =IF('Data Sheet'!D93>0,D12/'Data Sheet'!D93,0) -> 12.918763 | E13: =IF('Data Sheet'!E93>0,E12/'Data Sheet'!E93,0) -> 14.461465 | F13: =IF('Data Sheet'!F93>0,F12/'Data Sheet'!F93,0) -> 20.084594 | G13: =IF('Data Sheet'!G93>0,G12/'Data Sheet'!G93,0) -> 16.972677 | H13: =IF('Data Sheet'!H93>0,H12/'Data Sheet'!H93,0) -> 23.04029 | I13: =IF('Data Sheet'!I93>0,I12/'Data Sheet'!I93,0) -> 36.688416 | ... K13: =IF('Data Sheet'!K93>0,K12/'Data Sheet'!K93,0) -> 41.617028 | L13: =IF('Data Sheet'!$B6>0,'Profit & Loss'!L12/'Data Sheet'!$B6,0) -> 41.60185 | M13: =IF('Data Sheet'!$B6>0,'Profit & Loss'!M12/'Data Sheet'!$B6,0) -> 55.520514 | N13: =IF('Data Sheet'!$B6>0,'Profit & Loss'!N12/'Data Sheet'!$B6,0) -> 47.232925
A14: Price to earning | B14: =IF(B15>0,B15/B13,"") | C14: =IF(C15>0,C15/C13,"") -> 83.150326 | D14: =IF(D15>0,D15/D13,"") -> 102.54852 | E14: =IF(E15>0,E15/E13,"") -> 101.72552 | F14: =IF(F15>0,F15/F13,"") -> 108.91433 | G14: =IF(G15>0,G15/G13,"") -> 168.45015 | H14: =IF(H15>0,H15/H13,"") -> 173.75432 | I14: =IF(I15>0,I15/I13,"") -> 92.700923 | ... K14: =IF(K15>0,K15/K13,"") -> 98.113686 | L14: =IF(L13>0,L15/L13,0) -> 104.75976 | M14: =M25 -> 104.75976 | N14: =N25 -> 102.92169
A15: Price | B15: ='Data Sheet'!B90 -> 0 | C15: ='Data Sheet'!C90 -> 637.85 | D15: ='Data Sheet'!D90 -> 1324.8 | E15: ='Data Sheet'!E90 -> 1471.1 | F15: ='Data Sheet'!F90 -> 2187.5 | G15: ='Data Sheet'!G90 -> 2859.05 | H15: ='Data Sheet'!H90 -> 4003.35 | I15: ='Data Sheet'!I90 -> 3401.05 | ... K15: ='Data Sheet'!K90 -> 4083.2 | L15: ='Data Sheet'!B8 -> 4358.2 | M15: =M13*M14 -> 5816.316 | N15: =N13*N14 -> 4861.2927
A17: RATIOS:
A18: Dividend Payout | B18: =IF('Data Sheet'!B30>0, 'Data Sheet'!B31/'Data Sheet'!B30, 0) -> 0 | C18: =IF('Data Sheet'!C30>0, 'Data Sheet'!C31/'Data Sheet'!C30, 0) -> 0 | D18: =IF('Data Sheet'!D30>0, 'Data Sheet'!D31/'Data Sheet'!D30, 0) -> 0 | E18: =IF('Data Sheet'!E30>0, 'Data Sheet'!E31/'Data Sheet'!E30, 0) -> 0 | F18: =IF('Data Sheet'!F30>0, 'Data Sheet'!F31/'Data Sheet'!F30, 0) -> 0 | G18: =IF('Data Sheet'!G30>0, 'Data Sheet'!G31/'Data Sheet'!G30, 0) -> 0 | H18: =IF('Data Sheet'!H30>0, 'Data Sheet'!H31/'Data Sheet'!H30, 0) -> 0 | I18: =IF('Data Sheet'!I30>0, 'Data Sheet'!I31/'Data Sheet'!I30, 0) -> 0 | ... K18: =IF('Data Sheet'!K30>0, 'Data Sheet'!K31/'Data Sheet'!K30, 0) -> 0
A19: OPM | B19: =IF(B6>0,B6/B4,0) -> 0.077408968 | C19: =IF(C6>0,C6/C4,0) -> 0.081459442 | D19: =IF(D6>0,D6/D4,0) -> 0.089991486 | E19: =IF(E6>0,E6/E4,0) -> 0.081647048 | F19: =IF(F6>0,F6/F4,0) -> 0.085576714 | G19: =IF(G6>0,G6/G4,0) -> 0.072270458 | H19: =IF(H6>0,H6/H4,0) -> 0.080782806 | I19: =IF(I6>0,I6/I4,0) -> 0.084939481 | ... L19: =IF(L6>0,L6/L4,0) -> 0.074050656
G22: TRENDS: | H22: 10 YEARS | I22: 7 YEARS | J22: 5 YEARS | K22: 3 YEARS | L22: RECENT | M22: BEST | N22: WORST
G23: Sales Growth | H23: =IF(B4=0,"",POWER($K4/B4,1/9)-1) -> 0.23968498 | I23: =IF(D4=0,"",POWER($K4/D4,1/7)-1) -> 0.21675749 | J23: =IF(F4=0,"",POWER($K4/F4,1/5)-1) -> 0.19003592 | K23: =IF(H4=0,"",POWER($K4/H4, 1/3)-1) -> 0.24208171 | L23: =IF(ISERROR(MAX(IF(J4=0,"",(K4-J4)/J4),IF(K4=0,"",(L4-K4)/K4))),"",MAX(IF(J4=0,"",(K4-J4)/J4),IF(K4=0,"",(L4-K4)/K4))) -> 0.16872253 | M23: =MAX(K23:L23) -> 0.24208171 | N23: =MIN(H23:L23) -> 0.16872253
G24: OPM | H24: =IF(SUM(B4:$K$4)=0,"",SUMPRODUCT(B19:$K$19,B4:$K$4)/SUM(B4:$K$4)) -> 0.080535912 | I24: =IF(SUM(E4:$K$4)=0,"",SUMPRODUCT(E19:$K$19,E4:$K$4)/SUM(E4:$K$4)) -> 0.080036686 | J24: =IF(SUM(G4:$K$4)=0,"",SUMPRODUCT(G19:$K$19,G4:$K$4)/SUM(G4:$K$4)) -> 0.079219812 | K24: =IF(SUM(I4:$K$4)=0, "", SUMPRODUCT(I19:$K$19,I4:$K$4)/SUM(I4:$K$4)) -> 0.080000031 | L24: =L19 -> 0.074050656 | M24: =MAX(K24:L24) -> 0.080000031 | N24: =MIN(H24:L24) -> 0.074050656
G25: Price to Earning | H25: =IF(ISERROR(AVERAGEIF(B14:$L14,">0")),"",AVERAGEIF(B14:$L14,">0")) -> 115.02299 | I25: =IF(ISERROR(AVERAGEIF(E14:$L14,">0")),"",AVERAGEIF(E14:$L14,">0")) -> 120.56639 | J25: =IF(ISERROR(AVERAGEIF(G14:$L14,">0")),"",AVERAGEIF(G14:$L14,">0")) -> 125.64854 | K25: =IF(ISERROR(AVERAGEIF(I14:$L14,">0")),"",AVERAGEIF(I14:$L14,">0")) -> 102.92169 | L25: =L14 -> 104.75976 | M25: =MAX(K25:L25) -> 104.75976 | N25: =MIN(H25:L25) -> 102.92169

Sheet Quarters
A1: ='Profit & Loss'!A1 -> AVENUE SUPERMARTS LTD | E1: =UPDATE | J1: SCREENER.IN
A3: Narration | B3: ='Data Sheet'!B41 -> 45016 | C3: ='Data Sheet'!C41 -> 45107 | D3: ='Data Sheet'!D41 -> 45199 | E3: ='Data Sheet'!E41 -> 45291 | F3: ='Data Sheet'!F41 -> 45382 | G3: ='Data Sheet'!G41 -> 45473 | H3: ='Data Sheet'!H41 -> 45565 | I3: ='Data Sheet'!I41 -> 45657 | ... K3: ='Data Sheet'!K41 -> 45838
A4: Sales | B4: ='Data Sheet'!B42 -> 10594.11 | C4: ='Data Sheet'!C42 -> 11865.44 | D4: ='Data Sheet'!D42 -> 12624.37 | E4: ='Data Sheet'!E42 -> 13572.47 | F4: ='Data Sheet'!F42 -> 12726.55 | G4: ='Data Sheet'!G42 -> 14069.14 | H4: ='Data Sheet'!H42 -> 14444.5 | I4: ='Data Sheet'!I42 -> 15972.55 | ... K4: ='Data Sheet'!K42 -> 16359.7
A5: Expenses | B5: ='Data Sheet'!B43 -> 9822.6 | C5: ='Data Sheet'!C43 -> 10830.17 | D5: ='Data Sheet'!D43 -> 11619.4 | E5: ='Data Sheet'!E43 -> 12452.58 | F5: ='Data Sheet'!F43 -> 11782.91 | G5: ='Data Sheet'!G43 -> 12847.89 | H5: ='Data Sheet'!H43 -> 13350.73 | I5: ='Data Sheet'!I43 -> 14755.31 | ... K5: ='Data Sheet'!K43 -> 15060.66
A6: Operating Profit | B6: ='Data Sheet'!B50 -> 771.51 | C6: ='Data Sheet'!C50 -> 1035.27 | D6: ='Data Sheet'!D50 -> 1004.97 | E6: ='Data Sheet'!E50 -> 1119.89 | F6: ='Data Sheet'!F50 -> 943.64 | G6: ='Data Sheet'!G50 -> 1221.25 | H6: ='Data Sheet'!H50 -> 1093.77 | I6: ='Data Sheet'!I50 -> 1217.24 | ... K6: ='Data Sheet'!K50 -> 1299.04
A7: Other Income | B7: ='Data Sheet'!B44 -> 33.07 | C7: ='Data Sheet'!C44 -> 38.74 | D7: ='Data Sheet'!D44 -> 36.92 | E7: ='Data Sheet'!E44 -> 32.92 | F7: ='Data Sheet'!F44 -> 37.87 | G7: ='Data Sheet'!G44 -> 41.6 | H7: ='Data Sheet'!H44 -> 33.52 | I7: ='Data Sheet'!I44 -> 24.14 | ... K7: ='Data Sheet'!K44 -> 19.43
A8: Depreciation | B8: ='Data Sheet'!B45 -> 164.08 | C8: ='Data Sheet'!C45 -> 162.18 | D8: ='Data Sheet'!D45 -> 174.36 | E8: ='Data Sheet'!E45 -> 189.33 | F8: ='Data Sheet'!F45 -> 204.89 | G8: ='Data Sheet'!G45 -> 192.76 | H8: ='Data Sheet'!H45 -> 207.78 | I8: ='Data Sheet'!I45 -> 228.12 | ... K8: ='Data Sheet'!K45 -> 231.7
A9: Interest | B9: ='Data Sheet'!B46 -> 15.53 | C9: ='Data Sheet'!C46 -> 14.57 | D9: ='Data Sheet'!D46 -> 15.59 | E9: ='Data Sheet'!E46 -> 14.55 | F9: ='Data Sheet'!F46 -> 13.42 | G9: ='Data Sheet'!G46 -> 15.96 | H9: ='Data Sheet'!H46 -> 16.32 | I9: ='Data Sheet'!I46 -> 18.21 | ... K9: ='Data Sheet'!K46 -> 29.3
A10: Profit before tax | B10: ='Data Sheet'!B47 -> 624.97 | C10: ='Data Sheet'!C47 -> 897.26 | D10: ='Data Sheet'!D47 -> 851.94 | E10: ='Data Sheet'!E47 -> 948.93 | F10: ='Data Sheet'!F47 -> 763.2 | G10: ='Data Sheet'!G47 -> 1054.13 | H10: ='Data Sheet'!H47 -> 903.19 | I10: ='Data Sheet'!I47 -> 995.05 | ... K10: ='Data Sheet'!K47 -> 1057.47
A11: Tax | B11: ='Data Sheet'!B48 -> 164.87 | C11: ='Data Sheet'!C48 -> 238.55 | D11: ='Data Sheet'!D48 -> 228.59 | E11: ='Data Sheet'!E48 -> 258.52 | F11: ='Data Sheet'!F48 -> 200.06 | G11: ='Data Sheet'!G48 -> 280.45 | H11: ='Data Sheet'!H48 -> 243.75 | I11: ='Data Sheet'!I48 -> 271.51 | ... K11: ='Data Sheet'!K48 -> 284.66
A12: Net profit | B12: ='Data Sheet'!B49 -> 460.13 | C12: ='Data Sheet'!C49 -> 658.75 | D12: ='Data Sheet'!D49 -> 623.56 | E12: ='Data Sheet'!E49 -> 690.61 | F12: ='Data Sheet'!F49 -> 563.25 | G12: ='Data Sheet'!G49 -> 773.82 | H12: ='Data Sheet'!H49 -> 659.58 | I12: ='Data Sheet'!I49 -> 723.72 | ... K12: ='Data Sheet'!K49 -> 772.97
A14: OPM | B14: =IF(B4>0,B6/B4,"") -> 0.072824428 | C14: =IF(C4>0,C6/C4,"") -> 0.087250873 | D14: =IF(D4>0,D6/D4,"") -> 0.079605557 | E14: =IF(E4>0,E6/E4,"") -> 0.082511879 | F14: =IF(F4>0,F6/F4,"") -> 0.074147353 | G14: =IF(G4>0,G6/G4,"") -> 0.086803458 | H14: =IF(H4>0,H6/H4,"") -> 0.075722247 | I14: =IF(I4>0,I6/I4,"") -> 0.076208245 | ... K14: =IF(K4>0,K6/K4,"") -> 0.079404879

Sheet Balance Sheet
A1: ='Profit & Loss'!A1 -> AVENUE SUPERMARTS LTD | E1: =UPDATE | J1: SCREENER.IN
A3: Narration | B3: ='Data Sheet'!B56 -> 42460 | C3: ='Data Sheet'!C56 -> 42825 | D3: ='Data Sheet'!D56 -> 43190 | E3: ='Data Sheet'!E56 -> 43555 | F3: ='Data Sheet'!F56 -> 43921 | G3: ='Data Sheet'!G56 -> 44286 | H3: ='Data Sheet'!H56 -> 44651 | I3: ='Data Sheet'!I56 -> 45016 | ... K3: ='Data Sheet'!K56 -> 45747
A4: Equity Share Capital | B4: ='Data Sheet'!B57 -> 561.54 | C4: ='Data Sheet'!C57 -> 624.08 | D4: ='Data Sheet'!D57 -> 624.08 | E4: ='Data Sheet'!E57 -> 624.08 | F4: ='Data Sheet'!F57 -> 647.77 | G4: ='Data Sheet'!G57 -> 647.77 | H4: ='Data Sheet'!H57 -> 647.77 | I4: ='Data Sheet'!I57 -> 648.26 | ... K4: ='Data Sheet'!K57 -> 650.73
A5: Reserves | B5: ='Data Sheet'!B58 -> 958.9 | C5: ='Data Sheet'!C58 -> 3217.7 | D5: ='Data Sheet'!D58 -> 4044.97 | E5: ='Data Sheet'!E58 -> 4963.37 | F5: ='Data Sheet'!F58 -> 10431.97 | G5: ='Data Sheet'!G58 -> 11535.94 | H5: ='Data Sheet'!H58 -> 13029.87 | I5: ='Data Sheet'!I58 -> 15430.44 | ... K5: ='Data Sheet'!K58 -> 20777.02
A6: Borrowings | B6: ='Data Sheet'!B59 -> 1192.34 | C6: ='Data Sheet'!C59 -> 1497.32 | D6: ='Data Sheet'!D59 -> 439.25 | E6: ='Data Sheet'!E59 -> 700.15 | F6: ='Data Sheet'!F59 -> 333.19 | G6: ='Data Sheet'!G59 -> 392.71 | H6: ='Data Sheet'!H59 -> 646.94 | I6: ='Data Sheet'!I59 -> 642.98 | ... K6: ='Data Sheet'!K59 -> 819.62
A7: Other Liabilities | B7: ='Data Sheet'!B60 -> 388.78 | C7: ='Data Sheet'!C60 -> 480.18 | D7: ='Data Sheet'!D60 -> 539.92 | E7: ='Data Sheet'!E60 -> 717.9 | F7: ='Data Sheet'!F60 -> 663.23 | G7: ='Data Sheet'!G60 -> 1078.63 | H7: ='Data Sheet'!H60 -> 1146.4 | I7: ='Data Sheet'!I60 -> 1382.84 | ... K7: ='Data Sheet'!K60 -> 2065.41
A8: Total | B8: ='Data Sheet'!B61 -> 3101.56 | C8: ='Data Sheet'!C61 -> 5819.28 | D8: ='Data Sheet'!D61 -> 5648.22 | E8: ='Data Sheet'!E61 -> 7005.5 | F8: ='Data Sheet'!F61 -> 12076.16 | G8: ='Data Sheet'!G61 -> 13655.05 | H8: ='Data Sheet'!H61 -> 15470.98 | I8: ='Data Sheet'!I61 -> 18104.52 | ... K8: ='Data Sheet'!K61 -> 24312.78
A10: Net Block | B10: ='Data Sheet'!B62 -> 2093.52 | C10: ='Data Sheet'!C62 -> 2577.75 | D10: ='Data Sheet'!D62 -> 3399.97 | E10: ='Data Sheet'!E62 -> 4400.37 | F10: ='Data Sheet'!F62 -> 5948.03 | G10: ='Data Sheet'!G62 -> 7008.8 | H10: ='Data Sheet'!H62 -> 9260.02 | I10: ='Data Sheet'!I62 -> 11340.48 | ... K10: ='Data Sheet'!K62 -> 16206.46
A11: Capital Work in Progress | B11: ='Data Sheet'!B63 -> 81.69 | C11: ='Data Sheet'!C63 -> 152.89 | D11: ='Data Sheet'!D63 -> 147.07 | E11: ='Data Sheet'!E63 -> 376.84 | F11: ='Data Sheet'!F63 -> 364.4 | G11: ='Data Sheet'!G63 -> 1019.59 | H11: ='Data Sheet'!H63 -> 1129.34 | I11: ='Data Sheet'!I63 -> 829.16 | ... K11: ='Data Sheet'!K63 -> 1099.35
A12: Investments | B12: ='Data Sheet'!B64 -> 29.33 | C12: ='Data Sheet'!C64 -> 25.69 | D12: ='Data Sheet'!D64 -> 68.18 | E12: ='Data Sheet'!E64 -> 16.53 | F12: ='Data Sheet'!F64 -> 14.68 | G12: ='Data Sheet'!G64 -> 2.95 | H12: ='Data Sheet'!H64 -> 5.94 | I12: ='Data Sheet'!I64 -> 202.2 | ... K12: ='Data Sheet'!K64 -> 3.26
A13: Other Assets | B13: ='Data Sheet'!B65 -> 897.02 | C13: ='Data Sheet'!C65 -> 3062.95 | D13: ='Data Sheet'!D65 -> 2033 | E13: ='Data Sheet'!E65 -> 2211.76 | F13: ='Data Sheet'!F65 -> 5749.05 | G13: ='Data Sheet'!G65 -> 5623.71 | H13: ='Data Sheet'!H65 -> 5075.68 | I13: ='Data Sheet'!I65 -> 5732.68 | ... K13: ='Data Sheet'!K65 -> 7003.71
A14: Total | B14: ='Data Sheet'!B66 -> 3101.56 | C14: ='Data Sheet'!C66 -> 5819.28 | D14: ='Data Sheet'!D66 -> 5648.22 | E14: ='Data Sheet'!E66 -> 7005.5 | F14: ='Data Sheet'!F66 -> 12076.16 | G14: ='Data Sheet'!G66 -> 13655.05 | H14: ='Data Sheet'!H66 -> 15470.98 | I14: ='Data Sheet'!I66 -> 18104.52 | ... K14: ='Data Sheet'!K66 -> 24312.78
A16: Working Capital | B16: =B13-B7 -> 508.24 | C16: =C13-C7 -> 2582.77 | D16: =D13-D7 -> 1493.08 | E16: =E13-E7 -> 1493.86 | F16: =F13-F7 -> 5085.82 | G16: =G13-G7 -> 4545.08 | H16: =H13-H7 -> 3929.28 | I16: =I13-I7 -> 4349.84 | ... K16: =K13-K7 -> 4938.3
A17: Debtors | B17: ='Data Sheet'!B67 -> 8.42 | C17: ='Data Sheet'!C67 -> 21 | D17: ='Data Sheet'!D67 -> 33.52 | E17: ='Data Sheet'!E67 -> 64.37 | F17: ='Data Sheet'!F67 -> 19.55 | G17: ='Data Sheet'!G67 -> 43.58 | H17: ='Data Sheet'!H67 -> 66.89 | I17: ='Data Sheet'!I67 -> 62.16 | ... K17: ='Data Sheet'!K67 -> 153.79
A18: Inventory | B18: ='Data Sheet'!B68 -> 671.69 | C18: ='Data Sheet'!C68 -> 947.9 | D18: ='Data Sheet'!D68 -> 1163.45 | E18: ='Data Sheet'!E68 -> 1608.65 | F18: ='Data Sheet'!F68 -> 1947.4 | G18: ='Data Sheet'!G68 -> 2248.28 | H18: ='Data Sheet'!H68 -> 2742.66 | I18: ='Data Sheet'!I68 -> 3243.48 | ... K18: ='Data Sheet'!K68 -> 5044.37
A20: Debtor Days | B20: =IF('Profit & Loss'!B4>0,'Balance Sheet'!B17/('Profit & Loss'!B4/365),0) -> 0.35803657 | C20: =IF('Profit & Loss'!C4>0,'Balance Sheet'!C17/('Profit & Loss'!C4/365),0) -> 0.64424216 | D20: =IF('Profit & Loss'!D4>0,'Balance Sheet'!D17/('Profit & Loss'!D4/365),0) -> 0.81385201 | E20: =IF('Profit & Loss'!E4>0,'Balance Sheet'!E17/('Profit & Loss'!E4/365),0) -> 1.1744871 | F20: =IF('Profit & Loss'!F4>0,'Balance Sheet'!F17/('Profit & Loss'!F4/365),0) -> 0.28691969 | G20: =IF('Profit & Loss'!G4>0,'Balance Sheet'!G17/('Profit & Loss'!G4/365),0) -> 0.65885186 | H20: =IF('Profit & Loss'!H4>0,'Balance Sheet'!H17/('Profit & Loss'!H4/365),0) -> 0.78817914 | I20: =IF('Profit & Loss'!I4>0,'Balance Sheet'!I17/('Profit & Loss'!I4/365),0) -> 0.52961328 | ... K20: =IF('Profit & Loss'!K4>0,'Balance Sheet'!K17/('Profit & Loss'!K4/365),0) -> 0.94567375
A21: Inventory Turnover | B21: =IF('Balance Sheet'!B18>0,'Profit & Loss'!B4/'Balance Sheet'!B18,0) -> 12.779348 | C21: =IF('Balance Sheet'!C18>0,'Profit & Loss'!C4/'Balance Sheet'!C18,0) -> 12.55164 | D21: =IF('Balance Sheet'!D18>0,'Profit & Loss'!D4/'Balance Sheet'!D18,0) -> 12.921226 | E21: =IF('Balance Sheet'!E18>0,'Profit & Loss'!E4/'Balance Sheet'!E18,0) -> 12.435595 | F21: =IF('Balance Sheet'!F18>0,'Profit & Loss'!F4/'Balance Sheet'!F18,0) -> 12.770977 | G21: =IF('Balance Sheet'!G18>0,'Profit & Loss'!G4/'Balance Sheet'!G18,0) -> 10.738458 | H21: =IF('Balance Sheet'!H18>0,'Profit & Loss'!H4/'Balance Sheet'!H18,0) -> 11.294244 | I21: =IF('Balance Sheet'!I18>0,'Profit & Loss'!I4/'Balance Sheet'!I18,0) -> 13.2079 | ... K21: =IF('Balance Sheet'!K18>0,'Profit & Loss'!K4/'Balance Sheet'!K18,0) -> 11.767188
A23: Return on Equity | B23: =IF(SUM('Balance Sheet'!B4:B5)>0,'Profit & Loss'!B12/SUM('Balance Sheet'!B4:B5),"") -> 0.21062324 | C23: =IF(SUM('Balance Sheet'!C4:C5)>0,'Profit & Loss'!C12/SUM('Balance Sheet'!C4:C5),"") -> 0.12461671 | D23: =IF(SUM('Balance Sheet'!D4:D5)>0,'Profit & Loss'!D12/SUM('Balance Sheet'!D4:D5),"") -> 0.17268181 | E23: =IF(SUM('Balance Sheet'!E4:E5)>0,'Profit & Loss'!E12/SUM('Balance Sheet'!E4:E5),"") -> 0.16152986 | F23: =IF(SUM('Balance Sheet'!F4:F5)>0,'Profit & Loss'!F12/SUM('Balance Sheet'!F4:F5),"") -> 0.11742875 | G23: =IF(SUM('Balance Sheet'!G4:G5)>0,'Profit & Loss'!G12/SUM('Balance Sheet'!G4:G5),"") -> 0.090242627 | H23: =IF(SUM('Balance Sheet'!H4:H5)>0,'Profit & Loss'!H12/SUM('Balance Sheet'!H4:H5),"") -> 0.10912336 | I23: =IF(SUM('Balance Sheet'!I4:I5)>0,'Profit & Loss'!I12/SUM('Balance Sheet'!I4:I5),"") -> 0.14792925 | ... K23: =IF(SUM('Balance Sheet'!K4:K5)>0,'Profit & Loss'!K12/SUM('Balance Sheet'!K4:K5),"") -> 0.12637911
A24: Return on Capital Emp | C24: =IF((B4+B5+B6+C4+C5+C6)>0,('Profit & Loss'!C10+'Profit & Loss'!C9)*2/(B4+B5+B6+C4+C5+C6),"") -> 0.21586511 | D24: =IF((C4+C5+C6+D4+D5+D6)>0,('Profit & Loss'!D10+'Profit & Loss'!D9)*2/(C4+C5+C6+D4+D5+D6),"") -> 0.24534525 | E24: =IF((D4+D5+D6+E4+E5+E6)>0,('Profit & Loss'!E10+'Profit & Loss'!E9)*2/(D4+D5+D6+E4+E5+E6),"") -> 0.25783835 | F24: =IF((E4+E5+E6+F4+F5+F6)>0,('Profit & Loss'!F10+'Profit & Loss'!F9)*2/(E4+E5+E6+F4+F5+F6),"") -> 0.20495319 | G24: =IF((F4+F5+F6+G4+G5+G6)>0,('Profit & Loss'!G10+'Profit & Loss'!G9)*2/(F4+F5+F6+G4+G5+G6),"") -> 0.12714809 | H24: =IF((G4+G5+G6+H4+H5+H6)>0,('Profit & Loss'!H10+'Profit & Loss'!H9)*2/(G4+G5+G6+H4+H5+H6),"") -> 0.15745957 | I24: =IF((H4+H5+H6+I4+I5+I6)>0,('Profit & Loss'!I10+'Profit & Loss'!I9)*2/(H4+H5+H6+I4+I5+I6),"") -> 0.20147354 | J24: =IF((I4+I5+I6+J4+J5+J6)>0,('Profit & Loss'!J10+'Profit & Loss'!J9)*2/(I4+I5+I6+J4+J5+J6),"") -> 0.19546225 | K24: =IF((J4+J5+J6+K4+K5+K6)>0,('Profit & Loss'!K10+'Profit & Loss'!K9)*2/(J4+J5+J6+K4+K5+K6),"") -> 0.18018097

Sheet Cash Flow
A1: ='Balance Sheet'!A1 -> AVENUE SUPERMARTS LTD | E1: =UPDATE | J1: SCREENER.IN
A3: Narration | B3: ='Data Sheet'!B81 -> 42460 | C3: ='Data Sheet'!C81 -> 42825 | D3: ='Data Sheet'!D81 -> 43190 | E3: ='Data Sheet'!E81 -> 43555 | F3: ='Data Sheet'!F81 -> 43921 | G3: ='Data Sheet'!G81 -> 44286 | H3: ='Data Sheet'!H81 -> 44651 | I3: ='Data Sheet'!I81 -> 45016 | ... K3: ='Data Sheet'!K81 -> 45747
A4: Cash from Operating Activity | B4: ='Data Sheet'!B82 -> 433.47 | C4: ='Data Sheet'!C82 -> 455.28 | D4: ='Data Sheet'!D82 -> 729.99 | E4: ='Data Sheet'!E82 -> 806.84 | F4: ='Data Sheet'!F82 -> 1280.14 | G4: ='Data Sheet'!G82 -> 1375.14 | H4: ='Data Sheet'!H82 -> 1372.35 | I4: ='Data Sheet'!I82 -> 2630.27 | ... K4: ='Data Sheet'!K82 -> 2462.97
A5: Cash from Investing Activity | B5: ='Data Sheet'!B83 -> -632.89 | C5: ='Data Sheet'!C83 -> -2481.61 | D5: ='Data Sheet'!D83 -> 463.55 | E5: ='Data Sheet'!E83 -> -958.37 | F5: ='Data Sheet'!F83 -> -4656.56 | G5: ='Data Sheet'!G83 -> -1110 | H5: ='Data Sheet'!H83 -> -1289.49 | I5: ='Data Sheet'!I83 -> -2313.1 | ... K5: ='Data Sheet'!K83 -> -2185.31
A6: Cash from Financing Activity | B6: ='Data Sheet'!B84 -> 196.44 | C6: ='Data Sheet'!C84 -> 2025.26 | D6: ='Data Sheet'!D84 -> -1159.06 | E6: ='Data Sheet'!E84 -> 208.98 | F6: ='Data Sheet'!F84 -> 3357.42 | G6: ='Data Sheet'!G84 -> -179.5 | H6: ='Data Sheet'!H84 -> -179.24 | I6: ='Data Sheet'!I84 -> -205.14 | ... K6: ='Data Sheet'!K84 -> -259.3
A7: Net Cash Flow | B7: ='Data Sheet'!B85 -> -2.98 | C7: ='Data Sheet'!C85 -> -1.07 | D7: ='Data Sheet'!D85 -> 34.48 | E7: ='Data Sheet'!E85 -> 57.45 | F7: ='Data Sheet'!F85 -> -19 | G7: ='Data Sheet'!G85 -> 85.64 | H7: ='Data Sheet'!H85 -> -96.38 | I7: ='Data Sheet'!I85 -> 112.03 | ... K7: ='Data Sheet'!K85 -> 18.36

Sheet Data Sheet
A1: COMPANY NAME | B1: AVENUE SUPERMARTS LTD | E1: =IF(B2<>B3, "A NEW VERSION OF THE WORKSHEET IS AVAILABLE", "")
A2: LATEST VERSION | B2: 2.1 | E2: PLEASE DO NOT MAKE ANY CHANGES TO THIS SHEET
A3: CURRENT VERSION | B3: 2.1
A5: META
A6: Number of shares | B6: =IF(B9>0, B9/B8, 0) -> 65.073308
A7: Face Value | B7: 10
A8: Current Price | B8: 4358.2
A9: Market Capitalization | B9: 283602.49
A15: PROFIT & LOSS
A16: Report Date | B16: 42460 | C16: 42825 | D16: 43190 | E16: 43555 | F16: 43921 | G16: 44286 | H16: 44651 | I16: 45016 | J16: 45382 | K16: 45747
A17: Sales | B17: 8583.76 | C17: 11897.7 | D17: 15033.2 | E17: 20004.52 | F17: 24870.2 | G17: 24143.06 | H17: 30976.27 | I17: 42839.56 | J17: 50788.83 | K17: 59358.05
A18: Raw Material Cost | B18: 7435.62 | C18: 10357.25 | D18: 12846.95 | E18: 17445.49 | F18: 21441.68 | G18: 20855.56 | H18: 26891.77 | I18: 36884.77 | J18: 43958.31 | K18: 51668.76
A19: Change in Inventory | B19: 132.08 | C19: 276.22 | D19: 211.31 | E19: 444.65 | F19: 338.75 | G19: 300.88 | H19: 494.38 | I19: 500.82 | J19: 683.77 | K19: 1117.06
A20: Power and Fuel | B20: 79.24 | C20: 99.41 | D20: 121.26 | E20: 152.8 | F20: 188.24 | G20: 174.2 | H20: 207.86 | I20: 314.62 | J20: 376.59 | K20: 447.75
A21: Other Mfr. Exp | B21: 241.36 | C21: 332.9 | D21: 373.72 | E21: 499.72 | F21: 645.96 | G21: 746.43 | H21: 805.85 | I21: 1116.56 | J21: 1323.43 | K21: 1751.85
A22: Employee Cost | B22: 149.04 | C22: 192.67 | D22: 283.14 | E22: 356.17 | F22: 457.14 | G22: 537.58 | H22: 617.36 | I22: 748.16 | J22: 907.82 | K22: 1167.47
A23: Selling and admin | B23: 647.37 | C23: 71.24 | D23: 96 | E23: 135.84 | F23: 119.23 | G23: 108.69 | H23: 143.41 | I23: 212.04 | J23: 274.43 | K23: 312.48
A24: Other Expenses | B24: -501.25 | C24: 151.27 | D24: 170.58 | E24: 225.84 | F24: 228.39 | G24: 276.65 | H24: 302.05 | I24: 425.46 | J24: 526.38 | K24: 632.29
A25: Other Income | B25: 17.02 | C25: 27.7 | D25: 87.75 | E25: 48.33 | F25: 59.99 | G25: 194.43 | H25: 113.64 | I25: 127.6 | J25: 144.58 | K25: 117.13
A26: Depreciation | B26: 98.43 | C26: 127.82 | D26: 159 | E26: 212.49 | F26: 374.41 | G26: 414.16 | H26: 498.08 | I26: 638.87 | J26: 730.76 | K26: 869.52
A27: Interest | B27: 91.34 | C27: 121.98 | D27: 59.54 | E27: 47.21 | F27: 69.12 | G27: 41.65 | H27: 53.79 | I27: 67.41 | J27: 58.13 | K27: 69.45
... A30: Net profit | B30: 320.24 | C30: 478.75 | D30: 806.26 | E30: 902.54 | F30: 1301.08 | G30: 1099.49 | H30: 1492.55 | I30: 2378.51 | J30: 2536.17 | K30: 2708.02
A31: Dividend Amount
A32: EBITDA | B32: =B30+B27+B29+B26 -> 681.48 | C32: =C30+C27+C29+C26 -> 996.83 | D32: =D30+D27+D29+D26 -> 1440.59 | E32: =E30+E27+E29+E26 -> 1681.72 | F32: =F30+F27+F29+F26 -> 2188.4 | G32: =G30+G27+G29+G26 -> 1939.32 | H32: =H30+H27+H29+H26 -> 2616.14 | I32: =I30+I27+I29+I26 -> 3766.54 | ... K32: =K30+K27+K29+K26 -> 4612.21
A40: Quarters
A41: Report Date | B41: 45016 | C41: 45107 | D41: 45199 | E41: 45291 | F41: 45382 | G41: 45473 | H41: 45565 | I41: 45657 | J41: 45747 | K41: 45838
A42: Sales | B42: 10594.11 | C42: 11865.44 | D42: 12624.37 | E42: 13572.47 | F42: 12726.55 | G42: 14069.14 | H42: 14444.5 | I42: 15972.55 | J42: 14871.86 | K42: 16359.7
A43: Expenses | B43: 9822.6 | C43: 10830.17 | D43: 11619.4 | E43: 12452.58 | F43: 11782.91 | G43: 12847.89 | H43: 13350.73 | I43: 14755.31 | J43: 13916.79 | K43: 15060.66
A44: Other Income | B44: 33.07 | C44: 38.74 | D44: 36.92 | E44: 32.92 | F44: 37.87 | G44: 41.6 | H44: 33.52 | I44: 24.14 | J44: 25.05 | K44: 19.43
A45: Depreciation | B45: 164.08 | C45: 162.18 | D45: 174.36 | E45: 189.33 | F45: 204.89 | G45: 192.76 | H45: 207.78 | I45: 228.12 | J45: 240.86 | K45: 231.7
A46: Interest | B46: 15.53 | C46: 14.57 | D46: 15.59 | E46: 14.55 | F46: 13.42 | G46: 15.96 | H46: 16.32 | I46: 18.21 | J46: 18.96 | K46: 29.3
A47: Profit before tax | B47: 624.97 | C47: 897.26 | D47: 851.94 | E47: 948.93 | F47: 763.2 | G47: 1054.13 | H47: 903.19 | I47: 995.05 | J47: 720.3 | K47: 1057.47
A48: Tax | B48: 164.87 | C48: 238.55 | D48: 228.59 | E48: 258.52 | F48: 200.06 | G48: 280.45 | H48: 243.75 | I48: 271.51 | J48: 169.51 | K48: 284.66
A49: Net profit | B49: 460.13 | C49: 658.75 | D49: 623.56 | E49: 690.61 | F49: 563.25 | G49: 773.82 | H49: 659.58 | I49: 723.72 | J49: 550.9 | K49: 772.97
A50: Operating Profit | B50: 771.51 | C50: 1035.27 | D50: 1004.97 | E50: 1119.89 | F50: 943.64 | G50: 1221.25 | H50: 1093.77 | I50: 1217.24 | J50: 955.07 | K50: 1299.04
A55: BALANCE SHEET
A56: Report Date | B56: 42460 | C56: 42825 | D56: 43190 | E56: 43555 | F56: 43921 | G56: 44286 | H56: 44651 | I56: 45016 | J56: 45382 | K56: 45747
A57: Equity Share Capital | B57: 561.54 | C57: 624.08 | D57: 624.08 | E57: 624.08 | F57: 647.77 | G57: 647.77 | H57: 647.77 | I57: 648.26 | J57: 650.73 | K57: 650.73
A58: Reserves | B58: 958.9 | C58: 3217.7 | D58: 4044.97 | E58: 4963.37 | F58: 10431.97 | G58: 11535.94 | H58: 13029.87 | I58: 15430.44 | J58: 18047.09 | K58: 20777.02
A59: Borrowings | B59: 1192.34 | C59: 1497.32 | D59: 439.25 | E59: 700.15 | F59: 333.19 | G59: 392.71 | H59: 646.94 | I59: 642.98 | J59: 592.16 | K59: 819.62
A60: Other Liabilities | B60: 388.78 | C60: 480.18 | D60: 539.92 | E60: 717.9 | F60: 663.23 | G60: 1078.63 | H60: 1146.4 | I60: 1382.84 | J60: 1882.5 | K60: 2065.41
A61: Total | B61: 3101.56 | C61: 5819.28 | D61: 5648.22 | E61: 7005.5 | F61: 12076.16 | G61: 13655.05 | H61: 15470.98 | I61: 18104.52 | J61: 21172.48 | K61: 24312.78
A62: Net Block | B62: 2093.52 | C62: 2577.75 | D62: 3399.97 | E62: 4400.37 | F62: 5948.03 | G62: 7008.8 | H62: 9260.02 | I62: 11340.48 | J62: 13415 | K62: 16206.46
A63: Capital Work in Progress | B63: 81.69 | C63: 152.89 | D63: 147.07 | E63: 376.84 | F63: 364.4 | G63: 1019.59 | H63: 1129.34 | I63: 829.16 | J63: 935.22 | K63: 1099.35
A64: Investments | B64: 29.33 | C64: 25.69 | D64: 68.18 | E64: 16.53 | F64: 14.68 | G64: 2.95 | H64: 5.94 | I64: 202.2 | J64: 106.67 | K64: 3.26
A65: Other Assets | B65: 897.02 | C65: 3062.95 | D65: 2033 | E65: 2211.76 | F65: 5749.05 | G65: 5623.71 | H65: 5075.68 | I65: 5732.68 | J65: 6715.59 | K65: 7003.71
A66: Total | B66: 3101.56 | C66: 5819.28 | D66: 5648.22 | E66: 7005.5 | F66: 12076.16 | G66: 13655.05 | H66: 15470.98 | I66: 18104.52 | J66: 21172.48 | K66: 24312.78
A67: Receivables | B67: 8.42 | C67: 21 | D67: 33.52 | E67: 64.37 | F67: 19.55 | G67: 43.58 | H67: 66.89 | I67: 62.16 | J67: 166.37 | K67: 153.79
... A70: No. of Equity Shares | B70: 561542680 | C70: 624084486 | D70: 624084486 | E70: 624084486 | F70: 647774691 | G70: 647774691 | H70: 647774691 | I70: 648263978 | J70: 650733068 | K70: 650733068
A71: New Bonus Shares
A72: Face value | B72: 10 | C72: 10 | D72: 10 | E72: 10 | F72: 10 | G72: 10 | H72: 10 | I72: 10 | J72: 10 | K72: 10
A75: Total Asset | B75: =B66 -> 3101.56 | C75: =C66 -> 5819.28 | D75: =D66 -> 5648.22 | E75: =E66 -> 7005.5 | F75: =F66 -> 12076.16 | G75: =G66 -> 13655.05 | H75: =H66 -> 15470.98 | I75: =I66 -> 18104.52 | ... K75: =K66 -> 24312.78
A80: CASH FLOW:
A81: Report Date | B81: 42460 | C81: 42825 | D81: 43190 | E81: 43555 | F81: 43921 | G81: 44286 | H81: 44651 | I81: 45016 | J81: 45382 | K81: 45747
A82: Cash from Operating Activity | B82: 433.47 | C82: 455.28 | D82: 729.99 | E82: 806.84 | F82: 1280.14 | G82: 1375.14 | H82: 1372.35 | I82: 2630.27 | J82: 2745.84 | K82: 2462.97
A83: Cash from Investing Activity | B83: -632.89 | C83: -2481.61 | D83: 463.55 | E83: -958.37 | F83: -4656.56 | G83: -1110 | H83: -1289.49 | I83: -2313.1 | J83: -2468.23 | K83: -2185.31
A84: Cash from Financing Activity | B84: 196.44 | C84: 2025.26 | D84: -1159.06 | E84: 208.98 | F84: 3357.42 | G84: -179.5 | H84: -179.24 | I84: -205.14 | J84: -147.64 | K84: -259.3
A85: Net Cash Flow | B85: -2.98 | C85: -1.07 | D85: 34.48 | E85: 57.45 | F85: -19 | G85: 85.64 | H85: -96.38 | I85: 112.03 | J85: 129.97 | K85: 18.36
A90: PRICE: | C90: 637.85 | D90: 1324.8 | E90: 1471.1 | F90: 2187.5 | G90: 2859.05 | H90: 4003.35 | I90: 3401.05 | J90: 4525.6 | K90: 4083.2
A92: DERIVED:
A93: Adjusted Equity Shares in Cr | B93: 56.15 | C93: 62.41 | D93: 62.41 | E93: 62.41 | F93: 64.78 | G93: 64.78 | H93: 64.78 | I93: 64.83 | J93: 65.07 | K93: 65.07

Sheet HistoricaIFS
B2: ="Historial Financial Statement - "&'Data Sheet'!B1 -> Historial Financial Statement - AVENUE SUPERMARTS LTD
B3: Years | C3: ='Data Sheet'!B16 -> 42460 | D3: ='Data Sheet'!C16 -> 42825 | E3: ='Data Sheet'!D16 -> 43190 | F3: ='Data Sheet'!E16 -> 43555 | G3: ='Data Sheet'!F16 -> 43921 | H3: ='Data Sheet'!G16 -> 44286 | I3: ='Data Sheet'!H16 -> 44651 | J3: ='Data Sheet'!I16 -> 45016 | ... L3: ='Data Sheet'!K16 -> 45747 | M3: LTM
A4: # | B4: Income Statement
B5: Sales | C5: =IFERROR('Data Sheet'!B17,0) -> 8583.76 | D5: =IFERROR('Data Sheet'!C17,0) -> 11897.7 | E5: =IFERROR('Data Sheet'!D17,0) -> 15033.2 | F5: =IFERROR('Data Sheet'!E17,0) -> 20004.52 | G5: =IFERROR('Data Sheet'!F17,0) -> 24870.2 | H5: =IFERROR('Data Sheet'!G17,0) -> 24143.06 | I5: =IFERROR('Data Sheet'!H17,0) -> 30976.27 | J5: =IFERROR('Data Sheet'!I17,0) -> 42839.56 | ... L5: =IFERROR('Data Sheet'!K17,0) -> 59358.05 | M5: =IFERROR(SUM('Data Sheet'!H42:K42),0) -> 61648.61
B6: Sales Growth | C6: - | D6: =D5/C5-1 -> 0.38607091 | E6: =E5/D5-1 -> 0.26353833 | F6: =F5/E5-1 -> 0.33068941 | G6: =G5/F5-1 -> 0.24322903 | H6: =H5/G5-1 -> -0.029237401 | I6: =I5/H5-1 -> 0.28302999 | J6: =J5/I5-1 -> 0.38297994 | K6: =K5/J5-1 -> 0.1855591 | ... M6: =M5/L5-1 -> 0.038588869
B8: COGS | C8: =IFERROR(SUM('Data Sheet'!B18,'Data Sheet'!B20:B22)-1*'Data Sheet'!B19,0) -> 7773.18 | D8: =IFERROR(SUM('Data Sheet'!C18,'Data Sheet'!C20:C22)-1*'Data Sheet'!C19,0) -> 10706.01 | E8: =IFERROR(SUM('Data Sheet'!D18,'Data Sheet'!D20:D22)-1*'Data Sheet'!D19,0) -> 13413.76 | F8: =IFERROR(SUM('Data Sheet'!E18,'Data Sheet'!E20:E22)-1*'Data Sheet'!E19,0) -> 18009.53 | G8: =IFERROR(SUM('Data Sheet'!F18,'Data Sheet'!F20:F22)-1*'Data Sheet'!F19,0) -> 22394.27 | H8: =IFERROR(SUM('Data Sheet'!G18,'Data Sheet'!G20:G22)-1*'Data Sheet'!G19,0) -> 22012.89 | I8: =IFERROR(SUM('Data Sheet'!H18,'Data Sheet'!H20:H22)-1*'Data Sheet'!H19,0) -> 28028.46 | J8: =IFERROR(SUM('Data Sheet'!I18,'Data Sheet'!I20:I22)-1*'Data Sheet'!I19,0) -> 38563.29 | ... L8: =IFERROR(SUM('Data Sheet'!K18,'Data Sheet'!K20:K22)-1*'Data Sheet'!K19,0) -> 53918.77 | M8: =IFERROR(SUM('Data Sheet'!H43:K43),0) -> 57083.49
B9: Gross Margine(COGS % Sales) | C9: =C8/C5 -> 0.90556819 | D9: =D8/D5 -> 0.89983862 | E9: =E8/E5 -> 0.89227576 | F9: =F8/F5 -> 0.90027304 | G9: =G8/G5 -> 0.90044592 | H9: =H8/H5 -> 0.91176885 | I9: =I8/I5 -> 0.90483651 | J9: =J8/J5 -> 0.90017941 | ... M9: =M8/M5 -> 0.92594934
B11: Gross Profit | C11: =C5-C8 -> 810.58 | D11: =D5-D8 -> 1191.69 | E11: =E5-E8 -> 1619.44 | F11: =F5-F8 -> 1994.99 | G11: =G5-G8 -> 2475.93 | H11: =H5-H8 -> 2130.17 | I11: =I5-I8 -> 2947.81 | J11: =J5-J8 -> 4276.27 | ... M11: =M5-M8 -> 4565.12
B12: Gross Profit % Sales | C12: =C11/C5 -> 0.094431811 | D12: =D11/D5 -> 0.10016138 | E12: =E11/E5 -> 0.10772424 | F12: =F11/F5 -> 0.099726962 | G12: =G11/G5 -> 0.099554085 | H12: =H11/H5 -> 0.088231152 | I12: =I11/I5 -> 0.095163491 | J12: =J11/J5 -> 0.099820586 | ... M12: =M11/M5 -> 0.074050656
B14: Selling & Gernal Expenses | C14: =IFERROR(SUM('Data Sheet'!B23:B24),0) -> 146.12 | D14: =IFERROR(SUM('Data Sheet'!C23:C24),0) -> 222.51 | E14: =IFERROR(SUM('Data Sheet'!D23:D24),0) -> 266.58 | F14: =IFERROR(SUM('Data Sheet'!E23:E24),0) -> 361.68 | G14: =IFERROR(SUM('Data Sheet'!F23:F24),0) -> 347.62 | H14: =IFERROR(SUM('Data Sheet'!G23:G24),0) -> 385.34 | I14: =IFERROR(SUM('Data Sheet'!H23:H24),0) -> 445.46 | J14: =IFERROR(SUM('Data Sheet'!I23:I24),0) -> 637.5 | ... L14: =IFERROR(SUM('Data Sheet'!K23:K24),0) -> 944.77
B15: S & G Exp % Sales | C15: =C14/C5 -> 0.017022843 | D15: =D14/D5 -> 0.018701934 | E15: =E14/E5 -> 0.017732752 | F15: =F14/F5 -> 0.018079914 | G15: =G14/G5 -> 0.013977371 | H15: =H14/H5 -> 0.015960694 | I15: =I14/I5 -> 0.014380686 | J15: =J14/J5 -> 0.014881105 | ... M15: =M14/M5 -> 0
P16: =D17-D23 -> 841.36
B17: EBITDA | C17: =C11-C14 -> 664.46 | D17: =D11-D14 -> 969.18 | E17: =E11-E14 -> 1352.86 | F17: =F11-F14 -> 1633.31 | G17: =G11-G14 -> 2128.31 | H17: =H11-H14 -> 1744.83 | I17: =I11-I14 -> 2502.35 | J17: =J11-J14 -> 3638.77 | ... M17: =M11-M14 -> 4565.12
B18: EBITDA % Sales | C18: =C17/C5 -> 0.077408968 | D18: =D17/D5 -> 0.081459442 | E18: =E17/E5 -> 0.089991486 | F18: =F17/F5 -> 0.081647048 | G18: =G17/G5 -> 0.085576714 | H18: =H17/H5 -> 0.072270458 | I18: =I17/I5 -> 0.080782806 | J18: =J17/J5 -> 0.084939481 | ... M18: =M17/M5 -> 0.074050656
B20: Interest | C20: ='Data Sheet'!B27 -> 91.34 | D20: ='Data Sheet'!C27 -> 121.98 | E20: ='Data Sheet'!D27 -> 59.54 | F20: ='Data Sheet'!E27 -> 47.21 | G20: ='Data Sheet'!F27 -> 69.12 | H20: ='Data Sheet'!G27 -> 41.65 | I20: ='Data Sheet'!H27 -> 53.79 | J20: ='Data Sheet'!I27 -> 67.41 | ... L20: ='Data Sheet'!K27 -> 69.45 | M20: =IFERROR(SUM('Data Sheet'!H46:K46),0) -> 82.79
B21: Interest % Sales | C21: =C20/C5 -> 0.010641024 | D21: =D20/D5 -> 0.010252402 | E21: =E20/E5 -> 0.0039605673 | F21: =F20/F5 -> 0.0023599666 | G21: =G20/G5 -> 0.0027792298 | H21: =H20/H5 -> 0.0017251334 | I21: =I20/I5 -> 0.0017364905 | J21: =J20/J5 -> 0.0015735456 | ... M21: =M20/M5 -> 0.0013429338
B23: Deprisiation | C23: =IFERROR('Data Sheet'!B26,0) -> 98.43 | D23: =IFERROR('Data Sheet'!C26,0) -> 127.82 | E23: =IFERROR('Data Sheet'!D26,0) -> 159 | F23: =IFERROR('Data Sheet'!E26,0) -> 212.49 | G23: =IFERROR('Data Sheet'!F26,0) -> 374.41 | H23: =IFERROR('Data Sheet'!G26,0) -> 414.16 | I23: =IFERROR('Data Sheet'!H26,0) -> 498.08 | J23: =IFERROR('Data Sheet'!I26,0) -> 638.87 | ... L23: =IFERROR('Data Sheet'!K26,0) -> 869.52 | M23: =IFERROR(SUM('Data Sheet'!H45:K45),0) -> 908.46
B24: Deprisiation % Sales | C24: =C23/C5 -> 0.011467003 | D24: =D23/D5 -> 0.010743253 | E24: =E23/E5 -> 0.01057659 | F24: =F23/F5 -> 0.010622099 | G24: =G23/G5 -> 0.015054563 | H24: =H23/H5 -> 0.017154412 | I24: =I23/I5 -> 0.016079405 | J24: =J23/J5 -> 0.014913085 | ... M24: =M23/M5 -> 0.014736099
B26: EBT | C26: =IFERROR(C17-SUM(C20,C23),0) -> 474.69 | D26: =IFERROR(D17-SUM(D20,D23),0) -> 719.38 | E26: =IFERROR(E17-SUM(E20,E23),0) -> 1134.32 | F26: =IFERROR(F17-SUM(F20,F23),0) -> 1373.61 | G26: =IFERROR(G17-SUM(G20,G23),0) -> 1684.78 | H26: =IFERROR(H17-SUM(H20,H23),0) -> 1289.02 | I26: =IFERROR(I17-SUM(I20,I23),0) -> 1950.48 | J26: =IFERROR(J17-SUM(J20,J23),0) -> 2932.49 | ... M26: =IFERROR(M17-SUM(M20,M23),0) -> 3573.87 | O26: =L26-K26-1 -> 237.79
B27: EBT % Sales | C27: =C26/C5 -> 0.05530094 | D27: =D26/D5 -> 0.060463787 | E27: =E26/E5 -> 0.075454328 | F27: =F26/F5 -> 0.068664982 | G27: =G26/G5 -> 0.067742921 | H27: =H26/H5 -> 0.053390912 | I27: =I26/I5 -> 0.06296691 | J27: =J26/J5 -> 0.068452851 | ... M27: =M26/M5 -> 0.057971623
B29: TAX | C29: ='Data Sheet'!B29 -> 171.47 | D29: ='Data Sheet'!C29 -> 268.28 | E29: ='Data Sheet'!D29 -> 415.79 | F29: ='Data Sheet'!E29 -> 519.48 | G29: ='Data Sheet'!F29 -> 443.79 | H29: ='Data Sheet'!G29 -> 384.02 | I29: ='Data Sheet'!H29 -> 571.72 | J29: ='Data Sheet'!I29 -> 681.75 | ... L29: ='Data Sheet'!K29 -> 965.22 | M29: =IFERROR(SUM('Data Sheet'!H48:K48),0) -> 969.43
B30: TAX % Sales | C30: =C29/C5 -> 0.019976094 | D30: =D29/D5 -> 0.022548896 | E30: =E29/E5 -> 0.027658117 | F30: =F29/F5 -> 0.025968131 | G30: =G29/G5 -> 0.017844247 | H30: =H29/H5 -> 0.01590602 | I30: =I29/I5 -> 0.018456709 | J30: =J29/J5 -> 0.015914029 | ... M30: =M29/M5 -> 0.015725091
B32: Net Profit | C32: ='Data Sheet'!B30 -> 320.24 | D32: ='Data Sheet'!C30 -> 478.75 | E32: ='Data Sheet'!D30 -> 806.26 | F32: ='Data Sheet'!E30 -> 902.54 | G32: ='Data Sheet'!F30 -> 1301.08 | H32: ='Data Sheet'!G30 -> 1099.49 | I32: ='Data Sheet'!H30 -> 1492.55 | J32: ='Data Sheet'!I30 -> 2378.51 | ... L32: ='Data Sheet'!K30 -> 2708.02 | M32: =IFERROR(SUM('Data Sheet'!H49:K49),0) -> 2707.17
B33: Net Profit % Sales | C33: =IFERROR(C32/C5,0) -> 0.03730766 | D33: =IFERROR(D32/D5,0) -> 0.04023887 | E33: =IFERROR(E32/E5,0) -> 0.053631961 | F33: =IFERROR(F32/F5,0) -> 0.045116804 | G33: =IFERROR(G32/G5,0) -> 0.052314819 | H33: =IFERROR(H32/H5,0) -> 0.045540623 | I33: =IFERROR(I32/I5,0) -> 0.048183658 | J33: =IFERROR(J32/J5,0) -> 0.055521345 | ... M33: =IFERROR(M32/M5,0) -> 0.043912912
B35: No Of Equity Share | C35: =IFERROR('Data Sheet'!B93,0) -> 56.15 | D35: =IFERROR('Data Sheet'!C93,0) -> 62.41 | E35: =IFERROR('Data Sheet'!D93,0) -> 62.41 | F35: =IFERROR('Data Sheet'!E93,0) -> 62.41 | G35: =IFERROR('Data Sheet'!F93,0) -> 64.78 | H35: =IFERROR('Data Sheet'!G93,0) -> 64.78 | I35: =IFERROR('Data Sheet'!H93,0) -> 64.78 | J35: =IFERROR('Data Sheet'!I93,0) -> 64.83 | ... L35: =IFERROR('Data Sheet'!K93,0) -> 65.07
B37: EPS | C37: =IFERROR(C32/C35,0) -> 5.7032947 | D37: =IFERROR(D32/D35,0) -> 7.6710463 | E37: =IFERROR(E32/E35,0) -> 12.918763 | F37: =IFERROR(F32/F35,0) -> 14.461465 | G37: =IFERROR(G32/G35,0) -> 20.084594 | H37: =IFERROR(H32/H35,0) -> 16.972677 | I37: =IFERROR(I32/I35,0) -> 23.04029 | J37: =IFERROR(J32/J35,0) -> 36.688416 | ... M37: =IFERROR(M32/M35,0) -> 0
B38: EPS Growth % | D38: =IFERROR(D37/C37-1,0) -> 0.34502014 | E38: =IFERROR(E37/D37-1,0) -> 0.68409399 | F38: =IFERROR(F37/E37-1,0) -> 0.11941557 | G38: =IFERROR(G37/F37-1,0) -> 0.38883541 | H38: =IFERROR(H37/G37-1,0) -> -0.15494051 | I38: =IFERROR(I37/H37-1,0) -> 0.35749302 | J38: =IFERROR(J37/I37-1,0) -> 0.5923591 | K38: =IFERROR(K37/J37-1,0) -> 0.062352378 | ... M38: =IFERROR(M37/L37-1,0) -> -1
B40: Dividend per Share | C40: =IFERROR('Data Sheet'!B31/HistoricaIFS!C35,0) -> 0 | D40: =IFERROR('Data Sheet'!C31/HistoricaIFS!D35,0) -> 0 | E40: =IFERROR('Data Sheet'!D31/HistoricaIFS!E35,0) -> 0 | F40: =IFERROR('Data Sheet'!E31/HistoricaIFS!F35,0) -> 0 | G40: =IFERROR('Data Sheet'!F31/HistoricaIFS!G35,0) -> 0 | H40: =IFERROR('Data Sheet'!G31/HistoricaIFS!H35,0) -> 0 | I40: =IFERROR('Data Sheet'!H31/HistoricaIFS!I35,0) -> 0 | J40: =IFERROR('Data Sheet'!I31/HistoricaIFS!J35,0) -> 0 | ... M40: =IFERROR('Data Sheet'!L31/HistoricaIFS!M35,0) -> 0
B41: Dividend Payout Ratio | C41: =C40/C37 -> 0 | D41: =D40/D37 -> 0 | E41: =E40/E37 -> 0 | F41: =F40/F37 -> 0 | G41: =G40/G37 -> 0 | H41: =H40/H37 -> 0 | I41: =I40/I37 -> 0 | J41: =J40/J37 -> 0 | ... L41: =L40/L37 -> 0
B43: Retained Earning | C43: =IFERROR(IF(C37>C40,1-C40,0),0) -> 1 | D43: =IFERROR(IF(D37>D40,1-D40,0),0) -> 1 | E43: =IFERROR(IF(E37>E40,1-E40,0),0) -> 1 | F43: =IFERROR(IF(F37>F40,1-F40,0),0) -> 1 | G43: =IFERROR(IF(G37>G40,1-G40,0),0) -> 1 | H43: =IFERROR(IF(H37>H40,1-H40,0),0) -> 1 | I43: =IFERROR(IF(I37>I40,1-I40,0),0) -> 1 | J43: =IFERROR(IF(J37>J40,1-J40,0),0) -> 1 | ... M43: =IFERROR(IF(M37>M40,1-M40,0),0) -> 0
B46: Balance Sheet
B47: Equity Share Capital | C47: =IFERROR('Data Sheet'!B57,0) -> 561.54 | D47: =IFERROR('Data Sheet'!C57,0) -> 624.08 | E47: =IFERROR('Data Sheet'!D57,0) -> 624.08 | F47: =IFERROR('Data Sheet'!E57,0) -> 624.08 | G47: =IFERROR('Data Sheet'!F57,0) -> 647.77 | H47: =IFERROR('Data Sheet'!G57,0) -> 647.77 | I47: =IFERROR('Data Sheet'!H57,0) -> 647.77 | J47: =IFERROR('Data Sheet'!I57,0) -> 648.26 | ... L47: =IFERROR('Data Sheet'!K57,0) -> 650.73
B48: Reserves | C48: =IFERROR('Data Sheet'!B58,0) -> 958.9 | D48: =IFERROR('Data Sheet'!C58,0) -> 3217.7 | E48: =IFERROR('Data Sheet'!D58,0) -> 4044.97 | F48: =IFERROR('Data Sheet'!E58,0) -> 4963.37 | G48: =IFERROR('Data Sheet'!F58,0) -> 10431.97 | H48: =IFERROR('Data Sheet'!G58,0) -> 11535.94 | I48: =IFERROR('Data Sheet'!H58,0) -> 13029.87 | J48: =IFERROR('Data Sheet'!I58,0) -> 15430.44 | ... L48: =IFERROR('Data Sheet'!K58,0) -> 20777.02
B49: Borrowings | C49: =IFERROR('Data Sheet'!B59,0) -> 1192.34 | D49: =IFERROR('Data Sheet'!C59,0) -> 1497.32 | E49: =IFERROR('Data Sheet'!D59,0) -> 439.25 | F49: =IFERROR('Data Sheet'!E59,0) -> 700.15 | G49: =IFERROR('Data Sheet'!F59,0) -> 333.19 | H49: =IFERROR('Data Sheet'!G59,0) -> 392.71 | I49: =IFERROR('Data Sheet'!H59,0) -> 646.94 | J49: =IFERROR('Data Sheet'!I59,0) -> 642.98 | ... L49: =IFERROR('Data Sheet'!K59,0) -> 819.62
B50: Other Liabilities | C50: =IFERROR('Data Sheet'!B60,0) -> 388.78 | D50: =IFERROR('Data Sheet'!C60,0) -> 480.18 | E50: =IFERROR('Data Sheet'!D60,0) -> 539.92 | F50: =IFERROR('Data Sheet'!E60,0) -> 717.9 | G50: =IFERROR('Data Sheet'!F60,0) -> 663.23 | H50: =IFERROR('Data Sheet'!G60,0) -> 1078.63 | I50: =IFERROR('Data Sheet'!H60,0) -> 1146.4 | J50: =IFERROR('Data Sheet'!I60,0) -> 1382.84 | ... L50: =IFERROR('Data Sheet'!K60,0) -> 2065.41
B51: Total Liablities | C51: =IFERROR('Data Sheet'!B61,0) -> 3101.56 | D51: =IFERROR('Data Sheet'!C61,0) -> 5819.28 | E51: =IFERROR('Data Sheet'!D61,0) -> 5648.22 | F51: =IFERROR('Data Sheet'!E61,0) -> 7005.5 | G51: =IFERROR('Data Sheet'!F61,0) -> 12076.16 | H51: =IFERROR('Data Sheet'!G61,0) -> 13655.05 | I51: =IFERROR('Data Sheet'!H61,0) -> 15470.98 | J51: =IFERROR('Data Sheet'!I61,0) -> 18104.52 | ... L51: =IFERROR('Data Sheet'!K61,0) -> 24312.78
B54: Fix Asset Net Block | C54: =IFERROR('Data Sheet'!B62,0) -> 2093.52 | D54: =IFERROR('Data Sheet'!C62,0) -> 2577.75 | E54: =IFERROR('Data Sheet'!D62,0) -> 3399.97 | F54: =IFERROR('Data Sheet'!E62,0) -> 4400.37 | G54: =IFERROR('Data Sheet'!F62,0) -> 5948.03 | H54: =IFERROR('Data Sheet'!G62,0) -> 7008.8 | I54: =IFERROR('Data Sheet'!H62,0) -> 9260.02 | J54: =IFERROR('Data Sheet'!I62,0) -> 11340.48 | ... L54: =IFERROR('Data Sheet'!K62,0) -> 16206.46
B55: Capital Work in Progress | C55: =IFERROR('Data Sheet'!B63,0) -> 81.69 | D55: =IFERROR('Data Sheet'!C63,0) -> 152.89 | E55: =IFERROR('Data Sheet'!D63,0) -> 147.07 | F55: =IFERROR('Data Sheet'!E63,0) -> 376.84 | G55: =IFERROR('Data Sheet'!F63,0) -> 364.4 | H55: =IFERROR('Data Sheet'!G63,0) -> 1019.59 | I55: =IFERROR('Data Sheet'!H63,0) -> 1129.34 | J55: =IFERROR('Data Sheet'!I63,0) -> 829.16 | ... L55: =IFERROR('Data Sheet'!K63,0) -> 1099.35
B56: Investments | C56: =IFERROR('Data Sheet'!B64,0) -> 29.33 | D56: =IFERROR('Data Sheet'!C64,0) -> 25.69 | E56: =IFERROR('Data Sheet'!D64,0) -> 68.18 | F56: =IFERROR('Data Sheet'!E64,0) -> 16.53 | G56: =IFERROR('Data Sheet'!F64,0) -> 14.68 | H56: =IFERROR('Data Sheet'!G64,0) -> 2.95 | I56: =IFERROR('Data Sheet'!H64,0) -> 5.94 | J56: =IFERROR('Data Sheet'!I64,0) -> 202.2 | ... L56: =IFERROR('Data Sheet'!K64,0) -> 3.26
B57: Other Assets | C57: =IFERROR('Data Sheet'!B65-SUM('Data Sheet'!B67:B69),0) -> 181.81 | D57: =IFERROR('Data Sheet'!C65-SUM('Data Sheet'!C67:C69),0) -> 209.76 | E57: =IFERROR('Data Sheet'!D65-SUM('Data Sheet'!D67:D69),0) -> 275.85 | F57: =IFERROR('Data Sheet'!E65-SUM('Data Sheet'!E67:E69),0) -> 319.67 | G57: =IFERROR('Data Sheet'!F65-SUM('Data Sheet'!F67:F69),0) -> 3674.22 | H57: =IFERROR('Data Sheet'!G65-SUM('Data Sheet'!G67:G69),0) -> 1886.27 | I57: =IFERROR('Data Sheet'!H65-SUM('Data Sheet'!H67:H69),0) -> 1967.55 | J57: =IFERROR('Data Sheet'!I65-SUM('Data Sheet'!I67:I69),0) -> 1018.71 | ... L57: =IFERROR('Data Sheet'!K65-SUM('Data Sheet'!K67:K69),0) -> 1447.35
B58: Total Non Current Asset | C58: =SUM(C54:C57) -> 2386.35 | D58: =SUM(D54:D57) -> 2966.09 | E58: =SUM(E54:E57) -> 3891.07 | F58: =SUM(F54:F57) -> 5113.41 | G58: =SUM(G54:G57) -> 10001.33 | H58: =SUM(H54:H57) -> 9917.61 | I58: =SUM(I54:I57) -> 12362.85 | J58: =SUM(J54:J57) -> 13390.55 | ... L58: =SUM(L54:L57) -> 18756.42
B61: Receivables | C61: =IFERROR('Data Sheet'!B67,0) -> 8.42 | D61: =IFERROR('Data Sheet'!C67,0) -> 21 | E61: =IFERROR('Data Sheet'!D67,0) -> 33.52 | F61: =IFERROR('Data Sheet'!E67,0) -> 64.37 | G61: =IFERROR('Data Sheet'!F67,0) -> 19.55 | H61: =IFERROR('Data Sheet'!G67,0) -> 43.58 | I61: =IFERROR('Data Sheet'!H67,0) -> 66.89 | J61: =IFERROR('Data Sheet'!I67,0) -> 62.16 | ... L61: =IFERROR('Data Sheet'!K67,0) -> 153.79
B62: Inventory | C62: =IFERROR('Data Sheet'!B68,0) -> 671.69 | D62: =IFERROR('Data Sheet'!C68,0) -> 947.9 | E62: =IFERROR('Data Sheet'!D68,0) -> 1163.45 | F62: =IFERROR('Data Sheet'!E68,0) -> 1608.65 | G62: =IFERROR('Data Sheet'!F68,0) -> 1947.4 | H62: =IFERROR('Data Sheet'!G68,0) -> 2248.28 | I62: =IFERROR('Data Sheet'!H68,0) -> 2742.66 | J62: =IFERROR('Data Sheet'!I68,0) -> 3243.48 | ... L62: =IFERROR('Data Sheet'!K68,0) -> 5044.37
B63: Cash & Bank | C63: =IFERROR('Data Sheet'!B69,0) -> 35.1 | D63: =IFERROR('Data Sheet'!C69,0) -> 1884.29 | E63: =IFERROR('Data Sheet'!D69,0) -> 560.18 | F63: =IFERROR('Data Sheet'!E69,0) -> 219.07 | G63: =IFERROR('Data Sheet'!F69,0) -> 107.88 | H63: =IFERROR('Data Sheet'!G69,0) -> 1445.58 | I63: =IFERROR('Data Sheet'!H69,0) -> 298.58 | J63: =IFERROR('Data Sheet'!I69,0) -> 1408.33 | ... L63: =IFERROR('Data Sheet'!K69,0) -> 358.2
B64: Total Current Asset | C64: =IFERROR(SUM(C61:C63),0) -> 715.21 | D64: =IFERROR(SUM(D61:D63),0) -> 2853.19 | E64: =IFERROR(SUM(E61:E63),0) -> 1757.15 | F64: =IFERROR(SUM(F61:F63),0) -> 1892.09 | G64: =IFERROR(SUM(G61:G63),0) -> 2074.83 | H64: =IFERROR(SUM(H61:H63),0) -> 3737.44 | I64: =IFERROR(SUM(I61:I63),0) -> 3108.13 | J64: =IFERROR(SUM(J61:J63),0) -> 4713.97 | ... L64: =IFERROR(SUM(L61:L63),0) -> 5556.36
B66: Total Asset | C66: =C58+C64 -> 3101.56 | D66: =D58+D64 -> 5819.28 | E66: =E58+E64 -> 5648.22 | F66: =F58+F64 -> 7005.5 | G66: =G58+G64 -> 12076.16 | H66: =H58+H64 -> 13655.05 | I66: =I58+I64 -> 15470.98 | J66: =J58+J64 -> 18104.52 | ... L66: =L58+L64 -> 24312.78
B68: Check | C68: =C66=C51 -> TRUE | D68: =D66=D51 -> TRUE | E68: =E66=E51 -> TRUE | F68: =F66=F51 -> TRUE | G68: =G66=G51 -> TRUE | H68: =H66=H51 -> TRUE | I68: =I66=I51 -> TRUE | J68: =J66=J51 -> TRUE | ... L68: =L66=L51 -> TRUE
A71: # | B71: Cash Flow
B72: Operating Activity -
B73: Profit from operations | C73: =IFERROR('Cash Flow Data'!C5,0) -> 356 | D73: =IFERROR('Cash Flow Data'!D5,0) -> 474 | E73: =IFERROR('Cash Flow Data'!E5,0) -> 666 | F73: =IFERROR('Cash Flow Data'!F5,0) -> 984 | G73: =IFERROR('Cash Flow Data'!G5,0) -> 1375 | H73: =IFERROR('Cash Flow Data'!H5,0) -> 1659 | I73: =IFERROR('Cash Flow Data'!I5,0) -> 2149 | J73: =IFERROR('Cash Flow Data'!J5,0) -> 1764 | ... L73: =IFERROR('Cash Flow Data'!L5,0) -> 3659
B74: Receivables | C74: =IFERROR('Cash Flow Data'!C6,0) -> 4 | D74: =IFERROR('Cash Flow Data'!D6,0) -> 2 | E74: =IFERROR('Cash Flow Data'!E6,0) -> -1 | F74: =IFERROR('Cash Flow Data'!F6,0) -> 54 | G74: =IFERROR('Cash Flow Data'!G6,0) -> -13 | H74: =IFERROR('Cash Flow Data'!H6,0) -> -31 | I74: =IFERROR('Cash Flow Data'!I6,0) -> 45 | J74: =IFERROR('Cash Flow Data'!J6,0) -> -24 | ... L74: =IFERROR('Cash Flow Data'!L6,0) -> 5
B75: Inventory | C75: =IFERROR('Cash Flow Data'!C7,0) -> -102 | D75: =IFERROR('Cash Flow Data'!D7,0) -> -161 | E75: =IFERROR('Cash Flow Data'!E7,0) -> -132 | F75: =IFERROR('Cash Flow Data'!F7,0) -> -276 | G75: =IFERROR('Cash Flow Data'!G7,0) -> -212 | H75: =IFERROR('Cash Flow Data'!H7,0) -> -445 | I75: =IFERROR('Cash Flow Data'!I7,0) -> -339 | J75: =IFERROR('Cash Flow Data'!J7,0) -> -301 | ... L75: =IFERROR('Cash Flow Data'!L7,0) -> -501
B76: Payables | C76: =IFERROR('Cash Flow Data'!C8,0) -> 28 | D76: =IFERROR('Cash Flow Data'!D8,0) -> -4 | E76: =IFERROR('Cash Flow Data'!E8,0) -> 72 | F76: =IFERROR('Cash Flow Data'!F8,0) -> 0 | G76: =IFERROR('Cash Flow Data'!G8,0) -> 55 | H76: =IFERROR('Cash Flow Data'!H8,0) -> 146 | I76: =IFERROR('Cash Flow Data'!I8,0) -> -30 | J76: =IFERROR('Cash Flow Data'!J8,0) -> 145 | ... L76: =IFERROR('Cash Flow Data'!L8,0) -> 165
B77: Loans Advances | C77: =IFERROR('Cash Flow Data'!C9,0) -> -18 | D77: =IFERROR('Cash Flow Data'!D9,0) -> -5 | E77: =IFERROR('Cash Flow Data'!E9,0) -> 0 | F77: =IFERROR('Cash Flow Data'!F9,0) -> 0 | G77: =IFERROR('Cash Flow Data'!G9,0) -> 0 | H77: =IFERROR('Cash Flow Data'!H9,0) -> 0 | I77: =IFERROR('Cash Flow Data'!I9,0) -> 0 | J77: =IFERROR('Cash Flow Data'!J9,0) -> 0 | ... L77: =IFERROR('Cash Flow Data'!L9,0) -> 0
B78: Other WC items | C78: =IFERROR('Cash Flow Data'!C10,0) -> 0 | D78: =IFERROR('Cash Flow Data'!D10,0) -> 0 | E78: =IFERROR('Cash Flow Data'!E10,0) -> 0 | F78: =IFERROR('Cash Flow Data'!F10,0) -> -2 | G78: =IFERROR('Cash Flow Data'!G10,0) -> -62 | H78: =IFERROR('Cash Flow Data'!H10,0) -> 52 | I78: =IFERROR('Cash Flow Data'!I10,0) -> 2 | J78: =IFERROR('Cash Flow Data'!J10,0) -> 12 | ... L78: =IFERROR('Cash Flow Data'!L10,0) -> 0
B79: Working capital changes | C79: =IFERROR('Cash Flow Data'!C11,0) -> 6 | D79: =IFERROR('Cash Flow Data'!D11,0) -> 16 | E79: =IFERROR('Cash Flow Data'!E11,0) -> -7 | F79: =IFERROR('Cash Flow Data'!F11,0) -> -46 | G79: =IFERROR('Cash Flow Data'!G11,0) -> -11 | H79: =IFERROR('Cash Flow Data'!H11,0) -> -72 | I79: =IFERROR('Cash Flow Data'!I11,0) -> -54 | J79: =IFERROR('Cash Flow Data'!J11,0) -> 41 | ... L79: =IFERROR('Cash Flow Data'!L11,0) -> 12
B80: Direct taxes | C80: =IFERROR('Cash Flow Data'!C12,0) -> -83 | D80: =IFERROR('Cash Flow Data'!D12,0) -> -152 | E80: =IFERROR('Cash Flow Data'!E12,0) -> -69 | F80: =IFERROR('Cash Flow Data'!F12,0) -> -270 | G80: =IFERROR('Cash Flow Data'!G12,0) -> -243 | H80: =IFERROR('Cash Flow Data'!H12,0) -> -351 | I80: =IFERROR('Cash Flow Data'!I12,0) -> -376 | J80: =IFERROR('Cash Flow Data'!J12,0) -> -127 | ... L80: =IFERROR('Cash Flow Data'!L12,0) -> -320
B81: Cash from Operating Activity - | C81: =C73+C79+C80 -> 279 | D81: =D73+D79+D80 -> 338 | E81: =E73+E79+E80 -> 590 | F81: =F73+F79+F80 -> 668 | G81: =G73+G79+G80 -> 1121 | H81: =H73+H79+H80 -> 1236 | I81: =I73+I79+I80 -> 1719 | J81: =J73+J79+J80 -> 1678 | ... L81: =L73+L79+L80 -> 3351
B83: Investing Activity -
B84: Fixed assets purchased | C84: =IFERROR('Cash Flow Data'!C14,0) -> -270 | D84: =IFERROR('Cash Flow Data'!D14,0) -> -474 | E84: =IFERROR('Cash Flow Data'!E14,0) -> -633 | F84: =IFERROR('Cash Flow Data'!F14,0) -> -2482 | G84: =IFERROR('Cash Flow Data'!G14,0) -> 464 | H84: =IFERROR('Cash Flow Data'!H14,0) -> -958 | I84: =IFERROR('Cash Flow Data'!I14,0) -> -4657 | J84: =IFERROR('Cash Flow Data'!J14,0) -> -1110 | ... L84: =IFERROR('Cash Flow Data'!L14,0) -> -2313
B85: Fixed assets sold | C85: =IFERROR('Cash Flow Data'!C15,0) -> -272 | D85: =IFERROR('Cash Flow Data'!D15,0) -> -477 | E85: =IFERROR('Cash Flow Data'!E15,0) -> 0 | F85: =IFERROR('Cash Flow Data'!F15,0) -> -645 | G85: =IFERROR('Cash Flow Data'!G15,0) -> -916 | H85: =IFERROR('Cash Flow Data'!H15,0) -> -1417 | I85: =IFERROR('Cash Flow Data'!I15,0) -> -1712 | J85: =IFERROR('Cash Flow Data'!J15,0) -> -2029 | ... L85: =IFERROR('Cash Flow Data'!L15,0) -> -2212
B86: Investments purchased | C86: =IFERROR('Cash Flow Data'!C16,0) -> 1 | D86: =IFERROR('Cash Flow Data'!D16,0) -> 0 | E86: =IFERROR('Cash Flow Data'!E16,0) -> 2 | F86: =IFERROR('Cash Flow Data'!F16,0) -> 10 | G86: =IFERROR('Cash Flow Data'!G16,0) -> 7 | H86: =IFERROR('Cash Flow Data'!H16,0) -> 8 | I86: =IFERROR('Cash Flow Data'!I16,0) -> 6 | J86: =IFERROR('Cash Flow Data'!J16,0) -> 2 | ... L86: =IFERROR('Cash Flow Data'!L16,0) -> 5
B87: Investments sold | C87: =IFERROR('Cash Flow Data'!C17,0) -> -644 | D87: =IFERROR('Cash Flow Data'!D17,0) -> -2901 | E87: =IFERROR('Cash Flow Data'!E17,0) -> -638 | F87: =IFERROR('Cash Flow Data'!F17,0) -> 0 | G87: =IFERROR('Cash Flow Data'!G17,0) -> 0 | H87: =IFERROR('Cash Flow Data'!H17,0) -> 0 | I87: =IFERROR('Cash Flow Data'!I17,0) -> 0 | J87: =IFERROR('Cash Flow Data'!J17,0) -> 0 | ... L87: =IFERROR('Cash Flow Data'!L17,0) -> -193
B88: Interest received | C88: =IFERROR('Cash Flow Data'!C18,0) -> 645 | D88: =IFERROR('Cash Flow Data'!D18,0) -> 2904 | E88: =IFERROR('Cash Flow Data'!E18,0) -> 0 | F88: =IFERROR('Cash Flow Data'!F18,0) -> 0 | G88: =IFERROR('Cash Flow Data'!G18,0) -> 1376 | H88: =IFERROR('Cash Flow Data'!H18,0) -> 410 | I88: =IFERROR('Cash Flow Data'!I18,0) -> 232 | J88: =IFERROR('Cash Flow Data'!J18,0) -> 3 | ... L88: =IFERROR('Cash Flow Data'!L18,0) -> 6
B89: Dividends received | C89: =IFERROR('Cash Flow Data'!C19,0) -> 0 | D89: =IFERROR('Cash Flow Data'!D19,0) -> 0 | E89: =IFERROR('Cash Flow Data'!E19,0) -> 3 | F89: =IFERROR('Cash Flow Data'!F19,0) -> 8 | G89: =IFERROR('Cash Flow Data'!G19,0) -> 0 | H89: =IFERROR('Cash Flow Data'!H19,0) -> 0 | I89: =IFERROR('Cash Flow Data'!I19,0) -> 0 | J89: =IFERROR('Cash Flow Data'!J19,0) -> 0 | ... L89: =IFERROR('Cash Flow Data'!L19,0) -> 0
B90: Investment in group cos | C90: =IFERROR('Cash Flow Data'!C20,0) -> 0 | D90: =IFERROR('Cash Flow Data'!D20,0) -> 0 | E90: =IFERROR('Cash Flow Data'!E20,0) -> 1 | F90: =IFERROR('Cash Flow Data'!F20,0) -> 1 | G90: =IFERROR('Cash Flow Data'!G20,0) -> 31 | H90: =IFERROR('Cash Flow Data'!H20,0) -> 36 | I90: =IFERROR('Cash Flow Data'!I20,0) -> 12 | J90: =IFERROR('Cash Flow Data'!J20,0) -> 129 | ... L90: =IFERROR('Cash Flow Data'!L20,0) -> 39
B91: Redemp n Canc of Shares | C91: =IFERROR('Cash Flow Data'!C21,0) -> 0 | D91: =IFERROR('Cash Flow Data'!D21,0) -> 0 | E91: =IFERROR('Cash Flow Data'!E21,0) -> 0 | F91: =IFERROR('Cash Flow Data'!F21,0) -> 0 | G91: =IFERROR('Cash Flow Data'!G21,0) -> 0 | H91: =IFERROR('Cash Flow Data'!H21,0) -> 0 | I91: =IFERROR('Cash Flow Data'!I21,0) -> 0 | J91: =IFERROR('Cash Flow Data'!J21,0) -> 0 | ... L91: =IFERROR('Cash Flow Data'!L21,0) -> 0
B92: Acquisition of companies | C92: =IFERROR('Cash Flow Data'!C22,0) -> 0 | D92: =IFERROR('Cash Flow Data'!D22,0) -> 0 | E92: =IFERROR('Cash Flow Data'!E22,0) -> -14 | F92: =IFERROR('Cash Flow Data'!F22,0) -> -21 | G92: =IFERROR('Cash Flow Data'!G22,0) -> -49 | H92: =IFERROR('Cash Flow Data'!H22,0) -> 0 | I92: =IFERROR('Cash Flow Data'!I22,0) -> 0 | J92: =IFERROR('Cash Flow Data'!J22,0) -> 0 | ... L92: =IFERROR('Cash Flow Data'!L22,0) -> 0
B93: Inter corporate deposits | C93: =IFERROR('Cash Flow Data'!C23,0) -> 0 | D93: =IFERROR('Cash Flow Data'!D23,0) -> 0 | E93: =IFERROR('Cash Flow Data'!E23,0) -> 0 | F93: =IFERROR('Cash Flow Data'!F23,0) -> 0 | G93: =IFERROR('Cash Flow Data'!G23,0) -> 8 | H93: =IFERROR('Cash Flow Data'!H23,0) -> 0 | I93: =IFERROR('Cash Flow Data'!I23,0) -> 0 | J93: =IFERROR('Cash Flow Data'!J23,0) -> 0 | ... L93: =IFERROR('Cash Flow Data'!L23,0) -> 0
B94: Other investing items | C94: =IFERROR('Cash Flow Data'!C24,0) -> 0 | D94: =IFERROR('Cash Flow Data'!D24,0) -> 0 | E94: =IFERROR('Cash Flow Data'!E24,0) -> 14 | F94: =IFERROR('Cash Flow Data'!F24,0) -> -1835 | G94: =IFERROR('Cash Flow Data'!G24,0) -> 7 | H94: =IFERROR('Cash Flow Data'!H24,0) -> 3 | I94: =IFERROR('Cash Flow Data'!I24,0) -> -3194 | J94: =IFERROR('Cash Flow Data'!J24,0) -> 786 | ... L94: =IFERROR('Cash Flow Data'!L24,0) -> 42
B95: Cash from Investing Activity - | C95: =SUM(C84:C94) -> -540 | D95: =SUM(D84:D94) -> -948 | E95: =SUM(E84:E94) -> -1265 | F95: =SUM(F84:F94) -> -4964 | G95: =SUM(G84:G94) -> 928 | H95: =SUM(H84:H94) -> -1918 | I95: =SUM(I84:I94) -> -9313 | J95: =SUM(J84:J94) -> -2219 | ... L95: =SUM(L84:L94) -> -4626
B97: Financing Activity -
B98: Proceeds from shares | C98: =IFERROR('Cash Flow Data'!C26,0) -> 5 | D98: =IFERROR('Cash Flow Data'!D26,0) -> 33 | E98: =IFERROR('Cash Flow Data'!E26,0) -> 0 | F98: =IFERROR('Cash Flow Data'!F26,0) -> 1841 | G98: =IFERROR('Cash Flow Data'!G26,0) -> 0 | H98: =IFERROR('Cash Flow Data'!H26,0) -> 0 | I98: =IFERROR('Cash Flow Data'!I26,0) -> 110 | J98: =IFERROR('Cash Flow Data'!J26,0) -> 0 | ... L98: =IFERROR('Cash Flow Data'!L26,0) -> 15
B99: Redemption of debentures | C99: =IFERROR('Cash Flow Data'!C27,0) -> 0 | D99: =IFERROR('Cash Flow Data'!D27,0) -> 200 | E99: =IFERROR('Cash Flow Data'!E27,0) -> 350 | F99: =IFERROR('Cash Flow Data'!F27,0) -> 250 | G99: =IFERROR('Cash Flow Data'!G27,0) -> 0 | H99: =IFERROR('Cash Flow Data'!H27,0) -> 0 | I99: =IFERROR('Cash Flow Data'!I27,0) -> 300 | J99: =IFERROR('Cash Flow Data'!J27,0) -> 0 | ... L99: =IFERROR('Cash Flow Data'!L27,0) -> 0
B100: Proceeds from borrowings | C100: =IFERROR('Cash Flow Data'!C28,0) -> 0 | D100: =IFERROR('Cash Flow Data'!D28,0) -> 0 | E100: =IFERROR('Cash Flow Data'!E28,0) -> 0 | F100: =IFERROR('Cash Flow Data'!F28,0) -> 0 | G100: =IFERROR('Cash Flow Data'!G28,0) -> -384 | H100: =IFERROR('Cash Flow Data'!H28,0) -> -170 | I100: =IFERROR('Cash Flow Data'!I28,0) -> -512 | J100: =IFERROR('Cash Flow Data'!J28,0) -> -34 | ... L100: =IFERROR('Cash Flow Data'!L28,0) -> 0
B101: Repayment of borrowings | C101: =IFERROR('Cash Flow Data'!C29,0) -> 245 | D101: =IFERROR('Cash Flow Data'!D29,0) -> 295 | E101: =IFERROR('Cash Flow Data'!E29,0) -> -60 | F101: =IFERROR('Cash Flow Data'!F29,0) -> 260 | G101: =IFERROR('Cash Flow Data'!G29,0) -> 0 | H101: =IFERROR('Cash Flow Data'!H29,0) -> 992 | I101: =IFERROR('Cash Flow Data'!I29,0) -> 1100 | J101: =IFERROR('Cash Flow Data'!J29,0) -> 200 | ... L101: =IFERROR('Cash Flow Data'!L29,0) -> 0
B102: Interest paid fin | C102: =IFERROR('Cash Flow Data'!C30,0) -> -130 | D102: =IFERROR('Cash Flow Data'!D30,0) -> -232 | E102: =IFERROR('Cash Flow Data'!E30,0) -> 0 | F102: =IFERROR('Cash Flow Data'!F30,0) -> -155 | G102: =IFERROR('Cash Flow Data'!G30,0) -> -695 | H102: =IFERROR('Cash Flow Data'!H30,0) -> -562 | I102: =IFERROR('Cash Flow Data'!I30,0) -> -1550 | J102: =IFERROR('Cash Flow Data'!J30,0) -> -204 | ... L102: =IFERROR('Cash Flow Data'!L30,0) -> 0
B103: Dividends paid | C103: =IFERROR('Cash Flow Data'!C31,0) -> -54 | D103: =IFERROR('Cash Flow Data'!D31,0) -> -62 | E103: =IFERROR('Cash Flow Data'!E31,0) -> -93 | F103: =IFERROR('Cash Flow Data'!F31,0) -> -120 | G103: =IFERROR('Cash Flow Data'!G31,0) -> -80 | H103: =IFERROR('Cash Flow Data'!H31,0) -> -51 | I103: =IFERROR('Cash Flow Data'!I31,0) -> -98 | J103: =IFERROR('Cash Flow Data'!J31,0) -> -44 | ... L103: =IFERROR('Cash Flow Data'!L31,0) -> -67
B104: Financial liabilities | C104: =IFERROR('Cash Flow Data'!C32,0) -> 0 | D104: =IFERROR('Cash Flow Data'!D32,0) -> 0 | E104: =IFERROR('Cash Flow Data'!E32,0) -> 0 | F104: =IFERROR('Cash Flow Data'!F32,0) -> 0 | G104: =IFERROR('Cash Flow Data'!G32,0) -> 0 | H104: =IFERROR('Cash Flow Data'!H32,0) -> 0 | I104: =IFERROR('Cash Flow Data'!I32,0) -> -70 | J104: =IFERROR('Cash Flow Data'!J32,0) -> -98 | ... L104: =IFERROR('Cash Flow Data'!L32,0) -> -153
B105: Other financing items | C105: =IFERROR('Cash Flow Data'!C33,0) -> 0 | D105: =IFERROR('Cash Flow Data'!D33,0) -> 0 | E105: =IFERROR('Cash Flow Data'!E33,0) -> 0 | F105: =IFERROR('Cash Flow Data'!F33,0) -> 0 | G105: =IFERROR('Cash Flow Data'!G33,0) -> 0 | H105: =IFERROR('Cash Flow Data'!H33,0) -> 0 | I105: =IFERROR('Cash Flow Data'!I33,0) -> 0 | J105: =IFERROR('Cash Flow Data'!J33,0) -> 0 | ... L105: =IFERROR('Cash Flow Data'!L33,0) -> 1
B106: Cash from Financing Activity - | C106: =SUM(C98:C105) -> 66 | D106: =SUM(D98:D105) -> 234 | E106: =SUM(E98:E105) -> 197 | F106: =SUM(F98:F105) -> 2076 | G106: =SUM(G98:G105) -> -1159 | H106: =SUM(H98:H105) -> 209 | I106: =SUM(I98:I105) -> -720 | J106: =SUM(J98:J105) -> -180 | ... L106: =SUM(L98:L105) -> -204
B108: Net Cash Flow | C108: =C81+C106+C95 -> -195 | D108: =D81+D106+D95 -> -376 | E108: =E81+E106+E95 -> -478 | F108: =F81+F106+F95 -> -2220 | G108: =G81+G106+G95 -> 890 | H108: =H81+H106+H95 -> -473 | I108: =I81+I106+I95 -> -8314 | J108: =J81+J106+J95 -> -721 | ... L108: =L81+L106+L95 -> -1479

Sheet Forcasting
B2: FORCASTING
B4: ='Data Sheet'!B1&" - "&'Data Sheet'!A17 -> AVENUE SUPERMARTS LTD - Sales | G4: ='Data Sheet'!B1&" - "&HistoricaIFS!B17 -> AVENUE SUPERMARTS LTD - EBITDA | L4: ='Data Sheet'!B1&" - "&HistoricaIFS!B37 -> AVENUE SUPERMARTS LTD - EPS
B5: Year Weight | C5: Year | D5: Sales | E5: Sales Growth | G5: Year Weight | H5: Year | I5: EBITDA | J5: EBITDA Growth | L5: Year Weight | M5: Year | N5: EPS | O5: EPS Growth
B6: 1 | C6: 2016 | D6: {=TRANSPOSE('Data Sheet'!B17:K17)} -> 8583.76 | G6: 1 | H6: 2016 | I6: {=TRANSPOSE(HistoricaIFS!C17:L17)} -> 664.46 | L6: 1 | M6: 2016 | N6: {=TRANSPOSE(HistoricaIFS!C37:L37)} -> 5.7032947
B7: 2 | C7: 2017 | D7: 11897.7 | E7: =IFERROR(D7/D6-1,0) -> 0.38607091 | G7: 2 | H7: 2017 | I7: 969.18 | J7: =IFERROR(I7/I6-1,0) -> 0.45859796 | L7: 2 | M7: 2017 | N7: 7.6710463 | O7: =IFERROR(N7/N6-1,0) -> 0.34502014
B8: 3 | C8: 2018 | D8: 15033.2 | E8: =IFERROR(D8/D7-1,0) -> 0.26353833 | G8: 3 | H8: 2018 | I8: 1352.86 | J8: =IFERROR(I8/I7-1,0) -> 0.39588105 | L8: 3 | M8: 2018 | N8: 12.918763 | O8: =IFERROR(N8/N7-1,0) -> 0.68409399
B9: 4 | C9: 2019 | D9: 20004.52 | E9: =IFERROR(D9/D8-1,0) -> 0.33068941 | G9: 4 | H9: 2019 | I9: 1633.31 | J9: =IFERROR(I9/I8-1,0) -> 0.20730157 | L9: 4 | M9: 2019 | N9: 14.461465 | O9: =IFERROR(N9/N8-1,0) -> 0.11941557
B10: 5 | C10: 2020 | D10: 24870.2 | E10: =IFERROR(D10/D9-1,0) -> 0.24322903 | G10: 5 | H10: 2020 | I10: 2128.31 | J10: =IFERROR(I10/I9-1,0) -> 0.30306555 | L10: 5 | M10: 2020 | N10: 20.084594 | O10: =IFERROR(N10/N9-1,0) -> 0.38883541
B11: 6 | C11: 2021 | D11: 24143.06 | E11: =IFERROR(D11/D10-1,0) -> -0.029237401 | G11: 6 | H11: 2021 | I11: 1744.83 | J11: =IFERROR(I11/I10-1,0) -> -0.18018052 | L11: 6 | M11: 2021 | N11: 16.972677 | O11: =IFERROR(N11/N10-1,0) -> -0.15494051
B12: 7 | C12: 2022 | D12: 30976.27 | E12: =IFERROR(D12/D11-1,0) -> 0.28302999 | G12: 7 | H12: 2022 | I12: 2502.35 | J12: =IFERROR(I12/I11-1,0) -> 0.43415118 | L12: 7 | M12: 2022 | N12: 23.04029 | O12: =IFERROR(N12/N11-1,0) -> 0.35749302
B13: 8 | C13: 2023 | D13: 42839.56 | E13: =IFERROR(D13/D12-1,0) -> 0.38297994 | G13: 8 | H13: 2023 | I13: 3638.77 | J13: =IFERROR(I13/I12-1,0) -> 0.45414111 | L13: 8 | M13: 2023 | N13: 36.688416 | O13: =IFERROR(N13/N12-1,0) -> 0.5923591
B14: 9 | C14: 2024 | D14: 50788.83 | E14: =IFERROR(D14/D13-1,0) -> 0.1855591 | G14: 9 | H14: 2024 | I14: 4105.64 | J14: =IFERROR(I14/I13-1,0) -> 0.12830434 | L14: 9 | M14: 2024 | N14: 38.976026 | O14: =IFERROR(N14/N13-1,0) -> 0.062352378
B15: 10 | C15: 2025 | D15: 59358.05 | E15: =IFERROR(D15/D14-1,0) -> 0.16872253 | G15: 10 | H15: 2025 | I15: 4494.51 | J15: =IFERROR(I15/I14-1,0) -> 0.094716049 | L15: 10 | M15: 2025 | N15: 41.617028 | O15: =IFERROR(N15/N14-1,0) -> 0.067759653
B16: 11 | C16: 2026 | D16: =FORECAST(B16,D6:D15,B6:B15) -> 58863.729 | E16: =IFERROR(D16/D15-1,0) -> -0.0083277781 | G16: 11 | H16: 2026 | I16: =FORECAST(G16,I6:I15,G6:G15) -> 4659.384 | J16: =IFERROR(I16/I15-1,0) -> 0.03668342 | L16: 11 | M16: 2026 | N16: =FORECAST(L16,N6:N15,L6:L15) -> 44.607736 | O16: =IFERROR(N16/N15-1,0) -> 0.071862605
B17: 12 | C17: 2027 | D17: =FORECAST(B17,D6:D16,B6:B16) -> 64320.859 | E17: =IFERROR(D17/D16-1,0) -> 0.092707852 | G17: 12 | H17: 2027 | I17: =FORECAST(G17,I7:I16,G7:G16) -> 5151.3789 | J17: =IFERROR(I17/I16-1,0) -> 0.10559227 | L17: 12 | M17: 2027 | N17: =FORECAST(L17,N7:N16,L7:L16) -> 49.429469 | O17: =IFERROR(N17/N16-1,0) -> 0.10809186
B18: 13 | C18: 2028 | D18: =FORECAST(B18,D6:D17,B6:B17) -> 69777.989 | E18: =IFERROR(D18/D17-1,0) -> 0.084842304 | G18: 13 | H18: 2028 | I18: =FORECAST(G18,I8:I17,G8:G17) -> 5655.1022 | J18: =IFERROR(I18/I17-1,0) -> 0.097784169 | L18: 13 | M18: 2028 | N18: =FORECAST(L18,N8:N17,L8:L17) -> 54.110999 | O18: =IFERROR(N18/N17-1,0) -> 0.094711326
B19: 14 | C19: 2029 | D19: =FORECAST(B19,D7:D18,B7:B18) -> 76145.401 | E19: =IFERROR(D19/D18-1,0) -> 0.091252442 | G19: 14 | H19: 2029 | I19: =FORECAST(G19,I9:I18,G9:G18) -> 6183.8163 | J19: =IFERROR(I19/I18-1,0) -> 0.093493276 | L19: 14 | M19: 2029 | N19: =FORECAST(L19,N9:N18,L9:L18) -> 59.280638 | O19: =IFERROR(N19/N18-1,0) -> 0.095537675
B20: 15 | C20: 2030 | D20: =FORECAST(B20,D8:D19,B8:B19) -> 82556.685 | E20: =IFERROR(D20/D19-1,0) -> 0.08419791 | G20: 15 | H20: 2030 | I20: =FORECAST(G20,I10:I19,G10:G19) -> 6711.9864 | J20: =IFERROR(I20/I19-1,0) -> 0.085411685 | L20: 15 | M20: 2030 | N20: =FORECAST(L20,N10:N19,L10:L19) -> 64.183371 | O20: =IFERROR(N20/N19-1,0) -> 0.082703776
B22: Arithmatic Mean | C22: =IFERROR(AVERAGE(E6:E15),0) -> 0.24606465
B23: Geometric Mean | C23: =_xlfn.RRI(B15,D6,D15) -> 0.21333355
B25: Standard Deviation | C25: =_xlfn.STDEV.S(E6:E15) -> 0.12875493

Sheet WACC
B2: Weighted Average Cost of Capital
B4: All Figures are in INR Unless satrted otherwise
B6: Peer Comps
J7: Debt / | K7: Debt/ | L7: Leverd | M7: Unleverd
B8: Name Of The Comp | F8: Country | G8: Total Debt | H8: Total Equity | I8: Tax Rate 1 | J8: Equity | K8: Capital | L8: Beta 2 | M8: Beta 3
O9: =G10 -> 819.62
B10: ='Beta - Comp '!C4 -> Avenue Super. | F10: India | G10: ='Beta - Comp '!F4 -> 819.62 | H10: ='Beta - Comp '!E4 -> 261737.44 | I10: 0.3 | J10: =G10/H10 -> 0.0031314588 | K10: =G10/(G10+H10) -> 0.0031216833 | L10: =Beta!M7 -> 1.2414891 | M10: =L10/(1+(1-I10)*J10) -> 1.2387737 | O10: =H10+G10 -> 262557.06
B11: ='Beta - Comp '!C5 -> Trent | F11: India | G11: ='Beta - Comp '!F5 -> 2237.19 | H11: ='Beta - Comp '!E5 -> 183059.4 | I11: 0.3 | J11: =G11/H11 -> 0.012221115 | K11: =G11/(G11+H11) -> 0.012073563 | L11: 1.54 | M11: =L11/(1+(1-I11)*J11) -> 1.5269374
B12: ='Beta - Comp '!C9 -> Vedant Fashions | F12: India | G12: ='Beta - Comp '!F9 -> 482.9 | H12: ='Beta - Comp '!E9 -> 19296.24 | I12: 0.3 | J12: =G12/H12 -> 0.025025601 | K12: =G12/(G12+H12) -> 0.024414611 | L12: 0.61 | M12: =L12/(1+(1-I12)*J12) -> 0.59949804 | O12: =O9/O10 -> 0.0031216833
B13: ='Beta - Comp '!C15 -> Aditya Bir. Fas. | F13: India | G13: ='Beta - Comp '!F15 -> 5016.78 | H13: ='Beta - Comp '!E15 -> 9234.98 | I13: 0.3 | J13: =G13/H13 -> 0.54323669 | K13: =G13/(G13+H13) -> 0.35201126 | L13: 0.93 | M13: =L13/(1+(1-I13)*J13) -> 0.67378332
B14: Metro Brands | F14: India | G14: ='Beta - Comp '!F17 -> 1227.08 | H14: ='Beta - Comp '!E17 -> 32844.94 | I14: 0.3 | J14: =G14/H14 -> 0.037359788 | K14: =G14/(G14+H14) -> 0.036014301 | L14: 0.79 | M14: =L14/(1+(1-I14)*J14) -> 0.76986656
H17: Average | I17: =AVERAGE(I10:I14) -> 0.3 | J17: =AVERAGE(J10:J14) -> 0.12419493 | K17: =AVERAGE(K10:K14) -> 0.085527084 | L17: =AVERAGE(L10:L14) -> 1.0222978 | M17: =AVERAGE(M10:M14) -> 0.9617718
H18: Median | I18: =MEDIAN(I10:I14) -> 0.3 | J18: =MEDIAN(J10:J14) -> 0.025025601 | K18: =MEDIAN(K10:K14) -> 0.024414611 | L18: =MEDIAN(L10:L14) -> 0.93 | M18: =MEDIAN(M10:M14) -> 0.76986656
B21: Cost Of Debt | H21: Cost Of Equity
B23: Pre -Tax Cost Of Debt | E23: 0.084 | H23: Risk Free rate | M23: 0.0739
B24: Tax Rate | E24: 0.3 | H24: Equity Risk Primium | M24: ='Rm '!G7-WACC!M23 -> 0.079448
B25: Post -Tax Cost Of Debt | E25: =E23*(1-E24) -> 0.0588 | H25: Levered Beta 4 | M25: =M34 -> 0.82026839
H26: Cost Of Equity | M26: =M23+M24*M25 -> 0.13906868
B29: Capital Structure | H29: Leveard Beta
D31: Current | E31: Target | H31: Comps Median Unleverad Beta | M31: =M18 -> 0.76986656
B32: Total Debt | C32: =G10 -> 819.62 | D32: =C32/$C$34 -> 0.0031216833 | E32: =K17 -> 0.085527084 | H32: Target Rate /Equity | M32: =E36 -> 0.093526098
B33: Market Capitalization | C33: =H10 -> 261737.44 | D33: =C33/$C$34 -> 0.99687832 | E33: =E34-E32 -> 0.91447292 | H33: =B24 -> Tax Rate | M33: =E24 -> 0.3
B34: Total Capital | C34: =C32+C33 -> 262557.06 | D34: =D32+D33 -> 1 | E34: 1 | H34: Leverad Beta | M34: =M31*(1+(1-M33)*M32) -> 0.82026839
B36: Debt / Equity | D36: =D32/D33 -> 0.0031314588 | E36: =E32/E33 -> 0.093526098
H37: =B2 -> Weighted Average Cost of Capital
B38: 1. Tax Rate considered as Marginal Tax Rate for the country
B39: 2. Levered Beta is based on 2 year Weekly data | H39: Cost Of Debt | M39: =E25 -> 0.0588
B40: 3. Unlevered Beta = Levered Beta/(1+(1-Tax Rate) x Debt/Equity) | H40: Debt Weight | M40: =E32 -> 0.085527084
B41: 3. Levered Beta = Unlevered Beta/(1+(1-Tax Rate) x Debt/Equity)
H42: Cost of Equity | M42: =M26 -> 0.13906868
H43: Equity Weight | M43: =E33 -> 0.91447292
H45: WACC | M45: =(M39*M40)+(M42*M43) -> 0.13220354

Sheet Beta
B2: Avenue Supermart Weekly Report | F2: NIFTY Returns | I2: Beta drifting | M2: Beta
B3: Date | C3: Closing Price | D3: Return | F3: Closing Price | G3: Return
B4: 44249 | C4: 2994.2 | F4: 14529.2 | I4: Leaverged Raw Beta | J4: =M4 -> 1.2414891 | L4: Beta 1 | M4: =SLOPE(D4:D108,G4:G108) -> 1.2414891
B5: 44256 | C5: 3286.1 | D5: 0.0975 | F5: 14938.1 | G5: 0.0281 | I5: Raw Beta Weight | J5: 0.75 | L5: beta2 | M5: =_xlfn.COVARIANCE.S(D4:D108,G4:G108)/_xlfn.VAR.S(G4:G108) -> 1.2414891
B6: 44263 | C6: 3129.4 | D6: -0.0477 | F6: 15031 | G6: 0.0062
B7: 44270 | C7: 2960.3 | D7: -0.054 | F7: 14744 | G7: -0.0191 | I7: Market Raw Beta | J7: 1 | L7: Beta 3 | M7: =J29 -> 1.2414891
B8: 44277 | C8: 2855.2 | D8: -0.0355 | F8: 14507.3 | G8: -0.0161 | I8: Market Beta Weight | J8: 0.25
B9: 44284 | C9: 2912.7 | D9: 0.0201 | F9: 14867.3 | G9: 0.0248
B10: 44291 | C10: 2947.8 | D10: 0.012 | F10: 14834.8 | G10: -0.0022
B11: 44298 | C11: 2919.9 | D11: -0.0094 | F11: 14617.8 | G11: -0.0146 | I11: Adjusted Beta | J11: =(J4*J5)+(J7*J8) -> 1.1811168
B12: 44305 | C12: 2713.7 | D12: -0.0706 | F12: 14341.3 | G12: -0.0189
B13: 44312 | C13: 2852.9 | D13: 0.0513 | F13: 14631.1 | G13: 0.0202
B14: 44319 | C14: 2895.5 | D14: 0.0149 | F14: 14823.2 | G14: 0.0131 | I14: Regression Statistics
B15: 44326 | C15: 2844.6 | D15: -0.0176 | F15: 14677.8 | G15: -0.0098 | I15: Multiple R | J15: 0.51083871
B16: 44333 | C16: 3034.1 | D16: 0.0666 | F16: 15175.3 | G16: 0.0339 | I16: R Square | J16: 0.26095619
B17: 44340 | C17: 3022.1 | D17: -0.004 | F17: 15435.7 | G17: 0.0172 | I17: Adjusted R Square | J17: 0.25371066
B18: 44347 | C18: 3197 | D18: 0.0579 | F18: 15670.3 | G18: 0.0152 | I18: Standard Error | J18: 0.042295755
B19: 44354 | C19: 3175.6 | D19: -0.0067 | F19: 15799.3 | G19: 0.0082 | I19: Observations | J19: 104
B20: 44361 | C20: 3317.7 | D20: 0.0448 | F20: 15683.3 | G20: -0.0073
B21: 44368 | C21: 3315.4 | D21: -0.0007 | F21: 15860.3 | G21: 0.0113 | I21: ANOVA
B22: 44375 | C22: 3314.3 | D22: -0.0003 | F22: 15722.2 | G22: -0.0087 | J22: df | K22: SS | L22: MS | M22: F | N22: Significance F
B23: 44382 | C23: 3377.6 | D23: 0.0191 | F23: 15689.8 | G23: -0.0021 | I23: Regression | J23: 1 | K23: 0.064430448 | L23: 0.064430448 | M23: 36.016175 | N23: 3.0154038e-08
B24: 44389 | C24: 3349.2 | D24: -0.0084 | F24: 15923.4 | G24: 0.0149 | I24: Residual | J24: 102 | K24: 0.18247095 | L24: 0.0017889309
B25: 44396 | C25: 3413.2 | D25: 0.0191 | F25: 15856 | G25: -0.0042 | I25: Total | J25: 103 | K25: 0.2469014
B26: 44403 | C26: 3500.8 | D26: 0.0257 | F26: 15763 | G26: -0.0059
B27: 44410 | C27: 3529.2 | D27: 0.0081 | F27: 16238.2 | G27: 0.0301 | J27: Coefficients | K27: Standard Error | L27: t Stat | M27: P-value | N27: Lower 95% | O27: Upper 95% | P27: Lower 95.0% | Q27: Upper 95.0%
B28: 44417 | C28: 3594.6 | D28: 0.0185 | F28: 16529.1 | G28: 0.0179 | I28: Intercept | J28: 0.00011322271 | K28: 0.0041717746 | L28: 0.027140179 | M28: 0.97840096 | N28: -0.0081614725 | O28: 0.0083879179 | P28: -0.0081614725 | Q28: 0.0083879179
B29: 44424 | C29: 3643.1 | D29: 0.0135 | F29: 16450.5 | G29: -0.0048 | I29: X Variable 1 | J29: 1.2414891 | K29: 0.20686838 | L29: 6.0013477 | M29: 3.0154038e-08 | N29: 0.83116666 | O29: 1.6518116 | P29: 0.83116666 | Q29: 1.6518116
B30: 44431 | C30: 3833.1 | D30: 0.0521 | F30: 16705.2 | G30: 0.0155
B31: 44438 | C31: 3938.9 | D31: 0.0276 | F31: 17323.6 | G31: 0.037
B32: 44445 | C32: 3950.5 | D32: 0.0029 | F32: 17369.3 | G32: 0.0026
B33: 44452 | C33: 4239.6 | D33: 0.0732 | F33: 17585.2 | G33: 0.0124
B34: 44459 | C34: 4422.4 | D34: 0.0431 | F34: 17853.2 | G34: 0.0152
B35: 44466 | C35: 4235.6 | D35: -0.0422 | F35: 17532.1 | G35: -0.018
B36: 44473 | C36: 4408 | D36: 0.0407 | F36: 17895.2 | G36: 0.0207
B37: 44480 | C37: 5323.8 | D37: 0.2078 | F37: 18338.6 | G37: 0.0248
B38: 44487 | C38: 4521.5 | D38: -0.1507 | F38: 18114.9 | G38: -0.0122
B39: 44494 | C39: 4635.5 | D39: 0.0252 | F39: 17671.7 | G39: -0.0245
B40: 44501 | C40: 4783.7 | D40: 0.032 | F40: 17916.8 | G40: 0.0139
B41: 44508 | C41: 5078.5 | D41: 0.0616 | F41: 18102.8 | G41: 0.0104
... B108: 44977 | C108: 3552.9 | D108: 0.0022 | F108: 17844.6 | G108: -0.0056

Sheet Beta  - Comp 
B3: S.No. | C3: Name | D3: CMP Rs. | E3: Mar Cap Rs.Cr. | F3: Debt Rs.Cr. | G3: Debt / Eq
B4: 2 | C4: Avenue Super. | D4: 4021 | E4: 261737.44 | F4: 819.62 | G4: 0.04
B5: 3 | C5: Trent | D5: 5154 | E5: 183059.4 | F5: 2237.19 | G5: 0.41
B6: 5 | C6: Info Edg.(India) | D6: 1457.2 | E6: 94431 | F6: 267.34 | G6: 0.01
B7: 6 | C7: Vishal Mega Mart | D7: 140.01 | E7: 65277.75 | F7: 1729.38 | G7: 0.27
B8: 7 | C8: FSN E-Commerce | D8: 215.62 | E8: 61731.33 | F8: 1320.59 | G8: 1.01
B9: 8 | C9: Vedant Fashions | D9: 794.3 | E9: 19296.24 | F9: 482.9 | G9: 0.27
B10: 9 | C10: Brainbees Solut. | D10: 358.25 | E10: 18650.67 | F10: 1569.93 | G10: 0.33
B11: 10 | C11: A B Lifestyle | D11: 149.77 | E11: 18270.33 | F11: 2932.45 | G11: 2.3
B12: 11 | C12: Indiamart Inter. | D12: 2621 | E12: 15794.78 | F12: 33.04 | G12: 0.02
B13: 12 | C13: Medplus Health | D13: 887.2 | E13: 10615.24 | F13: 1119.8 | G13: 0.64
B14: 13 | C14: Cartrade Tech | D14: 1965.6 | E14: 9322.13 | F14: 131.37 | G14: 0.06
B15: 14 | C15: Aditya Bir. Fas. | D15: 75.67 | E15: 9234.98 | F15: 5016.78 | G15: 0.74
... B17: 16 | C17: Metro Brands | D17: 1205.7 | E17: 32844.94 | F17: 1227.08 | G17: 0.72

Sheet Common Size Statement
B2: ="Common Size"&" "&"-"&'Data Sheet'!B1 -> Common Size -AVENUE SUPERMARTS LTD
B4: Particular | C4: ='Data Sheet'!B56 -> 42460 | D4: ='Data Sheet'!C56 -> 42825 | E4: ='Data Sheet'!D56 -> 43190 | F4: ='Data Sheet'!E56 -> 43555 | G4: ='Data Sheet'!F56 -> 43921 | H4: ='Data Sheet'!G56 -> 44286 | I4: ='Data Sheet'!H56 -> 44651 | J4: ='Data Sheet'!I56 -> 45016 | ... L4: ='Data Sheet'!K56 -> 45747
B5: ='Data Sheet'!A17 -> Sales | C5: ='Data Sheet'!B17/'Data Sheet'!B$17 -> 1 | D5: ='Data Sheet'!C17/'Data Sheet'!C$17 -> 1 | E5: ='Data Sheet'!D17/'Data Sheet'!D$17 -> 1 | F5: ='Data Sheet'!E17/'Data Sheet'!E$17 -> 1 | G5: ='Data Sheet'!F17/'Data Sheet'!F$17 -> 1 | H5: ='Data Sheet'!G17/'Data Sheet'!G$17 -> 1 | I5: ='Data Sheet'!H17/'Data Sheet'!H$17 -> 1 | J5: ='Data Sheet'!I17/'Data Sheet'!I$17 -> 1 | ... L5: ='Data Sheet'!K17/'Data Sheet'!K$17 -> 1
B6: ='Data Sheet'!A18 -> Raw Material Cost | C6: ='Data Sheet'!B18/'Data Sheet'!B$17 -> 0.86624277 | D6: ='Data Sheet'!C18/'Data Sheet'!C$17 -> 0.8705254 | E6: ='Data Sheet'!D18/'Data Sheet'!D$17 -> 0.85457188 | F6: ='Data Sheet'!E18/'Data Sheet'!E$17 -> 0.87207741 | G6: ='Data Sheet'!F18/'Data Sheet'!F$17 -> 0.86214345 | H6: ='Data Sheet'!G18/'Data Sheet'!G$17 -> 0.86383251 | I6: ='Data Sheet'!H18/'Data Sheet'!H$17 -> 0.868141 | J6: ='Data Sheet'!I18/'Data Sheet'!I$17 -> 0.86099787 | ... L6: ='Data Sheet'!K18/'Data Sheet'!K$17 -> 0.87045919
B7: ='Data Sheet'!A19 -> Change in Inventory | C7: ='Data Sheet'!B19/'Data Sheet'!B$17 -> 0.015387196 | D7: ='Data Sheet'!C19/'Data Sheet'!C$17 -> 0.023216252 | E7: ='Data Sheet'!D19/'Data Sheet'!D$17 -> 0.014056222 | F7: ='Data Sheet'!E19/'Data Sheet'!E$17 -> 0.022227477 | G7: ='Data Sheet'!F19/'Data Sheet'!F$17 -> 0.013620719 | H7: ='Data Sheet'!G19/'Data Sheet'!G$17 -> 0.01246238 | I7: ='Data Sheet'!H19/'Data Sheet'!H$17 -> 0.015959959 | J7: ='Data Sheet'!I19/'Data Sheet'!I$17 -> 0.011690596 | ... L7: ='Data Sheet'!K19/'Data Sheet'!K$17 -> 0.018819014
B8: ='Data Sheet'!A20 -> Power and Fuel | C8: ='Data Sheet'!B20/'Data Sheet'!B$17 -> 0.0092313858 | D8: ='Data Sheet'!C20/'Data Sheet'!C$17 -> 0.0083553964 | E8: ='Data Sheet'!D20/'Data Sheet'!D$17 -> 0.0080661469 | F8: ='Data Sheet'!E20/'Data Sheet'!E$17 -> 0.0076382738 | G8: ='Data Sheet'!F20/'Data Sheet'!F$17 -> 0.0075688977 | H8: ='Data Sheet'!G20/'Data Sheet'!G$17 -> 0.007215324 | I8: ='Data Sheet'!H20/'Data Sheet'!H$17 -> 0.0067102979 | J8: ='Data Sheet'!I20/'Data Sheet'!I$17 -> 0.0073441464 | ... L8: ='Data Sheet'!K20/'Data Sheet'!K$17 -> 0.007543206
B9: ='Data Sheet'!A21 -> Other Mfr. Exp | C9: ='Data Sheet'!B21/'Data Sheet'!B$17 -> 0.028118214 | D9: ='Data Sheet'!C21/'Data Sheet'!C$17 -> 0.027980198 | E9: ='Data Sheet'!D21/'Data Sheet'!D$17 -> 0.024859644 | F9: ='Data Sheet'!E21/'Data Sheet'!E$17 -> 0.024980354 | G9: ='Data Sheet'!F21/'Data Sheet'!F$17 -> 0.025973253 | H9: ='Data Sheet'!G21/'Data Sheet'!G$17 -> 0.030916959 | I9: ='Data Sheet'!H21/'Data Sheet'!H$17 -> 0.026015075 | J9: ='Data Sheet'!I21/'Data Sheet'!I$17 -> 0.02606376 | ... L9: ='Data Sheet'!K21/'Data Sheet'!K$17 -> 0.029513267
B10: ='Data Sheet'!A22 -> Employee Cost | C10: ='Data Sheet'!B22/'Data Sheet'!B$17 -> 0.01736302 | D10: ='Data Sheet'!C22/'Data Sheet'!C$17 -> 0.016193886 | E10: ='Data Sheet'!D22/'Data Sheet'!D$17 -> 0.018834313 | F10: ='Data Sheet'!E22/'Data Sheet'!E$17 -> 0.017804476 | G10: ='Data Sheet'!F22/'Data Sheet'!F$17 -> 0.018381034 | H10: ='Data Sheet'!G22/'Data Sheet'!G$17 -> 0.02226644 | I10: ='Data Sheet'!H22/'Data Sheet'!H$17 -> 0.019930095 | J10: ='Data Sheet'!I22/'Data Sheet'!I$17 -> 0.017464232 | ... L10: ='Data Sheet'!K22/'Data Sheet'!K$17 -> 0.019668267
B11: ='Data Sheet'!A23 -> Selling and admin | C11: ='Data Sheet'!B23/'Data Sheet'!B$17 -> 0.075417999 | D11: ='Data Sheet'!C23/'Data Sheet'!C$17 -> 0.0059877119 | E11: ='Data Sheet'!D23/'Data Sheet'!D$17 -> 0.006385866 | F11: ='Data Sheet'!E23/'Data Sheet'!E$17 -> 0.0067904654 | G11: ='Data Sheet'!F23/'Data Sheet'!F$17 -> 0.0047940909 | H11: ='Data Sheet'!G23/'Data Sheet'!G$17 -> 0.0045019148 | I11: ='Data Sheet'!H23/'Data Sheet'!H$17 -> 0.004629673 | J11: ='Data Sheet'!I23/'Data Sheet'!I$17 -> 0.0049496307 | ... L11: ='Data Sheet'!K23/'Data Sheet'!K$17 -> 0.0052643239
B12: ='Data Sheet'!A24 -> Other Expenses | C12: ='Data Sheet'!B24/'Data Sheet'!B$17 -> -0.058395156 | D12: ='Data Sheet'!C24/'Data Sheet'!C$17 -> 0.012714222 | E12: ='Data Sheet'!D24/'Data Sheet'!D$17 -> 0.011346886 | F12: ='Data Sheet'!E24/'Data Sheet'!E$17 -> 0.011289449 | G12: ='Data Sheet'!F24/'Data Sheet'!F$17 -> 0.0091832796 | H12: ='Data Sheet'!G24/'Data Sheet'!G$17 -> 0.011458779 | I12: ='Data Sheet'!H24/'Data Sheet'!H$17 -> 0.0097510126 | J12: ='Data Sheet'!I24/'Data Sheet'!I$17 -> 0.0099314746 | ... L12: ='Data Sheet'!K24/'Data Sheet'!K$17 -> 0.010652136
B13: ='Data Sheet'!A25 -> Other Income | C13: ='Data Sheet'!B25/'Data Sheet'!B$17 -> 0.0019828141 | D13: ='Data Sheet'!C25/'Data Sheet'!C$17 -> 0.0023281811 | E13: ='Data Sheet'!D25/'Data Sheet'!D$17 -> 0.0058370806 | F13: ='Data Sheet'!E25/'Data Sheet'!E$17 -> 0.002415954 | G13: ='Data Sheet'!F25/'Data Sheet'!F$17 -> 0.0024121237 | H13: ='Data Sheet'!G25/'Data Sheet'!G$17 -> 0.0080532459 | I13: ='Data Sheet'!H25/'Data Sheet'!H$17 -> 0.0036686147 | J13: ='Data Sheet'!I25/'Data Sheet'!I$17 -> 0.0029785553 | ... L13: ='Data Sheet'!K25/'Data Sheet'!K$17 -> 0.0019732791
B14: ='Data Sheet'!A26 -> Depreciation | C14: ='Data Sheet'!B26/'Data Sheet'!B$17 -> 0.011467003 | D14: ='Data Sheet'!C26/'Data Sheet'!C$17 -> 0.010743253 | E14: ='Data Sheet'!D26/'Data Sheet'!D$17 -> 0.01057659 | F14: ='Data Sheet'!E26/'Data Sheet'!E$17 -> 0.010622099 | G14: ='Data Sheet'!F26/'Data Sheet'!F$17 -> 0.015054563 | H14: ='Data Sheet'!G26/'Data Sheet'!G$17 -> 0.017154412 | I14: ='Data Sheet'!H26/'Data Sheet'!H$17 -> 0.016079405 | J14: ='Data Sheet'!I26/'Data Sheet'!I$17 -> 0.014913085 | ... L14: ='Data Sheet'!K26/'Data Sheet'!K$17 -> 0.014648729
B15: ='Data Sheet'!A27 -> Interest | C15: ='Data Sheet'!B27/'Data Sheet'!B$17 -> 0.010641024 | D15: ='Data Sheet'!C27/'Data Sheet'!C$17 -> 0.010252402 | E15: ='Data Sheet'!D27/'Data Sheet'!D$17 -> 0.0039605673 | F15: ='Data Sheet'!E27/'Data Sheet'!E$17 -> 0.0023599666 | G15: ='Data Sheet'!F27/'Data Sheet'!F$17 -> 0.0027792298 | H15: ='Data Sheet'!G27/'Data Sheet'!G$17 -> 0.0017251334 | I15: ='Data Sheet'!H27/'Data Sheet'!H$17 -> 0.0017364905 | J15: ='Data Sheet'!I27/'Data Sheet'!I$17 -> 0.0015735456 | ... L15: ='Data Sheet'!K27/'Data Sheet'!K$17 -> 0.0011700182
B16: ='Data Sheet'!A28 -> Profit before tax | C16: ='Data Sheet'!B28/'Data Sheet'!B$17 -> 0.057283754 | D16: ='Data Sheet'!C28/'Data Sheet'!C$17 -> 0.062791968 | E16: ='Data Sheet'!D28/'Data Sheet'!D$17 -> 0.081291408 | F16: ='Data Sheet'!E28/'Data Sheet'!E$17 -> 0.071080936 | G16: ='Data Sheet'!F28/'Data Sheet'!F$17 -> 0.070155045 | H16: ='Data Sheet'!G28/'Data Sheet'!G$17 -> 0.061444158 | I16: ='Data Sheet'!H28/'Data Sheet'!H$17 -> 0.066635525 | J16: ='Data Sheet'!I28/'Data Sheet'!I$17 -> 0.071431406 | ... L16: ='Data Sheet'!K28/'Data Sheet'!K$17 -> 0.061873158
... B20: ='Data Sheet'!A32 -> EBITDA | C20: ='Data Sheet'!B32/'Data Sheet'!B$17 -> 0.079391782 | D20: ='Data Sheet'!C32/'Data Sheet'!C$17 -> 0.08378342 | E20: ='Data Sheet'!D32/'Data Sheet'!D$17 -> 0.095827236 | F20: ='Data Sheet'!E32/'Data Sheet'!E$17 -> 0.084067001 | G20: ='Data Sheet'!F32/'Data Sheet'!F$17 -> 0.087992859 | H20: ='Data Sheet'!G32/'Data Sheet'!G$17 -> 0.080326189 | I20: ='Data Sheet'!H32/'Data Sheet'!H$17 -> 0.084456263 | J20: ='Data Sheet'!I32/'Data Sheet'!I$17 -> 0.087922005 | ... L20: ='Data Sheet'!K32/'Data Sheet'!K$17 -> 0.077701508
B22: ="Common Size Statement Balance Sheet"&" "&"-"&'Data Sheet'!B1 -> Common Size Statement Balance Sheet -AVENUE SUPERMARTS LTD
B24: Particular | C24: ='Data Sheet'!B56 -> 42460 | D24: ='Data Sheet'!C56 -> 42825 | E24: ='Data Sheet'!D56 -> 43190 | F24: ='Data Sheet'!E56 -> 43555 | G24: ='Data Sheet'!F56 -> 43921 | H24: ='Data Sheet'!G56 -> 44286 | I24: ='Data Sheet'!H56 -> 44651 | J24: ='Data Sheet'!I56 -> 45016 | ... L24: ='Data Sheet'!K56 -> 45747
B25: ='Data Sheet'!A57 -> Equity Share Capital | C25: ='Data Sheet'!B57/'Data Sheet'!B$61 -> 0.18105083 | D25: ='Data Sheet'!C57/'Data Sheet'!C$61 -> 0.10724351 | E25: ='Data Sheet'!D57/'Data Sheet'!D$61 -> 0.11049145 | F25: ='Data Sheet'!E57/'Data Sheet'!E$61 -> 0.089084291 | G25: ='Data Sheet'!F57/'Data Sheet'!F$61 -> 0.053640396 | H25: ='Data Sheet'!G57/'Data Sheet'!G$61 -> 0.047438127 | I25: ='Data Sheet'!H57/'Data Sheet'!H$61 -> 0.041870004 | J25: ='Data Sheet'!I57/'Data Sheet'!I$61 -> 0.035806528 | ... L25: ='Data Sheet'!K57/'Data Sheet'!K$61 -> 0.026764936
B26: ='Data Sheet'!A58 -> Reserves | C26: ='Data Sheet'!B58/'Data Sheet'!B$61 -> 0.309167 | D26: ='Data Sheet'!C58/'Data Sheet'!C$61 -> 0.55293782 | E26: ='Data Sheet'!D58/'Data Sheet'!D$61 -> 0.71614951 | F26: ='Data Sheet'!E58/'Data Sheet'!E$61 -> 0.70849618 | G26: ='Data Sheet'!F58/'Data Sheet'!F$61 -> 0.86384828 | H26: ='Data Sheet'!G58/'Data Sheet'!G$61 -> 0.84481126 | I26: ='Data Sheet'!H58/'Data Sheet'!H$61 -> 0.84221362 | J26: ='Data Sheet'!I58/'Data Sheet'!I$61 -> 0.85229766 | ... L26: ='Data Sheet'!K58/'Data Sheet'!K$61 -> 0.85457196
B27: ='Data Sheet'!A59 -> Borrowings | C27: ='Data Sheet'!B59/'Data Sheet'!B$61 -> 0.38443235 | D27: ='Data Sheet'!C59/'Data Sheet'!C$61 -> 0.25730331 | E27: ='Data Sheet'!D59/'Data Sheet'!D$61 -> 0.077767863 | F27: ='Data Sheet'!E59/'Data Sheet'!E$61 -> 0.099942902 | G27: ='Data Sheet'!F59/'Data Sheet'!F$61 -> 0.027590724 | H27: ='Data Sheet'!G59/'Data Sheet'!G$61 -> 0.028759323 | I27: ='Data Sheet'!H59/'Data Sheet'!H$61 -> 0.041816356 | J27: ='Data Sheet'!I59/'Data Sheet'!I$61 -> 0.035514888 | ... L27: ='Data Sheet'!K59/'Data Sheet'!K$61 -> 0.033711488
B28: ='Data Sheet'!A60 -> Other Liabilities | C28: ='Data Sheet'!B60/'Data Sheet'!B$61 -> 0.12534982 | D28: ='Data Sheet'!C60/'Data Sheet'!C$61 -> 0.082515363 | E28: ='Data Sheet'!D60/'Data Sheet'!D$61 -> 0.095591177 | F28: ='Data Sheet'!E60/'Data Sheet'!E$61 -> 0.10247663 | G28: ='Data Sheet'!F60/'Data Sheet'!F$61 -> 0.054920604 | H28: ='Data Sheet'!G60/'Data Sheet'!G$61 -> 0.078991289 | I28: ='Data Sheet'!H60/'Data Sheet'!H$61 -> 0.074100025 | J28: ='Data Sheet'!I60/'Data Sheet'!I$61 -> 0.076380926 | ... L28: ='Data Sheet'!K60/'Data Sheet'!K$61 -> 0.084951618
B29: ='Data Sheet'!A61 -> Total | C29: ='Data Sheet'!B61/'Data Sheet'!B$61 -> 1 | D29: ='Data Sheet'!C61/'Data Sheet'!C$61 -> 1 | E29: ='Data Sheet'!D61/'Data Sheet'!D$61 -> 1 | F29: ='Data Sheet'!E61/'Data Sheet'!E$61 -> 1 | G29: ='Data Sheet'!F61/'Data Sheet'!F$61 -> 1 | H29: ='Data Sheet'!G61/'Data Sheet'!G$61 -> 1 | I29: ='Data Sheet'!H61/'Data Sheet'!H$61 -> 1 | J29: ='Data Sheet'!I61/'Data Sheet'!I$61 -> 1 | ... L29: ='Data Sheet'!K61/'Data Sheet'!K$61 -> 1
B31: ='Data Sheet'!A62 -> Net Block | C31: ='Data Sheet'!B62/'Data Sheet'!B$75 -> 0.67498936 | D31: ='Data Sheet'!C62/'Data Sheet'!C$75 -> 0.44296717 | E31: ='Data Sheet'!D62/'Data Sheet'!D$75 -> 0.60195424 | F31: ='Data Sheet'!E62/'Data Sheet'!E$75 -> 0.62813075 | G31: ='Data Sheet'!F62/'Data Sheet'!F$75 -> 0.49254316 | H31: ='Data Sheet'!G62/'Data Sheet'!G$75 -> 0.51327531 | I31: ='Data Sheet'!H62/'Data Sheet'!H$75 -> 0.59854127 | J31: ='Data Sheet'!I62/'Data Sheet'!I$75 -> 0.62638943 | ... L31: ='Data Sheet'!K62/'Data Sheet'!K$75 -> 0.66658194
B32: ='Data Sheet'!A63 -> Capital Work in Progress | C32: ='Data Sheet'!B63/'Data Sheet'!B$75 -> 0.026338359 | D32: ='Data Sheet'!C63/'Data Sheet'!C$75 -> 0.02627301 | E32: ='Data Sheet'!D63/'Data Sheet'!D$75 -> 0.026038292 | F32: ='Data Sheet'!E63/'Data Sheet'!E$75 -> 0.053792021 | G32: ='Data Sheet'!F63/'Data Sheet'!F$75 -> 0.030175155 | H32: ='Data Sheet'!G63/'Data Sheet'!G$75 -> 0.074667614 | I32: ='Data Sheet'!H63/'Data Sheet'!H$75 -> 0.072997315 | J32: ='Data Sheet'!I63/'Data Sheet'!I$75 -> 0.045798508 | ... L32: ='Data Sheet'!K63/'Data Sheet'!K$75 -> 0.04521696
B33: ='Data Sheet'!A64 -> Investments | C33: ='Data Sheet'!B64/'Data Sheet'!B$75 -> 0.0094565316 | D33: ='Data Sheet'!C64/'Data Sheet'!C$75 -> 0.0044146355 | E33: ='Data Sheet'!D64/'Data Sheet'!D$75 -> 0.01207106 | F33: ='Data Sheet'!E64/'Data Sheet'!E$75 -> 0.0023595746 | G33: ='Data Sheet'!F64/'Data Sheet'!F$75 -> 0.0012156182 | H33: ='Data Sheet'!G64/'Data Sheet'!G$75 -> 0.00021603729 | I33: ='Data Sheet'!H64/'Data Sheet'!H$75 -> 0.00038394465 | J33: ='Data Sheet'!I64/'Data Sheet'!I$75 -> 0.011168482 | ... L33: ='Data Sheet'!K64/'Data Sheet'!K$75 -> 0.00013408586
B34: ='Data Sheet'!A65 -> Other Assets | C34: ='Data Sheet'!B65/'Data Sheet'!B$75 -> 0.28921575 | D34: ='Data Sheet'!C65/'Data Sheet'!C$75 -> 0.52634518 | E34: ='Data Sheet'!D65/'Data Sheet'!D$75 -> 0.3599364 | F34: ='Data Sheet'!E65/'Data Sheet'!E$75 -> 0.31571765 | G34: ='Data Sheet'!F65/'Data Sheet'!F$75 -> 0.47606607 | H34: ='Data Sheet'!G65/'Data Sheet'!G$75 -> 0.41184104 | I34: ='Data Sheet'!H65/'Data Sheet'!H$75 -> 0.32807747 | J34: ='Data Sheet'!I65/'Data Sheet'!I$75 -> 0.31664358 | ... L34: ='Data Sheet'!K65/'Data Sheet'!K$75 -> 0.28806702
B35: ='Data Sheet'!A67 -> Receivables | C35: ='Data Sheet'!B67/'Data Sheet'!B$75 -> 0.0027147629 | D35: ='Data Sheet'!C67/'Data Sheet'!C$75 -> 0.0036086939 | E35: ='Data Sheet'!D67/'Data Sheet'!D$75 -> 0.005934613 | F35: ='Data Sheet'!E67/'Data Sheet'!E$75 -> 0.0091884948 | G35: ='Data Sheet'!F67/'Data Sheet'!F$75 -> 0.0016188921 | H35: ='Data Sheet'!G67/'Data Sheet'!G$75 -> 0.0031914933 | I35: ='Data Sheet'!H67/'Data Sheet'!H$75 -> 0.0043235787 | J35: ='Data Sheet'!I67/'Data Sheet'!I$75 -> 0.0034333967 | ... L35: ='Data Sheet'!K67/'Data Sheet'!K$75 -> 0.0063254799
B36: ='Data Sheet'!A68 -> Inventory | C36: ='Data Sheet'!B68/'Data Sheet'!B$75 -> 0.21656521 | D36: ='Data Sheet'!C68/'Data Sheet'!C$75 -> 0.16288957 | E36: ='Data Sheet'!D68/'Data Sheet'!D$75 -> 0.20598525 | F36: ='Data Sheet'!E68/'Data Sheet'!E$75 -> 0.22962672 | G36: ='Data Sheet'!F68/'Data Sheet'!F$75 -> 0.16125987 | H36: ='Data Sheet'!G68/'Data Sheet'!G$75 -> 0.16464824 | I36: ='Data Sheet'!H68/'Data Sheet'!H$75 -> 0.17727772 | J36: ='Data Sheet'!I68/'Data Sheet'!I$75 -> 0.17915305 | ... L36: ='Data Sheet'!K68/'Data Sheet'!K$75 -> 0.20747812
B37: ='Data Sheet'!A69 -> Cash & Bank | C37: ='Data Sheet'!B69/'Data Sheet'!B$75 -> 0.011316886 | D37: ='Data Sheet'!C69/'Data Sheet'!C$75 -> 0.32380123 | E37: ='Data Sheet'!D69/'Data Sheet'!D$75 -> 0.099178148 | F37: ='Data Sheet'!E69/'Data Sheet'!E$75 -> 0.031271144 | G37: ='Data Sheet'!F69/'Data Sheet'!F$75 -> 0.0089333033 | H37: ='Data Sheet'!G69/'Data Sheet'!G$75 -> 0.10586413 | I37: ='Data Sheet'!H69/'Data Sheet'!H$75 -> 0.019299359 | J37: ='Data Sheet'!I69/'Data Sheet'!I$75 -> 0.077788862 | ... L37: ='Data Sheet'!K69/'Data Sheet'!K$75 -> 0.014732992
B39: Total Asset | C39: ='Data Sheet'!B75/'Data Sheet'!B$75 -> 1 | D39: ='Data Sheet'!C75/'Data Sheet'!C$75 -> 1 | E39: ='Data Sheet'!D75/'Data Sheet'!D$75 -> 1 | F39: ='Data Sheet'!E75/'Data Sheet'!E$75 -> 1 | G39: ='Data Sheet'!F75/'Data Sheet'!F$75 -> 1 | H39: ='Data Sheet'!G75/'Data Sheet'!G$75 -> 1 | I39: ='Data Sheet'!H75/'Data Sheet'!H$75 -> 1 | J39: ='Data Sheet'!I75/'Data Sheet'!I$75 -> 1 | ... L39: ='Data Sheet'!K75/'Data Sheet'!K$75 -> 1

Sheet DCF
B2: Calculation Of PV Of FCFF | E2: ='Intresnsic Growth'!I2 -> 45717 | F2: =E2+365 -> 46082 | G2: =F2+366 -> 46448 | H2: =G2+365 -> 46813 | I2: =H2+365 -> 47178 | J2: =I2+366 -> 47544
B4: EBIT | E4: ='Data Sheet'!K32-'Data Sheet'!K26 -> 3742.69 | F4: =E4*(1+$C$13) -> 4461.2865 | G4: =F4*(1+$C$13) -> 5317.8535 | H4: =G4*(1+$C$13) -> 6338.8814 | I4: =H4*(1+$C$13) -> 7555.9466 | J4: =I4*(1+$C$13) -> 9006.6883
B5: Tax Rate | E5: =25% -> 0.25 | F5: =25% -> 0.25 | G5: =25% -> 0.25 | H5: =25% -> 0.25 | I5: =25% -> 0.25 | J5: =25% -> 0.25
B6: EBIT(1-T) | E6: =E4*(1-E5) -> 2807.0175 | F6: =F4*(1-F5) -> 3345.9649 | G6: =G4*(1-G5) -> 3988.3901 | H6: =H4*(1-H5) -> 4754.161 | I6: =I4*(1-I5) -> 5666.9599 | J6: =J4*(1-J5) -> 6755.0162
B7: Less: Reinvestment Rate | E7: ='Intresnsic Growth'!I48 -> 1.8810147 | F7: =E7+((J7-E7)/4) -> 1.730486 | G7: =F7+((K7-F7)/4) -> 1.2978645 | H7: =G7+((L7-G7)/4) -> 0.97339839 | I7: =H7+((M7-H7)/4) -> 0.73004879 | J7: 1.2789
B8: Free Cash Flow Of Firm(FCFF) | E8: =E6*(1-E7) -> -2473.0237 | F8: =F6*(1-F7) -> -2444.1806 | G8: =G6*(1-G7) -> -1187.9999 | H8: =H6*(1-H7) -> 126.46832 | I8: =I6*(1-I7) -> 1529.8027 | J8: =J6*(1-J7) -> -1883.974
B9: Mid Year Convension | F9: 0.5 | G9: =F9+1 -> 1.5 | H9: =G9+1 -> 2.5 | I9: =H9+1 -> 3.5 | J9: =I9+1 -> 4.5
B10: Discounting Factor | F10: =1/(1+$C$15)^F9 -> 0.93980499 | G10: =1/(1+$C$15)^G9 -> 0.83006717 | H10: =1/(1+$C$15)^H9 -> 0.73314307 | I10: =1/(1+$C$15)^I9 -> 0.64753646 | J10: =1/(1+$C$15)^J9 -> 0.57192584
B11: PV Of FCFF | F11: =F8*F10 -> -2297.0531 | G11: =G8*G10 -> -986.11974 | H11: =H8*H10 -> 92.719375 | I11: =I8*I10 -> 990.603 | J11: =J8*J10 -> -1077.4934
B13: Expected Growth | C13: 0.192
B14: Terminal Growth | C14: 0.055
B15: WACC | C15: =WACC!M45 -> 0.13220354
B17: Calculation OF Terminal Value | E17: Sensitivity Analysis
B19: FCFF (n+1) | C19: =J8*(1+C13) -> -2245.697 | E19: =C29 -> -19913.527 | F19: 0.11 | G19: 0.12 | H19: =C20 -> 0.13220354 | I19: 0.14 | J19: 0.15
B20: WACC | C20: =C15 -> 0.13220354 | E20: 0.03 | F20: -19331.996 | G20: -17548.146 | H20: -17548.146 | I20: -14953.454 | J20: -13980.445
B21: Terminal Value Rate | C21: =C14 -> 0.055 | E21: 0.04 | F21: -21625.518 | G21: -19331.996 | H21: -19331.996 | I21: -16121.066 | J21: -14953.454
E22: =C21 -> 0.055 | F22: -21625.518 | G22: -19331.996 | H22: -19331.996 | I22: -16121.066 | J22: -14953.454
B23: Terminal Value | C23: =C19/(C20-C21) -> -29088.007 | E23: 0.06 | F23: -28964.787 | G23: -24683.547 | H23: -24683.547 | I23: -19331.996 | J23: -17548.146
E24: 0.07 | F24: -35386.648 | G24: -28964.787 | H24: -28964.787 | I24: -21625.518 | J24: -19331.996
B25: Calculation Of Equity Value
B27: PV Of FCFF | C27: =SUM(F11:J11) -> -3277.3439
B28: PV Of Terminal Value | C28: =C23*J10 -> -16636.183
B29: Value Of Operating Asset | C29: =SUM(C27:C28) -> -19913.527
B31: Add: Cash | C31: ='Data Sheet'!K69 -> 358.2
B32: Less : Debt | C32: ='Data Sheet'!K59 -> 819.62
B33: Value Of Equity | C33: =C29+C31-C32 -> -20374.947
B34: No Of Shares | C34: ='Data Sheet'!B6 -> 65.073308
B36: Equity Value Per Share | C36: =C33/C34 -> -313.10759
B38: Share Price | C38: 4358
B39: Discounted/Primium | C39: =C38/C36 -> -13.918538

Sheet Ratio Analysis
B2: ="Ratio Analysis - "&'Data Sheet'!B1 -> Ratio Analysis - AVENUE SUPERMARTS LTD
B3: Years | C3: ='Data Sheet'!B16 -> 42460 | D3: ='Data Sheet'!C16 -> 42825 | E3: ='Data Sheet'!D16 -> 43190 | F3: ='Data Sheet'!E16 -> 43555 | G3: ='Data Sheet'!F16 -> 43921 | H3: ='Data Sheet'!G16 -> 44286 | I3: ='Data Sheet'!H16 -> 44651 | J3: ='Data Sheet'!I16 -> 45016 | ... L3: ='Data Sheet'!K16 -> 45747 | M3: Trend | N3: Mean | O3: Median
B5: Sales Growth | D5: =HistoricaIFS!D6 -> 0.38607091 | E5: =HistoricaIFS!E6 -> 0.26353833 | F5: =HistoricaIFS!F6 -> 0.33068941 | G5: =HistoricaIFS!G6 -> 0.24322903 | H5: =HistoricaIFS!H6 -> -0.029237401 | I5: =HistoricaIFS!I6 -> 0.28302999 | J5: =HistoricaIFS!J6 -> 0.38297994 | K5: =HistoricaIFS!K6 -> 0.1855591 | L5: =HistoricaIFS!L6 -> 0.16872253 | N5: =IFERROR(AVERAGE(D5:L5),0) -> 0.24606465 | O5: =IFERROR(MEDIAN(D5:L5),0) -> 0.26353833
B6: EBITDA Growth | D6: =HistoricaIFS!D17/HistoricaIFS!C17-1 -> 0.45859796 | E6: =HistoricaIFS!E17/HistoricaIFS!D17-1 -> 0.39588105 | F6: =HistoricaIFS!F17/HistoricaIFS!E17-1 -> 0.20730157 | G6: =HistoricaIFS!G17/HistoricaIFS!F17-1 -> 0.30306555 | H6: =HistoricaIFS!H17/HistoricaIFS!G17-1 -> -0.18018052 | I6: =HistoricaIFS!I17/HistoricaIFS!H17-1 -> 0.43415118 | J6: =HistoricaIFS!J17/HistoricaIFS!I17-1 -> 0.45414111 | K6: =HistoricaIFS!K17/HistoricaIFS!J17-1 -> 0.12830434 | L6: =HistoricaIFS!L17/HistoricaIFS!K17-1 -> 0.094716049 | N6: =IFERROR(AVERAGE(D6:L6),0) -> 0.2551087 | O6: =IFERROR(MEDIAN(D6:L6),0) -> 0.30306555
B7: EBIT Growth | D7: =IFERROR(HistoricaIFS!D26-HistoricaIFS!C26-1,0) -> 243.69 | E7: =IFERROR(HistoricaIFS!E26-HistoricaIFS!D26-1,0) -> 413.94 | F7: =IFERROR(HistoricaIFS!F26-HistoricaIFS!E26-1,0) -> 238.29 | G7: =IFERROR(HistoricaIFS!G26-HistoricaIFS!F26-1,0) -> 310.17 | H7: =IFERROR(HistoricaIFS!H26-HistoricaIFS!G26-1,0) -> -396.76 | I7: =IFERROR(HistoricaIFS!I26-HistoricaIFS!H26-1,0) -> 660.46 | J7: =IFERROR(HistoricaIFS!J26-HistoricaIFS!I26-1,0) -> 981.01 | K7: =IFERROR(HistoricaIFS!K26-HistoricaIFS!J26-1,0) -> 383.26 | L7: =IFERROR(HistoricaIFS!L26-HistoricaIFS!K26-1,0) -> 237.79 | N7: =IFERROR(AVERAGE(D7:L7),0) -> 341.31667 | O7: =IFERROR(MEDIAN(D7:L7),0) -> 310.17
B8: Net Profit Growth | D8: =IFERROR((HistoricaIFS!D32/HistoricaIFS!C32-1),0) -> 0.49497252 | E8: =IFERROR((HistoricaIFS!E32/HistoricaIFS!D32-1),0) -> 0.68409399 | F8: =IFERROR((HistoricaIFS!F32/HistoricaIFS!E32-1),0) -> 0.11941557 | G8: =IFERROR((HistoricaIFS!G32/HistoricaIFS!F32-1),0) -> 0.441576 | H8: =IFERROR((HistoricaIFS!H32/HistoricaIFS!G32-1),0) -> -0.15494051 | I8: =IFERROR((HistoricaIFS!I32/HistoricaIFS!H32-1),0) -> 0.35749302 | J8: =IFERROR((HistoricaIFS!J32/HistoricaIFS!I32-1),0) -> 0.59358815 | K8: =IFERROR((HistoricaIFS!K32/HistoricaIFS!J32-1),0) -> 0.066285195 | L8: =IFERROR((HistoricaIFS!L32/HistoricaIFS!K32-1),0) -> 0.067759653 | N8: =IFERROR(AVERAGE(D8:L8),0) -> 0.29669373 | O8: =IFERROR(MEDIAN(D8:L8),0) -> 0.35749302
B9: Dividend Growth | D9: =IFERROR(HistoricaIFS!D40/HistoricaIFS!C40-1,0) -> 0 | E9: =IFERROR(HistoricaIFS!E40/HistoricaIFS!D40-1,0) -> 0 | F9: =IFERROR(HistoricaIFS!F40/HistoricaIFS!E40-1,0) -> 0 | G9: =IFERROR(HistoricaIFS!G40/HistoricaIFS!F40-1,0) -> 0 | H9: =IFERROR(HistoricaIFS!H40/HistoricaIFS!G40-1,0) -> 0 | I9: =IFERROR(HistoricaIFS!I40/HistoricaIFS!H40-1,0) -> 0 | J9: =IFERROR(HistoricaIFS!J40/HistoricaIFS!I40-1,0) -> 0 | K9: =IFERROR(HistoricaIFS!K40/HistoricaIFS!J40-1,0) -> 0 | L9: =IFERROR(HistoricaIFS!L40/HistoricaIFS!K40-1,0) -> 0 | N9: =IFERROR(AVERAGE(D9:L9),0) -> 0 | O9: =IFERROR(MEDIAN(D9:L9),0) -> 0
B11: Gross Margine | C11: =IFERROR(HistoricaIFS!C9,0) -> 0.90556819 | D11: =IFERROR(HistoricaIFS!D9,0) -> 0.89983862 | E11: =IFERROR(HistoricaIFS!E9,0) -> 0.89227576 | F11: =IFERROR(HistoricaIFS!F9,0) -> 0.90027304 | G11: =IFERROR(HistoricaIFS!G9,0) -> 0.90044592 | H11: =IFERROR(HistoricaIFS!H9,0) -> 0.91176885 | I11: =IFERROR(HistoricaIFS!I9,0) -> 0.90483651 | J11: =IFERROR(HistoricaIFS!J9,0) -> 0.90017941 | ... L11: =IFERROR(HistoricaIFS!L9,0) -> 0.90836491 | N11: =IFERROR(AVERAGE(D11:L11),0) -> 0.90237535 | O11: =IFERROR(MEDIAN(D11:L11),0) -> 0.90044592
B12: EBITDA Magrine | C12: =IFERROR(HistoricaIFS!C18,0) -> 0.077408968 | D12: =IFERROR(HistoricaIFS!D18,0) -> 0.081459442 | E12: =IFERROR(HistoricaIFS!E18,0) -> 0.089991486 | F12: =IFERROR(HistoricaIFS!F18,0) -> 0.081647048 | G12: =IFERROR(HistoricaIFS!G18,0) -> 0.085576714 | H12: =IFERROR(HistoricaIFS!H18,0) -> 0.072270458 | I12: =IFERROR(HistoricaIFS!I18,0) -> 0.080782806 | J12: =IFERROR(HistoricaIFS!J18,0) -> 0.084939481 | ... L12: =IFERROR(HistoricaIFS!L18,0) -> 0.075718626 | N12: =IFERROR(AVERAGE(D12:L12),0) -> 0.08146928 | O12: =IFERROR(MEDIAN(D12:L12),0) -> 0.081459442
B13: EBIT Margine | C13: =IFERROR(HistoricaIFS!C27,0) -> 0.05530094 | D13: =IFERROR(HistoricaIFS!D27,0) -> 0.060463787 | E13: =IFERROR(HistoricaIFS!E27,0) -> 0.075454328 | F13: =IFERROR(HistoricaIFS!F27,0) -> 0.068664982 | G13: =IFERROR(HistoricaIFS!G27,0) -> 0.067742921 | H13: =IFERROR(HistoricaIFS!H27,0) -> 0.053390912 | I13: =IFERROR(HistoricaIFS!I27,0) -> 0.06296691 | J13: =IFERROR(HistoricaIFS!J27,0) -> 0.068452851 | ... L13: =IFERROR(HistoricaIFS!L27,0) -> 0.059899879 | N13: =IFERROR(AVERAGE(D13:L13),0) -> 0.064704587 | O13: =IFERROR(MEDIAN(D13:L13),0) -> 0.065304714
B14: EBIT Margine | C14: =(HistoricaIFS!C17-HistoricaIFS!C23)/HistoricaIFS!C5 -> 0.065941965 | D14: =(HistoricaIFS!D17-HistoricaIFS!D23)/HistoricaIFS!D5 -> 0.070716189 | E14: =(HistoricaIFS!E17-HistoricaIFS!E23)/HistoricaIFS!E5 -> 0.079414895 | F14: =(HistoricaIFS!F17-HistoricaIFS!F23)/HistoricaIFS!F5 -> 0.071024948 | G14: =(HistoricaIFS!G17-HistoricaIFS!G23)/HistoricaIFS!G5 -> 0.070522151 | H14: =(HistoricaIFS!H17-HistoricaIFS!H23)/HistoricaIFS!H5 -> 0.055116046 | I14: =(HistoricaIFS!I17-HistoricaIFS!I23)/HistoricaIFS!I5 -> 0.0647034 | J14: =(HistoricaIFS!J17-HistoricaIFS!J23)/HistoricaIFS!J5 -> 0.070026396 | ... L14: =(HistoricaIFS!L17-HistoricaIFS!L23)/HistoricaIFS!L5 -> 0.061069897 | N14: =IFERROR(AVERAGE(D14:L14),0) -> 0.067671464 | O14: =IFERROR(MEDIAN(D14:L14),0) -> 0.070026396
B15: Net Profit Margine | C15: =IFERROR(HistoricaIFS!C33,0) -> 0.03730766 | D15: =IFERROR(HistoricaIFS!D33,0) -> 0.04023887 | E15: =IFERROR(HistoricaIFS!E33,0) -> 0.053631961 | F15: =IFERROR(HistoricaIFS!F33,0) -> 0.045116804 | G15: =IFERROR(HistoricaIFS!G33,0) -> 0.052314819 | H15: =IFERROR(HistoricaIFS!H33,0) -> 0.045540623 | I15: =IFERROR(HistoricaIFS!I33,0) -> 0.048183658 | J15: =IFERROR(HistoricaIFS!J33,0) -> 0.055521345 | ... L15: =IFERROR(HistoricaIFS!L33,0) -> 0.045621782 | N15: =IFERROR(AVERAGE(D15:L15),0) -> 0.048456161 | O15: =IFERROR(MEDIAN(D15:L15),0) -> 0.048183658
B17: SalesEXpenses %sales | C17: =IFERROR(HistoricaIFS!C15,0) -> 0.017022843 | D17: =IFERROR(HistoricaIFS!D15,0) -> 0.018701934 | E17: =IFERROR(HistoricaIFS!E15,0) -> 0.017732752 | F17: =IFERROR(HistoricaIFS!F15,0) -> 0.018079914 | G17: =IFERROR(HistoricaIFS!G15,0) -> 0.013977371 | H17: =IFERROR(HistoricaIFS!H15,0) -> 0.015960694 | I17: =IFERROR(HistoricaIFS!I15,0) -> 0.014380686 | J17: =IFERROR(HistoricaIFS!J15,0) -> 0.014881105 | ... L17: =IFERROR(HistoricaIFS!L15,0) -> 0.01591646 | N17: =IFERROR(AVERAGE(D17:L17),0) -> 0.016155373 | O17: =IFERROR(MEDIAN(D17:L17),0) -> 0.01591646
B18: Deprisiation%Sales | C18: =IFERROR(HistoricaIFS!C24,0) -> 0.011467003 | D18: =IFERROR(HistoricaIFS!D24,0) -> 0.010743253 | E18: =IFERROR(HistoricaIFS!E24,0) -> 0.01057659 | F18: =IFERROR(HistoricaIFS!F24,0) -> 0.010622099 | G18: =IFERROR(HistoricaIFS!G24,0) -> 0.015054563 | H18: =IFERROR(HistoricaIFS!H24,0) -> 0.017154412 | I18: =IFERROR(HistoricaIFS!I24,0) -> 0.016079405 | J18: =IFERROR(HistoricaIFS!J24,0) -> 0.014913085 | ... L18: =IFERROR(HistoricaIFS!L24,0) -> 0.014648729 | N18: =IFERROR(AVERAGE(D18:L18),0) -> 0.013797816 | O18: =IFERROR(MEDIAN(D18:L18),0) -> 0.014648729
B19: OperatinMargine%Sales | C19: =C13 -> 0.05530094 | D19: =D13 -> 0.060463787 | E19: =E13 -> 0.075454328 | F19: =F13 -> 0.068664982 | G19: =G13 -> 0.067742921 | H19: =H13 -> 0.053390912 | I19: =I13 -> 0.06296691 | J19: =J13 -> 0.068452851 | ... L19: =L13 -> 0.059899879 | N19: =IFERROR(AVERAGE(D19:L19),0) -> 0.064704587 | O19: =IFERROR(MEDIAN(D19:L19),0) -> 0.065304714
B21: Return on Capital Employed | C21: =IFERROR((HistoricaIFS!C17-HistoricaIFS!C23)/SUM(HistoricaIFS!C47:C49),0) -> 0.20865312 | D21: =IFERROR((HistoricaIFS!D17-HistoricaIFS!D23)/SUM(HistoricaIFS!D47:D49),0) -> 0.15758461 | E21: =IFERROR((HistoricaIFS!E17-HistoricaIFS!E23)/SUM(HistoricaIFS!E47:E49),0) -> 0.23370984 | F21: =IFERROR((HistoricaIFS!F17-HistoricaIFS!F23)/SUM(HistoricaIFS!F47:F49),0) -> 0.22597175 | G21: =IFERROR((HistoricaIFS!G17-HistoricaIFS!G23)/SUM(HistoricaIFS!G47:G49),0) -> 0.15367658 | H21: =IFERROR((HistoricaIFS!H17-HistoricaIFS!H23)/SUM(HistoricaIFS!H47:H49),0) -> 0.10580674 | I21: =IFERROR((HistoricaIFS!I17-HistoricaIFS!I23)/SUM(HistoricaIFS!I47:I49),0) -> 0.13991824 | J21: =IFERROR((HistoricaIFS!J17-HistoricaIFS!J23)/SUM(HistoricaIFS!J47:J49),0) -> 0.17940183 | ... L21: =IFERROR((HistoricaIFS!L17-HistoricaIFS!L23)/SUM(HistoricaIFS!L47:L49),0) -> 0.16294016 | N21: =IFERROR(AVERAGE(D21:L21),0) -> 0.17044054 | O21: =IFERROR(MEDIAN(D21:L21),0) -> 0.16294016
B22: Retained Earning | C22: =HistoricaIFS!C43 -> 1 | D22: =HistoricaIFS!D43 -> 1 | E22: =HistoricaIFS!E43 -> 1 | F22: =HistoricaIFS!F43 -> 1 | G22: =HistoricaIFS!G43 -> 1 | H22: =HistoricaIFS!H43 -> 1 | I22: =HistoricaIFS!I43 -> 1 | J22: =HistoricaIFS!J43 -> 1 | ... L22: =HistoricaIFS!L43 -> 1 | N22: =IFERROR(AVERAGE(D22:L22),0) -> 1 | O22: =IFERROR(MEDIAN(D22:L22),0) -> 1
B23: Return On Equity% | C23: =HistoricaIFS!C32/SUM(HistoricaIFS!C47:C48) -> 0.21062324 | D23: =HistoricaIFS!D32/SUM(HistoricaIFS!D47:D48) -> 0.12461671 | E23: =HistoricaIFS!E32/SUM(HistoricaIFS!E47:E48) -> 0.17268181 | F23: =HistoricaIFS!F32/SUM(HistoricaIFS!F47:F48) -> 0.16152986 | G23: =HistoricaIFS!G32/SUM(HistoricaIFS!G47:G48) -> 0.11742875 | H23: =HistoricaIFS!H32/SUM(HistoricaIFS!H47:H48) -> 0.090242627 | I23: =HistoricaIFS!I32/SUM(HistoricaIFS!I47:I48) -> 0.10912336 | J23: =HistoricaIFS!J32/SUM(HistoricaIFS!J47:J48) -> 0.14792925 | ... L23: =HistoricaIFS!L32/SUM(HistoricaIFS!L47:L48) -> 0.12637911 | N23: =IFERROR(AVERAGE(D23:L23),0) -> 0.13173015 | O23: =IFERROR(MEDIAN(D23:L23),0) -> 0.12637911
B24: Self sustained Growth Rate | C24: =IFERROR(C22*C23,0) -> 0.21062324 | D24: =IFERROR(D22*D23,0) -> 0.12461671 | E24: =IFERROR(E22*E23,0) -> 0.17268181 | F24: =IFERROR(F22*F23,0) -> 0.16152986 | G24: =IFERROR(G22*G23,0) -> 0.11742875 | H24: =IFERROR(H22*H23,0) -> 0.090242627 | I24: =IFERROR(I22*I23,0) -> 0.10912336 | J24: =IFERROR(J22*J23,0) -> 0.14792925 | ... L24: =IFERROR(L22*L23,0) -> 0.12637911 | N24: =IFERROR(AVERAGE(D24:L24),0) -> 0.13173015 | O24: =IFERROR(MEDIAN(D24:L24),0) -> 0.12637911
B25: Intrest Coverage Ratio | C25: =IFERROR((HistoricaIFS!C17-HistoricaIFS!C23)/HistoricaIFS!C20,0) -> 6.1969564 | D25: =IFERROR((HistoricaIFS!D17-HistoricaIFS!D23)/HistoricaIFS!D20,0) -> 6.8975242 | E25: =IFERROR((HistoricaIFS!E17-HistoricaIFS!E23)/HistoricaIFS!E20,0) -> 20.051394 | F25: =IFERROR((HistoricaIFS!F17-HistoricaIFS!F23)/HistoricaIFS!F20,0) -> 30.095742 | G25: =IFERROR((HistoricaIFS!G17-HistoricaIFS!G23)/HistoricaIFS!G20,0) -> 25.374711 | H25: =IFERROR((HistoricaIFS!H17-HistoricaIFS!H23)/HistoricaIFS!H20,0) -> 31.94886 | I25: =IFERROR((HistoricaIFS!I17-HistoricaIFS!I23)/HistoricaIFS!I20,0) -> 37.261015 | J25: =IFERROR((HistoricaIFS!J17-HistoricaIFS!J23)/HistoricaIFS!J20,0) -> 44.502299 | ... L25: =IFERROR((HistoricaIFS!L17-HistoricaIFS!L23)/HistoricaIFS!L20,0) -> 52.19568 | N25: =IFERROR(AVERAGE(D25:L25),0) -> 34.042743 | O25: =IFERROR(MEDIAN(D25:L25),0) -> 31.94886
B27: Debtor Turnover Ratio | C27: =IFERROR(HistoricaIFS!C5/HistoricaIFS!C61,0) -> 1019.4489 | D27: =IFERROR(HistoricaIFS!D5/HistoricaIFS!D61,0) -> 566.55714 | E27: =IFERROR(HistoricaIFS!E5/HistoricaIFS!E61,0) -> 448.48449 | F27: =IFERROR(HistoricaIFS!F5/HistoricaIFS!F61,0) -> 310.77396 | G27: =IFERROR(HistoricaIFS!G5/HistoricaIFS!G61,0) -> 1272.133 | H27: =IFERROR(HistoricaIFS!H5/HistoricaIFS!H61,0) -> 553.99403 | I27: =IFERROR(HistoricaIFS!I5/HistoricaIFS!I61,0) -> 463.09269 | J27: =IFERROR(HistoricaIFS!J5/HistoricaIFS!J61,0) -> 689.18211 | ... L27: =IFERROR(HistoricaIFS!L5/HistoricaIFS!L61,0) -> 385.9682 | N27: =IFERROR(AVERAGE(D27:L27),0) -> 555.05133 | O27: =IFERROR(MEDIAN(D27:L27),0) -> 463.09269
B28: Creditor Turnover Ratio | C28: =IFERROR(HistoricaIFS!C5/HistoricaIFS!C50,0) -> 22.078708 | D28: =IFERROR(HistoricaIFS!D5/HistoricaIFS!D50,0) -> 24.777583 | E28: =IFERROR(HistoricaIFS!E5/HistoricaIFS!E50,0) -> 27.843384 | F28: =IFERROR(HistoricaIFS!F5/HistoricaIFS!F50,0) -> 27.865329 | G28: =IFERROR(HistoricaIFS!G5/HistoricaIFS!G50,0) -> 37.498605 | H28: =IFERROR(HistoricaIFS!H5/HistoricaIFS!H50,0) -> 22.383079 | I28: =IFERROR(HistoricaIFS!I5/HistoricaIFS!I50,0) -> 27.020473 | J28: =IFERROR(HistoricaIFS!J5/HistoricaIFS!J50,0) -> 30.979405 | ... L28: =IFERROR(HistoricaIFS!L5/HistoricaIFS!L50,0) -> 28.739112 | N28: =IFERROR(AVERAGE(D28:L28),0) -> 28.231825 | O28: =IFERROR(MEDIAN(D28:L28),0) -> 27.843384
B29: Inventry Turnover Ratio | C29: =IFERROR(HistoricaIFS!C5/HistoricaIFS!C62,0) -> 12.779348 | D29: =IFERROR(HistoricaIFS!D5/HistoricaIFS!D62,0) -> 12.55164 | E29: =IFERROR(HistoricaIFS!E5/HistoricaIFS!E62,0) -> 12.921226 | F29: =IFERROR(HistoricaIFS!F5/HistoricaIFS!F62,0) -> 12.435595 | G29: =IFERROR(HistoricaIFS!G5/HistoricaIFS!G62,0) -> 12.770977 | H29: =IFERROR(HistoricaIFS!H5/HistoricaIFS!H62,0) -> 10.738458 | I29: =IFERROR(HistoricaIFS!I5/HistoricaIFS!I62,0) -> 11.294244 | J29: =IFERROR(HistoricaIFS!J5/HistoricaIFS!J62,0) -> 13.2079 | ... L29: =IFERROR(HistoricaIFS!L5/HistoricaIFS!L62,0) -> 11.767188 | N29: =IFERROR(AVERAGE(D29:L29),0) -> 12.29105 | O29: =IFERROR(MEDIAN(D29:L29),0) -> 12.55164
B30: Fixed Asset Turnover | C30: =IFERROR(HistoricaIFS!C5/HistoricaIFS!C54,0) -> 4.1001567 | D30: =IFERROR(HistoricaIFS!D5/HistoricaIFS!D54,0) -> 4.6155368 | E30: =IFERROR(HistoricaIFS!E5/HistoricaIFS!E54,0) -> 4.4215684 | F30: =IFERROR(HistoricaIFS!F5/HistoricaIFS!F54,0) -> 4.5460995 | G30: =IFERROR(HistoricaIFS!G5/HistoricaIFS!G54,0) -> 4.1812499 | H30: =IFERROR(HistoricaIFS!H5/HistoricaIFS!H54,0) -> 3.4446781 | I30: =IFERROR(HistoricaIFS!I5/HistoricaIFS!I54,0) -> 3.3451623 | J30: =IFERROR(HistoricaIFS!J5/HistoricaIFS!J54,0) -> 3.7775791 | ... L30: =IFERROR(HistoricaIFS!L5/HistoricaIFS!L54,0) -> 3.6626166 | N30: =IFERROR(AVERAGE(D30:L30),0) -> 3.9756071 | O30: =IFERROR(MEDIAN(D30:L30),0) -> 3.7859732
B31: Capital Turnover | C31: =IFERROR(HistoricaIFS!C5/SUM(HistoricaIFS!C47:C48),0) -> 5.6455763 | D31: =IFERROR(HistoricaIFS!D5/SUM(HistoricaIFS!D47:D48),0) -> 3.0969238 | E31: =IFERROR(HistoricaIFS!E5/SUM(HistoricaIFS!E47:E48),0) -> 3.2197556 | F31: =IFERROR(HistoricaIFS!F5/SUM(HistoricaIFS!F47:F48),0) -> 3.5802593 | G31: =IFERROR(HistoricaIFS!G5/SUM(HistoricaIFS!G47:G48),0) -> 2.2446556 | H31: =IFERROR(HistoricaIFS!H5/SUM(HistoricaIFS!H47:H48),0) -> 1.9815852 | I31: =IFERROR(HistoricaIFS!I5/SUM(HistoricaIFS!I47:I48),0) -> 2.2647379 | J31: =IFERROR(HistoricaIFS!J5/SUM(HistoricaIFS!J47:J48),0) -> 2.6643671 | ... L31: =IFERROR(HistoricaIFS!L5/SUM(HistoricaIFS!L47:L48),0) -> 2.7701485 | N31: =IFERROR(AVERAGE(D31:L31),0) -> 2.7265256 | O31: =IFERROR(MEDIAN(D31:L31),0) -> 2.7162969
B33: Debtors Days | C33: =IFERROR(365/C27,0) -> 0.35803657 | D33: =IFERROR(365/D27,0) -> 0.64424216 | E33: =IFERROR(365/E27,0) -> 0.81385201 | F33: =IFERROR(365/F27,0) -> 1.1744871 | G33: =IFERROR(365/G27,0) -> 0.28691969 | H33: =IFERROR(365/H27,0) -> 0.65885186 | I33: =IFERROR(365/I27,0) -> 0.78817914 | J33: =IFERROR(365/J27,0) -> 0.52961328 | ... L33: =IFERROR(365/L27,0) -> 0.94567375 | N33: =IFERROR(AVERAGE(D33:L33),0) -> 0.78193965 | O33: =IFERROR(MEDIAN(D33:L33),0) -> 0.78817914
B34: Payable Days | C34: =IFERROR(365/C28,0) -> 16.531765 | D34: =IFERROR(365/D28,0) -> 14.731057 | E34: =IFERROR(365/E28,0) -> 13.109039 | F34: =IFERROR(365/F28,0) -> 13.098715 | G34: =IFERROR(365/G28,0) -> 9.7336953 | H34: =IFERROR(365/H28,0) -> 16.306962 | I34: =IFERROR(365/I28,0) -> 13.508276 | J34: =IFERROR(365/J28,0) -> 11.782021 | ... L34: =IFERROR(365/L28,0) -> 12.700462 | N34: =IFERROR(AVERAGE(D34:L34),0) -> 13.16656 | O34: =IFERROR(MEDIAN(D34:L34),0) -> 13.109039
B35: Inventory Days | C35: =IFERROR(365/C29,0) -> 28.561708 | D35: =IFERROR(365/D29,0) -> 29.079864 | E35: =IFERROR(365/E29,0) -> 28.248094 | F35: =IFERROR(365/F29,0) -> 29.351229 | G35: =IFERROR(365/G29,0) -> 28.58043 | H35: =IFERROR(365/H29,0) -> 33.989983 | I35: =IFERROR(365/I29,0) -> 32.317348 | J35: =IFERROR(365/J29,0) -> 27.634976 | ... L35: =IFERROR(365/L29,0) -> 31.018456 | N35: =IFERROR(AVERAGE(D35:L35),0) -> 29.827163 | O35: =IFERROR(MEDIAN(D35:L35),0) -> 29.079864
B36: Cash Conversion Cycle | C36: =C34-SUM(C33,C35) -> -12.38798 | D36: =D34-SUM(D33,D35) -> -14.993049 | E36: =E34-SUM(E33,E35) -> -15.952908 | F36: =F34-SUM(F33,F35) -> -17.427001 | G36: =G34-SUM(G33,G35) -> -19.133654 | H36: =H34-SUM(H33,H35) -> -18.341873 | I36: =I34-SUM(I33,I35) -> -19.597251 | J36: =J34-SUM(J33,J35) -> -16.382568 | ... L36: =L34-SUM(L33,L35) -> -19.263668 | N36: =IFERROR(AVERAGE(D36:L36),0) -> -17.442542 | O36: =IFERROR(MEDIAN(D36:L36),0) -> -17.427001
B38: CFO/ Sales | C38: =IFERROR(HistoricaIFS!C81/HistoricaIFS!C5,0) -> 0.032503239 | D38: =IFERROR(HistoricaIFS!D81/HistoricaIFS!D5,0) -> 0.028408852 | E38: =IFERROR(HistoricaIFS!E81/HistoricaIFS!E5,0) -> 0.039246468 | F38: =IFERROR(HistoricaIFS!F81/HistoricaIFS!F5,0) -> 0.033392453 | G38: =IFERROR(HistoricaIFS!G81/HistoricaIFS!G5,0) -> 0.045074024 | H38: =IFERROR(HistoricaIFS!H81/HistoricaIFS!H5,0) -> 0.051194836 | I38: =IFERROR(HistoricaIFS!I81/HistoricaIFS!I5,0) -> 0.055494093 | J38: =IFERROR(HistoricaIFS!J81/HistoricaIFS!J5,0) -> 0.039169403 | ... L38: =IFERROR(HistoricaIFS!L81/HistoricaIFS!L5,0) -> 0.056454011 | N38: =IFERROR(AVERAGE(D38:L38),0) -> 0.042784041 | O38: =IFERROR(MEDIAN(D38:L38),0) -> 0.039246468
B39: CFO/Total Asset | C39: =IFERROR(HistoricaIFS!C81/HistoricaIFS!C66,0) -> 0.089954732 | D39: =IFERROR(HistoricaIFS!D81/HistoricaIFS!D66,0) -> 0.058082787 | E39: =IFERROR(HistoricaIFS!E81/HistoricaIFS!E66,0) -> 0.10445769 | F39: =IFERROR(HistoricaIFS!F81/HistoricaIFS!F66,0) -> 0.095353651 | G39: =IFERROR(HistoricaIFS!G81/HistoricaIFS!G66,0) -> 0.092827521 | H39: =IFERROR(HistoricaIFS!H81/HistoricaIFS!H66,0) -> 0.090515963 | I39: =IFERROR(HistoricaIFS!I81/HistoricaIFS!I66,0) -> 0.11111125 | J39: =IFERROR(HistoricaIFS!J81/HistoricaIFS!J66,0) -> 0.092684037 | ... L39: =IFERROR(HistoricaIFS!L81/HistoricaIFS!L66,0) -> 0.13782875 | N39: =IFERROR(AVERAGE(D39:L39),0) -> 0.096745726 | O39: =IFERROR(MEDIAN(D39:L39),0) -> 0.092827521
B40: CFO/Total Debt | C40: =IFERROR(HistoricaIFS!C81/HistoricaIFS!C49,0) -> 0.23399366 | D40: =IFERROR(HistoricaIFS!D81/HistoricaIFS!D49,0) -> 0.22573665 | E40: =IFERROR(HistoricaIFS!E81/HistoricaIFS!E49,0) -> 1.3431986 | F40: =IFERROR(HistoricaIFS!F81/HistoricaIFS!F49,0) -> 0.95408127 | G40: =IFERROR(HistoricaIFS!G81/HistoricaIFS!G49,0) -> 3.3644467 | H40: =IFERROR(HistoricaIFS!H81/HistoricaIFS!H49,0) -> 3.1473606 | I40: =IFERROR(HistoricaIFS!I81/HistoricaIFS!I49,0) -> 2.6571243 | J40: =IFERROR(HistoricaIFS!J81/HistoricaIFS!J49,0) -> 2.6097235 | ... L40: =IFERROR(HistoricaIFS!L81/HistoricaIFS!L49,0) -> 4.08848 | N40: =IFERROR(AVERAGE(D40:L40),0) -> 2.392355 | O40: =IFERROR(MEDIAN(D40:L40),0) -> 2.6571243

Sheet Cash Flow Data
C3: 41699 | D3: 42064 | E3: 42430 | F3: 42795 | G3: 43160 | H3: 43525 | I3: 43891 | J3: 44256 | K3: 44621 | L3: 44986 | M3: 45352 | N3: 45717
B4: Cash from Operating Activity - | C4: 198 | D4: 222 | E4: 433 | F4: 455 | G4: 730 | H4: 807 | I4: 1280 | J4: 1375 | K4: 1372 | L4: 2630 | M4: 2746 | N4: 2463
B5: Profit from operations | C5: 356 | D5: 474 | E5: 666 | F5: 984 | G5: 1375 | H5: 1659 | I5: 2149 | J5: 1764 | K5: 2515 | L5: 3659 | M5: 4131 | N5: 4535
B6: Receivables | C6: 4 | D6: 2 | E6: -1 | F6: 54 | G6: -13 | H6: -31 | I6: 45 | J6: -24 | K6: -23 | L6: 5 | M6: -104 | N6: 13
B7: Inventory | C7: -102 | D7: -161 | E7: -132 | F7: -276 | G7: -212 | H7: -445 | I7: -339 | J7: -301 | K7: -494 | L7: -501 | M7: -684 | N7: -1117
B8: Payables | C8: 28 | D8: -4 | E8: 72 | F8: 0 | G8: 55 | H8: 146 | I8: -30 | J8: 145 | K8: 11 | L8: 165 | M8: 231 | N8: 86
B9: Loans Advances | C9: -18 | D9: -5 | E9: 0 | F9: 0 | G9: 0 | H9: 0 | I9: 0 | J9: 0 | K9: 0 | L9: 0 | M9: 0 | N9: 0
B10: Operating investments | C10: 0 | D10: 0 | E10: 0 | F10: -2 | G10: -62 | H10: 52 | I10: 2 | J10: 12 | K10: -3 | L10: 0 | M10: 0 | N10: 0
B11: Other WC items | C11: 6 | D11: 16 | E11: -7 | F11: -46 | G11: -11 | H11: -72 | I11: -54 | J11: 41 | K11: -73 | L11: 12 | M11: -87 | N11: -94
B12: Working capital changes | C12: -83 | D12: -152 | E12: -69 | F12: -270 | G12: -243 | H12: -351 | I12: -376 | J12: -127 | K12: -582 | L12: -320 | M12: -644 | N12: -1113
B13: Direct taxes | C13: -75 | D13: -100 | E13: -164 | F13: -258 | G13: -403 | H13: -502 | I13: -492 | J13: -262 | K13: -560 | L13: -709 | M13: -742 | N13: -959
B14: Cash from Investing Activity - | C14: -270 | D14: -474 | E14: -633 | F14: -2482 | G14: 464 | H14: -958 | I14: -4657 | J14: -1110 | K14: -1289 | L14: -2313 | M14: -2468 | N14: -2185
B15: Fixed assets purchased | C15: -272 | D15: -477 | E15: 0 | F15: -645 | G15: -916 | H15: -1417 | I15: -1712 | J15: -2029 | K15: -2410 | L15: -2212 | M15: -2731 | N15: -3423
... B35: Net Cash Flow | C35: -7 | D35: -17 | E35: -3 | F35: -1 | G35: 34 | H35: 57 | I35: -19 | J35: 86 | K35: -96 | L35: 112 | M35: 130 | N35: 18

Sheet Rm 
B3: Return On Market
B4: Year | C4: Annual
B5: 2000 | C5: -14.65 | E5: Average Return | G5: =(AVERAGE(C5:C29))/100 -> 0.153348
B6: 2001 | C6: -16.18 | E6: Dividend yeild | G6: 1.24% 1
B7: 2002 | C7: 3.25 | E7: Total return | G7: =SUM(G5:G6) -> 0.153348
B8: 2003 | C8: 71.9
B9: 2004 | C9: 10.68
B10: 2005 | C10: 36.34
B11: 2006 | C11: 39.83
B12: 2007 | C12: 54.77
B13: 2008 | C13: -51.79
B14: 2009 | C14: 75.76
B15: 2010 | C15: 17.95
B16: 2011 | C16: -24.62
B17: 2012 | C17: 27.7
B18: 2013 | C18: 6.76
B19: 2014 | C19: 31.39
... B29: 2024 | C29: 8.75

Sheet Raw FS
B2: Particulars | C2: 41699 | D2: 42064 | E2: 42430 | F2: 42795 | G2: 43160 | H2: 43525 | I2: 43891 | J2: 44256 | K2: 44621 | L2: 44986 | M2: 45352 | N2: 45717
B4: Equity Capital | C4: 547 | D4: 562 | E4: 562 | F4: 624 | G4: 624 | H4: 624 | I4: 648 | J4: 648 | K4: 648 | L4: 648 | M4: 651 | N4: 651
B5: Reserves | C5: 409 | D5: 638 | E5: 959 | F5: 3218 | G5: 4045 | H5: 4963 | I5: 10432 | J5: 11536 | K5: 13030 | L5: 15430 | M5: 18047 | N5: 20777
B6: Borrowings -
B7: Long term Borrowings | E7: 908 | F7: 981 | G7: 246 | H7: 126 | I7: 0 | J7: 0 | K7: 0 | L7: 0 | M7: 0 | N7: 0
B8: Short term Borrowings | E8: 129 | F8: 139 | G8: 7 | H8: 304 | I8: 4 | J8: 0 | K8: 0 | L8: 0 | M8: 0 | N8: 0
B9: Lease Liabilities | E9: 0 | F9: 0 | G9: 0 | H9: 0 | I9: 295 | J9: 393 | K9: 647 | L9: 643 | M9: 592 | N9: 820
B10: Other Borrowings | C10: 641 | D10: 904 | E10: 155 | F10: 378 | G10: 186 | H10: 270 | I10: 34 | J10: 0 | K10: 0 | L10: 0 | M10: 0 | N10: 0
B11: Other Liabilities -
B12: Non controlling int | C12: 0 | D12: 0 | E12: 0 | F12: 0 | G12: 1 | H12: 1 | I12: 0 | J12: 0 | K12: 0 | L12: 0 | M12: 0 | N12: -1
B13: Trade Payables | C13: 123 | D13: 119 | E13: 194 | F13: 261 | G13: 317 | H13: 463 | I13: 433 | J13: 578 | K13: 589 | L13: 754 | M13: 985 | N13: 1071
B14: Other liability items | C14: 89 | D14: 133 | E14: 194 | F14: 219 | G14: 222 | H14: 254 | I14: 229 | J14: 500 | K14: 557 | L14: 629 | M14: 898 | N14: 996
B15: Total Liabilities | C15: 1808 | D15: 2355 | E15: 3102 | F15: 5819 | G15: 5648 | H15: 7006 | I15: 12076 | J15: 13655 | K15: 15471 | L15: 18105 | M15: 21172 | N15: 24313
B17: Fixed Assets - | C17: 2562 | D17: 2660 | E17: 3416 | F17: 3304 | G17: 3732 | H17: 6497 | I17: 6272 | J17: 5859 | K17: 5519 | L17: 5770 | M17: 7147 | N17: 9220
B18: Land | C18: 460 | D18: 602 | E18: 784 | F18: 1044 | G18: 1438 | H18: 2028 | I18: 2740 | J18: 3483 | K18: 4527 | L18: 5519 | M18: 6904 | N18: 8595
B19: Building | C19: 717 | D19: 946 | E19: 1162 | F19: 1379 | G19: 1757 | H19: 2173 | I19: 3139 | J19: 3649 | K19: 4938 | L19: 6201 | M19: 7062 | N19: 8256
B20: Plant Machinery | C20: 39 | D20: 51 | E20: 59 | F20: 88 | G20: 124 | H20: 191 | I20: 272 | J20: 352 | K20: 491 | L20: 656 | M20: 870 | N20: 1141
B21: Equipments | C21: 9 | D21: 12 | E21: 11 | F21: 16 | G21: 21 | H21: 29 | I21: 39 | J21: 50 | K21: 73 | L21: 85 | M21: 97 | N21: 115
B22: Computers | C22: 23 | D22: 30 | E22: 21 | F22: 30 | G22: 53 | H22: 76 | I22: 95 | J22: 119 | K22: 153 | L22: 190 | M22: 219 | N22: 276
B23: Furniture n fittings | C23: 135 | D23: 172 | E23: 143 | F23: 202 | G23: 265 | H23: 357 | I23: 476 | J23: 581 | K23: 772 | L23: 968 | M23: 1205 | N23: 1515
B24: Vehicles | C24: 4 | D24: 6 | E24: 6 | F24: 6 | G24: 2 | H24: 3 | I24: 4 | J24: 4 | K24: 3 | L24: 15 | M24: 17 | N24: 6
... B37: Total Assets | C37: 1808 | D37: 2355 | E37: 3102 | F37: 5819 | G37: 5648 | H37: 7006 | I37: 12076 | J37: 13655 | K37: 15471 | L37: 18105 | M37: 21172 | N37: 24313

Sheet Intresnsic Growth
B2: Calculation Of ROIC | E2: 44256 | F2: 44621 | G2: 44986 | H2: 45352 | I2: 45717
B4: ='Raw FS'!B32 -> Inventories | E4: ='Raw FS'!J32 -> 2248 | F4: ='Raw FS'!K32 -> 2743 | G4: ='Raw FS'!L32 -> 3243 | H4: ='Raw FS'!M32 -> 3927 | I4: ='Raw FS'!N32 -> 5044
B5: ='Raw FS'!B33 -> Trade receivables | E5: ='Raw FS'!J33 -> 44 | F5: ='Raw FS'!K33 -> 67 | G5: ='Raw FS'!L33 -> 62 | H5: ='Raw FS'!M33 -> 166 | I5: ='Raw FS'!N33 -> 154
B6: ='Raw FS'!B35 -> Loans n Advances | E6: ='Raw FS'!J35 -> 81 | F6: ='Raw FS'!K35 -> 109 | G6: ='Raw FS'!L35 -> 97 | H6: ='Raw FS'!M35 -> 105 | I6: ='Raw FS'!N35 -> 126
B7: ='Raw FS'!B36 -> Other asset items | E7: ='Raw FS'!J36 -> 1806 | F7: ='Raw FS'!K36 -> 1859 | G7: ='Raw FS'!L36 -> 922 | H7: ='Raw FS'!M36 -> 1879 | I7: ='Raw FS'!N36 -> 1321
B8: Total Current asset | E8: =SUM(E4:E7) -> 4179 | F8: =SUM(F4:F7) -> 4778 | G8: =SUM(G4:G7) -> 4324 | H8: =SUM(H4:H7) -> 6077 | I8: =SUM(I4:I7) -> 6645
B10: Current Liablities
B11: ='Raw FS'!B13 -> Trade Payables | E11: ='Raw FS'!J13 -> 578 | F11: ='Raw FS'!K13 -> 589 | G11: ='Raw FS'!L13 -> 754 | H11: ='Raw FS'!M13 -> 985 | I11: ='Raw FS'!N13 -> 1071
B12: ='Raw FS'!B14 -> Other liability items | E12: ='Raw FS'!J14 -> 500 | F12: ='Raw FS'!K14 -> 557 | G12: ='Raw FS'!L14 -> 629 | H12: ='Raw FS'!M14 -> 898 | I12: ='Raw FS'!N14 -> 996
A13: # | B13: Total Current Liablities | E13: =SUM(E11:E12) -> 1078 | F13: =SUM(F11:F12) -> 1146 | G13: =SUM(G11:G12) -> 1383 | H13: =SUM(H11:H12) -> 1883 | I13: =SUM(I11:I12) -> 2067
A15: # | B15: Net Working Capital | E15: =E8-E13 -> 3101 | F15: =F8-F13 -> 3632 | G15: =G8-G13 -> 2941 | H15: =H8-H13 -> 4194 | I15: =I8-I13 -> 4578
A17: # | B17: Non Current Asset
B18: ='Raw FS'!B18 -> Land | E18: ='Raw FS'!J18 -> 3483 | F18: ='Raw FS'!K18 -> 4527 | G18: ='Raw FS'!L18 -> 5519 | H18: ='Raw FS'!M18 -> 6904 | I18: ='Raw FS'!N18 -> 8595
B19: ='Raw FS'!B19 -> Building | E19: ='Raw FS'!J19 -> 3649 | F19: ='Raw FS'!K19 -> 4938 | G19: ='Raw FS'!L19 -> 6201 | H19: ='Raw FS'!M19 -> 7062 | I19: ='Raw FS'!N19 -> 8256
B20: ='Raw FS'!B20 -> Plant Machinery | E20: ='Raw FS'!J20 -> 352 | F20: ='Raw FS'!K20 -> 491 | G20: ='Raw FS'!L20 -> 656 | H20: ='Raw FS'!M20 -> 870 | I20: ='Raw FS'!N20 -> 1141
B21: ='Raw FS'!B21 -> Equipments | E21: ='Raw FS'!J21 -> 50 | F21: ='Raw FS'!K21 -> 73 | G21: ='Raw FS'!L21 -> 85 | H21: ='Raw FS'!M21 -> 97 | I21: ='Raw FS'!N21 -> 115
B22: ='Raw FS'!B22 -> Computers | E22: ='Raw FS'!J22 -> 119 | F22: ='Raw FS'!K22 -> 153 | G22: ='Raw FS'!L22 -> 190 | H22: ='Raw FS'!M22 -> 219 | I22: ='Raw FS'!N22 -> 276
B23: ='Raw FS'!B23 -> Furniture n fittings | E23: ='Raw FS'!J23 -> 581 | F23: ='Raw FS'!K23 -> 772 | G23: ='Raw FS'!L23 -> 968 | H23: ='Raw FS'!M23 -> 1205 | I23: ='Raw FS'!N23 -> 1515
B24: ='Raw FS'!B25 -> Intangible Assets | E24: ='Raw FS'!J25 -> 78 | F24: ='Raw FS'!K25 -> 78 | G24: ='Raw FS'!L25 -> 78 | H24: ='Raw FS'!M25 -> 78 | I24: ='Raw FS'!N25 -> 78
B25: ='Raw FS'!B26 -> Other fixed assets | E25: ='Raw FS'!J26 -> 81 | F25: ='Raw FS'!K26 -> 91 | G25: ='Raw FS'!L26 -> 105 | H25: ='Raw FS'!M26 -> 119 | I25: ='Raw FS'!N26 -> 124
B26: Gross Block | E26: =SUM(E18:E25) -> 8393 | F26: =SUM(F18:F25) -> 11123 | G26: =SUM(G18:G25) -> 13802 | H26: =SUM(H18:H25) -> 16554 | I26: =SUM(I18:I25) -> 20100
B27: ='Raw FS'!B28 -> Accumulated Depreciation | E27: ='Raw FS'!J28 -> 1387 | F27: ='Raw FS'!K28 -> 1867 | G27: ='Raw FS'!L28 -> 2476 | H27: ='Raw FS'!M28 -> 3156 | I27: ='Raw FS'!N28 -> 3900
A28: # | B28: Net Non Current Asset | E28: =E26-E27 -> 7006 | F28: =F26-F27 -> 9256 | G28: =G26-G27 -> 11326 | H28: =H26-H27 -> 13398 | I28: =I26-I27 -> 16200
A30: # | B30: Invested Capital | E30: =E28+E15 -> 10107 | F30: =F28+F15 -> 12888 | G30: =G28+G15 -> 14267 | H30: =H28+H15 -> 17592 | I30: =I28+I15 -> 20778
B31: EBIT | E31: =HistoricaIFS!H26+HistoricaIFS!H20 -> 1330.67 | F31: =HistoricaIFS!I26+HistoricaIFS!I20 -> 2004.27 | G31: =HistoricaIFS!J26+HistoricaIFS!J20 -> 2999.9 | H31: =HistoricaIFS!K26+HistoricaIFS!K20 -> 3374.88 | I31: =HistoricaIFS!L26+HistoricaIFS!L20 -> 3624.99
A33: # | B33: ROIC | E33: =E31/E30 -> 0.13165826 | F33: =F31/F30 -> 0.15551443 | G33: =G31/G30 -> 0.21026845 | H33: =H31/H30 -> 0.19184175 | I33: =I31/I30 -> 0.17446289
B35: Calculation Of Reinvestment Rate | E35: =E2 -> 44256 | F35: =F2 -> 44621 | G35: =G2 -> 44986 | H35: =H2 -> 45352 | I35: =I2 -> 45717
B37: Net capax | E37: =-SUM('Cash Flow Data'!H14:H15) -> 2375 | F37: =-SUM('Cash Flow Data'!I14:I15) -> 6369 | G37: =-SUM('Cash Flow Data'!J14:J15) -> 3139 | H37: =-SUM('Cash Flow Data'!K14:K15) -> 3699 | I37: =-SUM('Cash Flow Data'!L14:L15) -> 4525
B38: Change In Working Capital | F38: =F15-E15 -> 531 | G38: =G15-F15 -> -691 | H38: =H15-G15 -> 1253 | I38: =I15-H15 -> 384
B40: EBIT | E40: =E31 -> 1330.67 | F40: =F31 -> 2004.27 | G40: =G31 -> 2999.9 | H40: =H31 -> 3374.88 | I40: =I31 -> 3624.99
B41: Marginal Tax Rate | E41: 0.25 | F41: 0.25 | G41: 0.25 | H41: 0.25 | I41: 0.25
B42: EBIT(1-T) | E42: =E40*(1-E41) -> 998.0025 | F42: =F40*(1-F41) -> 1503.2025 | G42: =G40*(1-G41) -> 2249.925 | H42: =H40*(1-H41) -> 2531.16 | I42: =I40*(1-I41) -> 2718.7425
B44: Reinvestment | F44: =SUM(F37:F38) -> 6900 | G44: =SUM(G37:G38) -> 2448 | H44: =SUM(H37:H38) -> 4952 | I44: =SUM(I37:I38) -> 4909
B45: Reinstemnt Rate | F45: =F44/F42 -> 4.5901999 | G45: =G44/G42 -> 1.0880363 | H45: =H44/H42 -> 1.9564152 | I45: =I44/I42 -> 1.8056142
H47: 4 Year Average | I47: =AVERAGE(F45:I45) -> 2.3600664
H48: 4 Year Median | I48: =MEDIAN(F45:I45) -> 1.8810147
B51: Calculation Of Growth Rate | E51: =E35 -> 44256 | F51: =F35 -> 44621 | G51: =G35 -> 44986 | H51: =H35 -> 45352 | I51: =I35 -> 45717
B53: Reinstemnt Rate | F53: =F45 -> 4.5901999 | G53: =G45 -> 1.0880363 | H53: =H45 -> 1.9564152 | I53: =I45 -> 1.8056142
B54: =B33 -> ROIC | F54: =F33 -> 0.15551443 | G54: =G33 -> 0.21026845 | H54: =H33 -> 0.19184175 | I54: =I33 -> 0.17446289
B56: Intrensic Growth | F56: =F53*F54 -> 0.71384233 | G56: =G53*G54 -> 0.2287797 | H56: =H53*H54 -> 0.37532212 | I56: =I53*I54 -> 0.31501267

Sheet Comps Valuation 
B2: Comparable Of Company Valuation
B4: Market Data | J4: Financial | N4: Valuation
B5: Company | C5: Ticker | D5: Share Price | E5: Share Outstanding | F5: Equity Value | G5: Net Debt | H5: Enterprice Value | J5: Revenue | K5: EBITDA | L5: Net Income | N5: EV/Revenue | O5: EV/EBITDA | P5: P/E
B6: =DATA!C4 -> Avenue Super. | D6: =DATA!D4 -> 4358.2 | E6: =DATA!E4 -> 65.07 | F6: =D6*E6 -> 283588.07 | G6: =DATA!I4 -> 461.42 | H6: =F6+G6 -> 284049.49 | J6: =DATA!L4 -> 61648.61 | K6: =DATA!P4 -> 4667.2608 | L6: =DATA!N4 -> 2706.58 | N6: =H6/J6 -> 4.6075572 | O6: =H6/K6 -> 60.86 | P6: =F6/L6 -> 104.77727
B7: =DATA!C3 -> Eternal Ltd | D7: =DATA!D3 -> 318.4 | E7: =DATA!E3 -> 965.04 | F7: =D7*E7 -> 307268.74 | G7: =DATA!I3 -> -1569 | H7: =F7+G7 -> 305699.74 | J7: =DATA!L3 -> 23204 | K7: =DATA!P3 -> 1770.0176 | L7: =DATA!N3 -> 299 | N7: =H7/J7 -> 13.174441 | O7: =H7/K7 -> 172.71 | P7: =F7/L7 -> 1027.6546
B8: =DATA!C5 -> Trent | D8: =DATA!D5 -> 5370.5 | E8: =DATA!E5 -> 35.55 | F8: =D8*E8 -> 190921.27 | G8: =DATA!I5 -> 1897.35 | H8: =F8+G8 -> 192818.62 | J8: =DATA!L5 -> 17913.65 | K8: =DATA!P5 -> 3247.1981 | L8: =DATA!N5 -> 1567.9 | N8: =H8/J8 -> 10.763782 | O8: =H8/K8 -> 59.38 | P8: =F8/L8 -> 121.76878
B9: =DATA!C6 -> Swiggy | D9: =DATA!D6 -> 398.4 | E9: =DATA!E6 -> 249.36 | F9: =D9*E9 -> 99345.024 | G9: =DATA!I6 -> -1596.66 | H9: =F9+G9 -> 97748.364 | J9: =DATA!L6 -> 16965.52 | K9: =DATA!P6 -> -2803.2224 | L9: =DATA!N6 -> -3702.61 | N9: =H9/J9 -> 5.7615896 | O9: =H9/K9 -> -34.87 | P9: =F9/L9 -> -26.83108
B10: =DATA!C7 -> Info Edg.(India) | D10: =DATA!D7 -> 1365.4 | E10: =DATA!E7 -> 64.79 | F10: =D10*E10 -> 88464.266 | G10: =DATA!I7 -> 0.21 | H10: =F10+G10 -> 88464.476 | J10: =DATA!L7 -> 2963.71 | K10: =DATA!P7 -> 2047.3149 | L10: =DATA!N7 -> 1393.91 | N10: =H10/J10 -> 29.849235 | O10: =H10/K10 -> 43.21 | P10: =F10/L10 -> 63.464833
B11: =DATA!C8 -> Vishal Mega Mart | D11: =DATA!D8 -> 146.56 | E11: =DATA!E8 -> 466.14 | F11: =D11*E11 -> 68317.478 | G11: =DATA!I8 -> 1265.71 | H11: =F11+G11 -> 69583.188 | J11: =DATA!L8 -> 11260.37 | K11: =DATA!P8 -> 1691.7867 | L11: =DATA!N8 -> 687.89 | N11: =H11/J11 -> 6.1794762 | O11: =H11/K11 -> 41.13 | P11: =F11/L11 -> 99.314539
B12: =DATA!C9 -> FSN E-Commerce | D12: =DATA!D9 -> 215.14 | E12: =DATA!E9 -> 286.07 | F12: =D12*E12 -> 61545.1 | G12: =DATA!I9 -> 1103.44 | H12: =F12+G12 -> 62648.54 | J12: =DATA!L9 -> 8358.65 | K12: =DATA!P9 -> 547.72285 | L12: =DATA!N9 -> 82.9 | N12: =H12/J12 -> 7.4950548 | O12: =H12/K12 -> 114.38 | P12: =F12/L12 -> 742.40169
B13: =DATA!C10 -> Brainbees Solut. | D13: =DATA!D10 -> 370.45 | E13: =DATA!E10 -> 52.18 | F13: =D13*E13 -> 19330.081 | G13: =DATA!I10 -> -135.64 | H13: =F13+G13 -> 19194.441 | J13: =DATA!L10 -> 7870.11 | K13: =DATA!P10 -> 385.97307 | L13: =DATA!N10 -> -255.64 | N13: =H13/J13 -> 2.4389038 | O13: =H13/K13 -> 49.73 | P13: =F13/L13 -> -75.614462
B14: =DATA!C11 -> Vedant Fashions | D14: =DATA!D11 -> 743.6 | E14: =DATA!E11 -> 24.29 | F14: =D14*E14 -> 18062.044 | G14: =DATA!I11 -> 465.66 | H14: =F14+G14 -> 18527.704 | J14: =DATA!L11 -> 1427.86 | K14: =DATA!P11 -> 739.92428 | L14: =DATA!N11 -> 396.25 | N14: =H14/J14 -> 12.975855 | O14: =H14/K14 -> 25.04 | P14: =F14/L14 -> 45.582445
B15: =DATA!C12 -> A B Lifestyle | D15: =DATA!D12 -> 131.93 | E15: =DATA!E12 -> 122.03 | F15: =D15*E15 -> 16099.418 | G15: =DATA!I12 -> 2878.8 | H15: =F15+G15 -> 18978.218 | J15: =DATA!L12 -> 7829.96 | K15: =DATA!P12 -> 1293.6754 | L15: =DATA!N12 -> 59.6 | N15: =H15/J15 -> 2.423795 | O15: =H15/K15 -> 14.67 | P15: =F15/L15 -> 270.12446
B16: =DATA!C13 -> Indiamart Inter. | D16: =DATA!D13 -> 2545.8 | E16: =DATA!E13 -> 6 | F16: =D16*E16 -> 15274.8 | G16: =DATA!I13 -> -51.35 | H16: =F16+G16 -> 15223.45 | J16: =DATA!L13 -> 1429.2 | K16: =DATA!P13 -> 795.78934 | L16: =DATA!N13 -> 590.2 | N16: =H16/J16 -> 10.651728 | O16: =H16/K16 -> 19.13 | P16: =F16/L16 -> 25.880718
B17: =DATA!C14 -> Cartrade Tech | D17: =DATA!D14 -> 2320.9 | E17: =DATA!E14 -> 4.75 | F17: =D17*E17 -> 11024.275 | G17: =DATA!I14 -> 54.77 | H17: =F17+G17 -> 11079.045 | J17: =DATA!L14 -> 672.98 | K17: =DATA!P14 -> 252.65781 | L17: =DATA!N14 -> 169.43 | N17: =H17/J17 -> 16.462666 | O17: =H17/K17 -> 43.85 | P17: =F17/L17 -> 65.066842
B18: =DATA!C15 -> Medplus Health | D18: =DATA!D15 -> 813.8 | E18: =DATA!E15 -> 11.97 | F18: =D18*E18 -> 9741.186 | G18: =DATA!I15 -> 752.58 | H18: =F18+G18 -> 10493.766 | J18: =DATA!L15 -> 6189.86 | K18: =DATA!P15 -> 578.80673 | L18: =DATA!N15 -> 178.23 | N18: =H18/J18 -> 1.6953156 | O18: =H18/K18 -> 18.13 | P18: =F18/L18 -> 54.655142
B19: =DATA!C16 -> Aditya Bir. Fas. | D19: =DATA!D16 -> 75 | E19: =DATA!E16 -> 122.03 | F19: =D19*E19 -> 9152.25 | G19: =DATA!I16 -> 4243.72 | H19: =F19+G19 -> 13395.97 | J19: =DATA!L16 -> 9395.32 | K19: =DATA!P16 -> 1202.5108 | L19: =DATA!N16 -> -514.34 | N19: =H19/J19 -> 1.4258131 | O19: =H19/K19 -> 11.14 | P19: =F19/L19 -> -17.794163
B20: =DATA!C17 -> RattanIndia Ent | D20: =DATA!D17 -> 50.95 | E20: =DATA!E17 -> 138.23 | F20: =D20*E20 -> 7042.8185 | G20: =DATA!I17 -> 792.78 | H20: =F20+G20 -> 7835.5985 | J20: =DATA!L17 -> 7539.85 | K20: =DATA!P17 -> -160.4012 | L20: =DATA!N17 -> -268.22 | N20: =H20/J20 -> 1.0392247 | O20: =H20/K20 -> -48.85 | P20: =F20/L20 -> -26.257619
B22: High | N22: =MAX(N6:N20) -> 29.849235 | O22: =MAX(O6:O20) -> 172.71 | P22: =MAX(P6:P20) -> 1027.6546
B23: 75 th Percetile | N23: =QUARTILE(N6:N20,3) -> 11.869818 | O23: =QUARTILE(O6:O20,3) -> 54.555 | P23: =QUARTILE(P6:P20,3) -> 113.27303
B24: Average | N24: =AVERAGE(N6:N20) -> 8.4629625 | O24: =AVERAGE(O6:O20) -> 39.309333 | P24: =AVERAGE(P6:P20) -> 164.94627
B25: Median | N25: =MEDIAN(N6:N20) -> 6.1794762 | O25: =MEDIAN(O6:O20) -> 41.13 | P25: =MEDIAN(P6:P20) -> 63.464833
B26: 25 th Percentile | N26: =QUARTILE(N6:N20,1) -> 2.4313494 | O26: =QUARTILE(O6:O20,1) -> 16.4 | P26: =QUARTILE(P6:P20,1) -> 4.0432775
B27: Low | N27: =MIN(N6:N20) -> 1.0392247 | O27: =MIN(O6:O20) -> -48.85 | P27: =MIN(P6:P20) -> -75.614462
B30: AvenuesuperMart Comparable Valuation | N30: EV/Revenue | O30: EV/EBITDA | P30: P/E
B32: Implied Interprice Value | N32: =N25*J6 -> 380956.12 | O32: =O25*K6 -> 191964.44 | P32: =P34+P33 -> 172234.07
B33: Net Debt | N33: =G6 -> 461.42 | O33: 461.42 | P33: 461.42
B34: Implied Market Value | N34: =N32-N33 -> 380494.7 | O34: =O32-O33 -> 191503.02 | P34: =P25*L6 -> 171772.65
B35: Share Outstanding | N35: =E6 -> 65.07 | O35: 65.07 | P35: 65.07
B36: Implied Value Per share | N36: =N34/N35 -> 5847.4673 | O36: =O34/O35 -> 2943.0309 | P36: =P34/P35 -> 2639.8133
N38: =IF(N36<$D$6,"OverValued","UnderValued") -> UnderValued | O38: =IF(O36<$D$6,"OverValued","UnderValued") -> OverValued | P38: =IF(P36<$D$6,"OverValued","UnderValued") -> OverValued

Sheet DATA
B2: S.No. | C2: Name | D2: CMP Rs. | E2: No. Eq. Shares Cr. | F2: Market Cap | G2: Debt Rs.Cr. | H2: Cash End Rs.Cr. | I2: Net Debt | J2: EV | K2: EV Rs.Cr. | L2: Sales Rs.Cr. | M2: EV / EBITDA | N2: NP 12M Rs.Cr. | O2: Mar Cap Rs.Cr. | P2: EBITDA
B3: 1 | C3: Eternal Ltd | D3: 318.4 | E3: 965.04 | F3: =E3*D3 -> 307268.74 | G3: 2045 | H3: 3614 | I3: =G3-H3 -> -1569 | J3: =F3+G3-H3 -> 305699.74 | K3: 305698.16 | L3: 23204 | M3: 172.71 | N3: 299 | O3: 307267.16 | P3: =J3/M3 -> 1770.0176
B4: 2 | C4: Avenue Super. | D4: 4358.2 | E4: 65.07 | F4: =E4*D4 -> 283588.07 | G4: 819.62 | H4: 358.2 | I4: =G4-H4 -> 461.42 | J4: =F4+G4-H4 -> 284049.49 | K4: 284063.91 | L4: 61648.61 | M4: 60.86 | N4: 2706.58 | O4: 283602.49 | P4: =J4/M4 -> 4667.2608
B5: 3 | C5: Trent | D5: 5370.5 | E5: 35.55 | F5: =E5*D5 -> 190921.27 | G5: 2237.19 | H5: 339.84 | I5: =G5-H5 -> 1897.35 | J5: =F5+G5-H5 -> 192818.62 | K5: 192811.89 | L5: 17913.65 | M5: 59.38 | N5: 1567.9 | O5: 190914.54 | P5: =J5/M5 -> 3247.1981
B6: 4 | C6: Swiggy | D6: 398.4 | E6: 249.36 | F6: =E6*D6 -> 99345.024 | G6: 1702.95 | H6: 3299.61 | I6: =G6-H6 -> -1596.66 | J6: =F6+G6-H6 -> 97748.364 | K6: 97750.23 | L6: 16965.52 | M6: -34.87 | N6: -3702.61 | O6: 99346.89 | P6: =J6/M6 -> -2803.2224
B7: 5 | C7: Info Edg.(India) | D7: 1365.4 | E7: 64.79 | F7: =E7*D7 -> 88464.266 | G7: 267.34 | H7: 267.13 | I7: =G7-H7 -> 0.21 | J7: =F7+G7-H7 -> 88464.476 | K7: 88467.29 | L7: 2963.71 | M7: 43.21 | N7: 1393.91 | O7: 88467.08 | P7: =J7/M7 -> 2047.3149
B8: 6 | C8: Vishal Mega Mart | D8: 146.56 | E8: 466.14 | F8: =E8*D8 -> 68317.478 | G8: 1729.38 | H8: 463.67 | I8: =G8-H8 -> 1265.71 | J8: =F8+G8-H8 -> 69583.188 | K8: 69582.76 | L8: 11260.37 | M8: 41.13 | N8: 687.89 | O8: 68317.05 | P8: =J8/M8 -> 1691.7867
B9: 7 | C9: FSN E-Commerce | D9: 215.14 | E9: 286.07 | F9: =E9*D9 -> 61545.1 | G9: 1320.59 | H9: 217.15 | I9: =G9-H9 -> 1103.44 | J9: =F9+G9-H9 -> 62648.54 | K9: 62648.5 | L9: 8358.65 | M9: 114.38 | N9: 82.9 | O9: 61545.06 | P9: =J9/M9 -> 547.72285
B10: 8 | C10: Brainbees Solut. | D10: 370.45 | E10: 52.18 | F10: =E10*D10 -> 19330.081 | G10: 1569.93 | H10: 1705.57 | I10: =G10-H10 -> -135.64 | J10: =F10+G10-H10 -> 19194.441 | K10: 19195.36 | L10: 7870.11 | M10: 49.73 | N10: -255.64 | O10: 19331 | P10: =J10/M10 -> 385.97307
B11: 9 | C11: Vedant Fashions | D11: 743.6 | E11: 24.29 | F11: =E11*D11 -> 18062.044 | G11: 482.89 | H11: 17.23 | I11: =G11-H11 -> 465.66 | J11: =F11+G11-H11 -> 18527.704 | K11: 18531.38 | L11: 1427.86 | M11: 25.04 | N11: 396.25 | O11: 18065.72 | P11: =J11/M11 -> 739.92428
B12: 10 | C12: A B Lifestyle | D12: 131.93 | E12: 122.03 | F12: =E12*D12 -> 16099.418 | G12: 2932.45 | H12: 53.65 | I12: =G12-H12 -> 2878.8 | J12: =F12+G12-H12 -> 18978.218 | K12: 18978.15 | L12: 7829.96 | M12: 14.67 | N12: 59.6 | O12: 16099.35 | P12: =J12/M12 -> 1293.6754
B13: 11 | C13: Indiamart Inter. | D13: 2545.8 | E13: 6 | F13: =E13*D13 -> 15274.8 | G13: 33.04 | H13: 84.39 | I13: =G13-H13 -> -51.35 | J13: =F13+G13-H13 -> 15223.45 | K13: 15231.63 | L13: 1429.2 | M13: 19.13 | N13: 590.2 | O13: 15282.98 | P13: =J13/M13 -> 795.78934
B14: 12 | C14: Cartrade Tech | D14: 2320.9 | E14: 4.75 | F14: =E14*D14 -> 11024.275 | G14: 131.37 | H14: 76.6 | I14: =G14-H14 -> 54.77 | J14: =F14+G14-H14 -> 11079.045 | K14: 11077.67 | L14: 672.98 | M14: 43.85 | N14: 169.43 | O14: 11022.9 | P14: =J14/M14 -> 252.65781
... B17: 15 | C17: RattanIndia Ent | D17: 50.95 | E17: 138.23 | F17: =E17*D17 -> 7042.8185 | G17: 923.46 | H17: 130.68 | I17: =G17-H17 -> 792.78 | J17: =F17+G17-H17 -> 7835.5985 | K17: 7835.44 | L17: 7539.85 | M17: -48.85 | N17: -268.22 | O17: 7042.66 | P17: =J17/M17 -> -160.4012

Sheet Historical Approch
B2: Avenue SuperMart Historical Data - 2018-2025
B4: Date | C4: Close | D4: Return | E4: Sorted Return | F4: Replication | G4: Simulated Returns | I4: Calculation Of Value At Risk -AvenueSuperMart
B5: 43476.646 | C5: 1571.65 | D5: =(C5-C6)/C6 -> -0.65629715 | E5: 0.12469586 | F5: 1 | G5: =_xlfn.NORM.INV(RAND(),$M$7,$M$8) -> -0.018945213
B6: 45576.646 | C6: 4572.7 | D6: =(C6-C7)/C7 -> -0.14107537 | E6: 0.093006024 | F6: 2 | G6: =_xlfn.NORM.INV(RAND(),$M$7,$M$8) -> 0.005499441 | I6: Historcal Approch
B7: 44483.646 | C7: 5323.75 | D7: =(C7-C8)/C8 -> 0.34990365 | E7: 0.086967618 | F7: 3 | G7: =_xlfn.NORM.INV(RAND(),$M$7,$M$8) -> 0.014476412 | I7: Mean | M7: =AVERAGE(E5:E1882) -> -0.00052670452
B8: 44686.646 | C8: 3943.8 | D8: =(C8-C9)/C9 -> 0.83744496 | E8: 0.075718728 | F8: 4 | G8: =_xlfn.NORM.INV(RAND(),$M$7,$M$8) -> 0.029224597 | I8: Standard Deviation | M8: =_xlfn.STDEV.S(E5:E1882) -> 0.019828942
B9: 44027.646 | C9: 2146.35 | D9: =(C9-C10)/C10 -> 0.30231782 | E9: 0.069405346 | F9: 5 | G9: =_xlfn.NORM.INV(RAND(),$M$7,$M$8) -> 0.014923443 | I9: Max | M9: =MAX(E5:E1882) -> 0.12469586
B10: 43455.646 | C10: 1648.1 | D10: =(C10-C11)/C11 -> -0.6167031 | E10: 0.066213812 | F10: 6 | G10: =_xlfn.NORM.INV(RAND(),$M$7,$M$8) -> -0.039279372 | I10: Min | M10: =MIN(E5:E1882) -> -0.10287688
B11: 44582.646 | C11: 4299.8 | D11: =(C11-C12)/C12 -> 0.16759898 | E11: 0.065546552 | F11: 7 | G11: =_xlfn.NORM.INV(RAND(),$M$7,$M$8) -> -0.025716728 | I11: CMP | M11: 4608.1
B12: 44728.646 | C12: 3682.6 | D12: =(C12-C13)/C13 -> 1.6086279 | E12: 0.064166101 | F12: 8 | G12: =_xlfn.NORM.INV(RAND(),$M$7,$M$8) -> -0.020458593
B13: 43385.646 | C13: 1411.7 | D13: =(C13-C14)/C14 -> 0.078745272 | E13: 0.061628126 | F13: 9 | G13: =_xlfn.NORM.INV(RAND(),$M$7,$M$8) -> 0.0083533023 | I13: MonteCarlo Simulation
B14: 43390.646 | C14: 1308.65 | D14: =(C14-C15)/C15 -> -0.086775994 | E14: 0.060279522 | F14: 10 | G14: =_xlfn.NORM.INV(RAND(),$M$7,$M$8) -> -0.015044706 | I14: Mean | M14: =AVERAGE(G5:G1883) -> -0.00060678919
B15: 43650.646 | C15: 1433 | D15: =(C15-C16)/C16 -> -0.43674705 | E15: 0.056667773 | F15: 11 | G15: =_xlfn.NORM.INV(RAND(),$M$7,$M$8) -> -0.01196188 | I15: Standard Deviation | M15: =_xlfn.STDEV.S(G5:G1883) -> 0.020170836
B16: 43874.646 | C16: 2544.15 | D16: =(C16-C17)/C17 -> 0.70177258 | E16: 0.056387153 | F16: 12 | G16: =_xlfn.NORM.INV(RAND(),$M$7,$M$8) -> 0.031568675 | I16: Max | M16: =MAX(G5:G1883) -> 0.05397412
B17: 43237.646 | C17: 1495 | D17: =(C17-C18)/C18 -> -0.465011 | E17: 0.05489698 | F17: 13 | G17: =_xlfn.NORM.INV(RAND(),$M$7,$M$8) -> 0.0056760404 | I17: Min | M17: =MIN(G5:G1883) -> -0.069892198
B18: 44224.646 | C18: 2794.45 | D18: =(C18-C19)/C19 -> -0.37968656 | E18: 0.05391288 | F18: 14 | G18: =_xlfn.NORM.INV(RAND(),$M$7,$M$8) -> 0.033695526 | I18: CMP | M18: 4608.1
B19: 44572.646 | C19: 4504.9 | D19: =(C19-C20)/C20 -> 2.1787327 | E19: 0.0535067 | F19: 15 | G19: =_xlfn.NORM.INV(RAND(),$M$7,$M$8) -> -0.0034777825
B20: 43238.646 | C20: 1417.2 | D20: =(C20-C21)/C21 -> -0.26037263 | E20: 0.053327883 | F20: 16 | G20: =_xlfn.NORM.INV(RAND(),$M$7,$M$8) -> -0.005811934 | I20: Percentile | J20: Confidence | K20: VAR % | L20: Stock Price | M20: VAR(INR)
B21: 43910.646 | C21: 1916.1 | D21: =(C21-C22)/C22 -> -0.19917247 | E21: 0.052628688 | F21: 17 | G21: =_xlfn.NORM.INV(RAND(),$M$7,$M$8) -> 0.0029468545
B22: 43930.646 | C22: 2392.65 | D22: =(C22-C23)/C23 -> 0.13398422 | E22: 0.052616528 | F22: 18 | G22: =_xlfn.NORM.INV(RAND(),$M$7,$M$8) -> 0.025335107 | I22: 0.05 | J22: =100%-I22 -> 0.95 | K22: =_xlfn.PERCENTILE.INC(G5:G1883,I22) -> -0.033788788 | L22: =$M$11*(1-K22) -> 4763.8021 | M22: =$M$11-L22 -> -155.70212
B23: 43901.646 | C23: 2109.95 | D23: =(C23-C24)/C24 -> 0.098417409 | E23: 0.052606635 | F23: 19 | G23: =_xlfn.NORM.INV(RAND(),$M$7,$M$8) -> -8.613558e-05 | I23: 0.01 | J23: =100%-I23 -> 0.99 | K23: =_xlfn.PERCENTILE.INC(G5:G1884,I23) -> -0.044549863 | L23: =$M$11*(1-K23) -> 4813.3902 | M23: =$M$11-L23 -> -205.29022
B24: 43908.646 | C24: 1920.9 | D24: =(C24-C25)/C25 -> -0.049976508 | E24: 0.052605622 | F24: 20 | G24: =_xlfn.NORM.INV(RAND(),$M$7,$M$8) -> -0.004828586 | I24: 0.005 | J24: =100%-I24 -> 0.995 | K24: =_xlfn.PERCENTILE.INC(G5:G1885,I24) -> -0.049474305 | L24: =$M$11*(1-K24) -> 4836.0825 | M24: =$M$11-L24 -> -227.98254
B25: 43907.646 | C25: 2021.95 | D25: =(C25-C26)/C26 -> -0.037624941 | E25: 0.052605549 | F25: 21 | G25: =_xlfn.NORM.INV(RAND(),$M$7,$M$8) -> -0.028508752
B26: 43903.646 | C26: 2101 | D26: =(C26-C27)/C27 -> -0.58649058 | E26: 0.052447027 | F26: 22 | G26: =_xlfn.NORM.INV(RAND(),$M$7,$M$8) -> -0.023821818
B27: 44518.646 | C27: 5080.9 | D27: =(C27-C28)/C28 -> 3.2632153 | E27: 0.05231655 | F27: 23 | G27: =_xlfn.NORM.INV(RAND(),$M$7,$M$8) -> 0.0026507513
B28: 43395.646 | C28: 1191.8 | D28: =(C28-C29)/C29 -> -0.6766904 | E28: 0.051248126 | F28: 24 | G28: =_xlfn.NORM.INV(RAND(),$M$7,$M$8) -> 0.023296912
B29: 45667.646 | C29: 3686.25 | D29: =(C29-C30)/C30 -> -0.045927479 | E29: 0.050977206 | F29: 25 | G29: =_xlfn.NORM.INV(RAND(),$M$7,$M$8) -> -0.0037625968
B30: 44939.646 | C30: 3863.7 | D30: =(C30-C31)/C31 -> 0.61101614 | E30: 0.050389441 | F30: 26 | G30: =_xlfn.NORM.INV(RAND(),$M$7,$M$8) -> -0.0074558733
B31: 43973.646 | C31: 2398.3 | D31: =(C31-C32)/C32 -> 0.096365714 | E31: 0.0503887 | F31: 27 | G31: =_xlfn.NORM.INV(RAND(),$M$7,$M$8) -> -0.0055133602
B32: 43921.646 | C32: 2187.5 | D32: =(C32-C33)/C33 -> -0.47692492 | E32: 0.050319297 | F32: 28 | G32: =_xlfn.NORM.INV(RAND(),$M$7,$M$8) -> -0.019029391
B33: 44910.646 | C33: 4182 | D33: =(C33-C34)/C34 -> 0.41870918 | E33: 0.048120301 | F33: 29 | G33: =_xlfn.NORM.INV(RAND(),$M$7,$M$8) -> 0.028528328
B34: 44295.646 | C34: 2947.75 | D34: =(C34-C35)/C35 -> -0.34868588 | E34: 0.047195282 | F34: 30 | G34: =_xlfn.NORM.INV(RAND(),$M$7,$M$8) -> -0.012945977
B35: 44819.646 | C35: 4525.85 | D35: =(C35-C36)/C36 -> 0.23831347 | E35: 0.045822694 | F35: 31 | G35: =_xlfn.NORM.INV(RAND(),$M$7,$M$8) -> -0.022188032
B36: 45021.646 | C36: 3654.85 | D36: =(C36-C37)/C37 -> 0.63006489 | E36: 0.04540774 | F36: 32 | G36: =_xlfn.NORM.INV(RAND(),$M$7,$M$8) -> -0.037892954
... B1882: 45659.646 | C1882: 3611.1 | D1882: =(C1882-C1883)/C1883 -> -0.20774462 | E1882: -0.10287688 | F1882: 1878 | G1882: =_xlfn.NORM.INV(RAND(),$M$7,$M$8) -> -0.033404488
B1883: 45887.646 | C1883: 4558 | F1883: 1879 | G1883: =_xlfn.NORM.INV(RAND(),$M$7,$M$8) -> -0.0098753152

Sheet Monte Carlo Simulation
B2: Avenue SuperMart Historical Data - 2018-2025
B4: Date | C4: Close | D4: Return | E4: Sorted Return | G4: Calculation Of Value At Risk -AvenueSuperMart
B5: 43476.646 | C5: 1571.65 | D5: =(C5-C6)/C6 -> -0.65629715 | E5: 0.12469586
B6: 45576.646 | C6: 4572.7 | D6: =(C6-C7)/C7 -> -0.14107537 | E6: 0.093006024 | G6: Mean | K6: =AVERAGE(E5:E1882) -> -0.00052670452
B7: 44483.646 | C7: 5323.75 | D7: =(C7-C8)/C8 -> 0.34990365 | E7: 0.086967618 | G7: Standard Deviation | K7: =_xlfn.STDEV.S(E5:E1882) -> 0.019828942
B8: 44686.646 | C8: 3943.8 | D8: =(C8-C9)/C9 -> 0.83744496 | E8: 0.075718728 | G8: Max | K8: =MAX(E5:E1882) -> 0.12469586
B9: 44027.646 | C9: 2146.35 | D9: =(C9-C10)/C10 -> 0.30231782 | E9: 0.069405346 | G9: Min | K9: =MIN(E5:E1882) -> -0.10287688
B10: 43455.646 | C10: 1648.1 | D10: =(C10-C11)/C11 -> -0.6167031 | E10: 0.066213812 | G10: CMP | K10: 4608.1
B11: 44582.646 | C11: 4299.8 | D11: =(C11-C12)/C12 -> 0.16759898 | E11: 0.065546552
B12: 44728.646 | C12: 3682.6 | D12: =(C12-C13)/C13 -> 1.6086279 | E12: 0.064166101
B13: 43385.646 | C13: 1411.7 | D13: =(C13-C14)/C14 -> 0.078745272 | E13: 0.061628126 | G13: Percentile | H13: Confidence | I13: VAR % | J13: Stock Price | K13: VAR(INR)
B14: 43390.646 | C14: 1308.65 | D14: =(C14-C15)/C15 -> -0.086775994 | E14: 0.060279522
B15: 43650.646 | C15: 1433 | D15: =(C15-C16)/C16 -> -0.43674705 | E15: 0.056667773 | G15: 0.05 | H15: =100%-G15 -> 0.95 | I15: =_xlfn.PERCENTILE.INC(E5:E1882,G15) -> -0.033633508 | J15: =$K$10*(1-I15) -> 4763.0866 | K15: =$K$10-J15 -> -154.98657
B16: 43874.646 | C16: 2544.15 | D16: =(C16-C17)/C17 -> 0.70177258 | E16: 0.056387153 | G16: 0.01 | H16: =100%-G16 -> 0.99 | I16: =_xlfn.PERCENTILE.INC(E6:E1883,G16) -> -0.053852037 | J16: =$K$10*(1-I16) -> 4856.2556 | K16: =$K$10-J16 -> -248.15557
B17: 43237.646 | C17: 1495 | D17: =(C17-C18)/C18 -> -0.465011 | E17: 0.05489698 | G17: 0.005 | H17: =100%-G17 -> 0.995 | I17: =_xlfn.PERCENTILE.INC(E7:E1884,G17) -> -0.065375202 | J17: =$K$10*(1-I17) -> 4909.3555 | K17: =$K$10-J17 -> -301.25547
B18: 44224.646 | C18: 2794.45 | D18: =(C18-C19)/C19 -> -0.37968656 | E18: 0.05391288
B19: 44572.646 | C19: 4504.9 | D19: =(C19-C20)/C20 -> 2.1787327 | E19: 0.0535067
B20: 43238.646 | C20: 1417.2 | D20: =(C20-C21)/C21 -> -0.26037263 | E20: 0.053327883
B21: 43910.646 | C21: 1916.1 | D21: =(C21-C22)/C22 -> -0.19917247 | E21: 0.052628688
B22: 43930.646 | C22: 2392.65 | D22: =(C22-C23)/C23 -> 0.13398422 | E22: 0.052616528
B23: 43901.646 | C23: 2109.95 | D23: =(C23-C24)/C24 -> 0.098417409 | E23: 0.052606635
B24: 43908.646 | C24: 1920.9 | D24: =(C24-C25)/C25 -> -0.049976508 | E24: 0.052605622
B25: 43907.646 | C25: 2021.95 | D25: =(C25-C26)/C26 -> -0.037624941 | E25: 0.052605549
B26: 43903.646 | C26: 2101 | D26: =(C26-C27)/C27 -> -0.58649058 | E26: 0.052447027
B27: 44518.646 | C27: 5080.9 | D27: =(C27-C28)/C28 -> 3.2632153 | E27: 0.05231655
B28: 43395.646 | C28: 1191.8 | D28: =(C28-C29)/C29 -> -0.6766904 | E28: 0.051248126
B29: 45667.646 | C29: 3686.25 | D29: =(C29-C30)/C30 -> -0.045927479 | E29: 0.050977206
... B1882: 45659.646 | C1882: 3611.1 | D1882: =(C1882-C1883)/C1883 -> -0.20774462 | E1882: -0.10287688
B1883: 45887.646 | C1883: 4558

Sheet Dupond Analysis
B4: ='Data Sheet'!B1 -> AVENUE SUPERMARTS LTD
B7: =CONCATENATE(" ","INR "&'Data Sheet'!B8) -> INR 4358.2
B8: 52 Week (High- INR 5,484.85 & Low - INR 3,340.00)
B10: About The Company
B11: Avenue Supermarts Limited, DMart, is an Indian retail corporation that operates a chain of supermarkets and hypermarkets. The company was founded by Radhakishan Damani and is based in Mumbai. As of March 2025, DMart has 415 stores across 12 states and union territories in India] In March 2024, the company had a total of 13,971 permanent employees and 59,961 employees hired on contractual basis
B17: Summery
B45: Return On Equity (ROE)
C46: ='Raw FS'!F2 -> 42795 | D46: ='Raw FS'!G2 -> 43160 | E46: ='Raw FS'!H2 -> 43525 | F46: ='Raw FS'!I2 -> 43891 | G46: ='Raw FS'!J2 -> 44256 | H46: ='Raw FS'!K2 -> 44621 | I46: ='Raw FS'!L2 -> 44986 | J46: ='Raw FS'!M2 -> 45352 | K46: ='Raw FS'!N2 -> 45717
B47: Net Profit | C47: =HistoricaIFS!D32 -> 478.75 | D47: =HistoricaIFS!E32 -> 806.26 | E47: =HistoricaIFS!F32 -> 902.54 | F47: =HistoricaIFS!G32 -> 1301.08 | G47: =HistoricaIFS!H32 -> 1099.49 | H47: =HistoricaIFS!I32 -> 1492.55 | I47: =HistoricaIFS!J32 -> 2378.51 | J47: =HistoricaIFS!K32 -> 2536.17 | K47: =HistoricaIFS!L32 -> 2708.02
B48: Average Shareholder Equity | C48: =(('Data Sheet'!C57+'Data Sheet'!C58)+('Data Sheet'!B57+'Data Sheet'!B58))/2 -> 2681.11 | D48: =(('Data Sheet'!D57+'Data Sheet'!D58)+('Data Sheet'!C57+'Data Sheet'!C58))/2 -> 4255.415 | E48: =(('Data Sheet'!E57+'Data Sheet'!E58)+('Data Sheet'!D57+'Data Sheet'!D58))/2 -> 5128.25 | F48: =(('Data Sheet'!F57+'Data Sheet'!F58)+('Data Sheet'!E57+'Data Sheet'!E58))/2 -> 8333.595 | G48: =(('Data Sheet'!G57+'Data Sheet'!G58)+('Data Sheet'!F57+'Data Sheet'!F58))/2 -> 11631.725 | H48: =(('Data Sheet'!H57+'Data Sheet'!H58)+('Data Sheet'!G57+'Data Sheet'!G58))/2 -> 12930.675 | I48: =(('Data Sheet'!I57+'Data Sheet'!I58)+('Data Sheet'!H57+'Data Sheet'!H58))/2 -> 14878.17 | J48: =(('Data Sheet'!J57+'Data Sheet'!J58)+('Data Sheet'!I57+'Data Sheet'!I58))/2 -> 17388.26 | K48: =(('Data Sheet'!K57+'Data Sheet'!K58)+('Data Sheet'!J57+'Data Sheet'!J58))/2 -> 20062.785
B49: Return On Equity | C49: =C47/C48 -> 0.1785641 | D49: =D47/D48 -> 0.18946683 | E49: =E47/E48 -> 0.17599376 | F49: =F47/F48 -> 0.1561247 | G49: =G47/G48 -> 0.094525103 | H49: =H47/H48 -> 0.11542708 | I49: =I47/I48 -> 0.15986576 | J49: =J47/J48 -> 0.14585531 | K49: =K47/K48 -> 0.13497727
B51: ROE - Dupond Analysis
C52: =C46 -> 42795 | D52: =D46 -> 43160 | E52: =E46 -> 43525 | F52: =F46 -> 43891 | G52: =G46 -> 44256 | H52: =H46 -> 44621 | I52: =I46 -> 44986 | J52: =J46 -> 45352 | K52: =K46 -> 45717
B53: Net Profit | C53: 658.75 | D53: 623.56 | E53: 690.61 | F53: 563.25 | G53: 773.82 | H53: 659.58 | I53: 723.72 | J53: 550.9 | K53: 772.97
B54: Reserve | C54: ='Data Sheet'!C17 -> 11897.7 | D54: ='Data Sheet'!D17 -> 15033.2 | E54: ='Data Sheet'!E17 -> 20004.52 | F54: ='Data Sheet'!F17 -> 24870.2 | G54: ='Data Sheet'!G17 -> 24143.06 | H54: ='Data Sheet'!H17 -> 30976.27 | I54: ='Data Sheet'!I17 -> 42839.56 | J54: ='Data Sheet'!J17 -> 50788.83 | K54: ='Data Sheet'!K17 -> 59358.05
B55: Net Profit Margine(A) | C55: =C53/C54 -> 0.055367844 | D55: =D53/D54 -> 0.04147886 | E55: =E53/E54 -> 0.034522698 | F55: =F53/F54 -> 0.022647586 | G55: =G53/G54 -> 0.032051447 | H55: =H53/H54 -> 0.021293074 | I55: =I53/I54 -> 0.016893731 | J55: =J53/J54 -> 0.010846873 | K55: =K53/K54 -> 0.01302216
B57: Reserves | C57: =C54 -> 11897.7 | D57: =D54 -> 15033.2 | E57: =E54 -> 20004.52 | F57: =F54 -> 24870.2 | G57: =G54 -> 24143.06 | H57: =H54 -> 30976.27 | I57: =I54 -> 42839.56 | J57: =J54 -> 50788.83 | K57: =K54 -> 59358.05
B58: Average Total Asset | C58: =('Data Sheet'!C66+'Data Sheet'!B66)/2 -> 4460.42 | D58: =('Data Sheet'!D66+'Data Sheet'!C66)/2 -> 5733.75 | E58: =('Data Sheet'!E66+'Data Sheet'!D66)/2 -> 6326.86 | F58: =('Data Sheet'!F66+'Data Sheet'!E66)/2 -> 9540.83 | G58: =('Data Sheet'!G66+'Data Sheet'!F66)/2 -> 12865.605 | H58: =('Data Sheet'!H66+'Data Sheet'!G66)/2 -> 14563.015 | I58: =('Data Sheet'!I66+'Data Sheet'!H66)/2 -> 16787.75 | J58: =('Data Sheet'!J66+'Data Sheet'!I66)/2 -> 19638.5 | K58: =('Data Sheet'!K66+'Data Sheet'!J66)/2 -> 22742.63
B59: Asset Turnover Ratio (B) | C59: =C57/C58 -> 2.6673946 | D59: =D57/D58 -> 2.6218792 | E59: =E57/E58 -> 3.1618402 | F59: =F57/F58 -> 2.6067124 | G59: =G57/G58 -> 1.8765585 | H59: =H57/H58 -> 2.1270506 | I59: =I57/I58 -> 2.5518345 | J59: =J57/J58 -> 2.5861868 | K59: =K57/K58 -> 2.6099906
B61: =B58 -> Average Total Asset | C61: =C58 -> 4460.42 | D61: =D58 -> 5733.75 | E61: =E58 -> 6326.86 | F61: =F58 -> 9540.83 | G61: =G58 -> 12865.605 | H61: =H58 -> 14563.015 | I61: =I58 -> 16787.75 | ... K61: =K58 -> 22742.63
B62: =B48 -> Average Shareholder Equity | C62: =C48 -> 2681.11 | D62: =D48 -> 4255.415 | E62: =E48 -> 5128.25 | F62: =F48 -> 8333.595 | G62: =G48 -> 11631.725 | H62: =H48 -> 12930.675 | I62: =I48 -> 14878.17 | ... K62: =K48 -> 20062.785
B63: Equity Multiplier (C) | C63: =C61/C62 -> 1.6636468 | D63: =D61/D62 -> 1.3474009 | E63: =E61/E62 -> 1.2337269 | F63: =F61/F62 -> 1.1448637 | G63: =G61/G62 -> 1.1060788 | H63: =H61/H62 -> 1.1262378 | I63: =I61/I62 -> 1.1283478 | J63: =J61/J62 -> 1.1294115 | K63: =K61/K62 -> 1.1335729
B65: =B49 -> Return On Equity | C65: =C63*C59*C55 -> 0.24570047 | D65: =D63*D59*D55 -> 0.1465333 | E65: =E63*E59*E55 -> 0.13466777 | F65: =F63*F59*F55 -> 0.067587878 | G65: =G63*G59*G55 -> 0.066526676 | H65: =H63*H59*H55 -> 0.051008938 | I65: =I63*I59*I55 -> 0.048643079 | J65: =J63*J59*J55 -> 0.031682296 | K65: =K63*K59*K55 -> 0.038527552
B67: Return On Asset (ROA)
C68: =C46 -> 42795 | D68: =D46 -> 43160 | E68: =E46 -> 43525 | F68: =F46 -> 43891 | G68: =G46 -> 44256 | H68: =H46 -> 44621 | I68: =I46 -> 44986 | J68: =J46 -> 45352 | K68: =K46 -> 45717
B69: Net Profit | C69: =C47 -> 478.75 | D69: =D47 -> 806.26 | E69: =E47 -> 902.54 | F69: =F47 -> 1301.08 | G69: =G47 -> 1099.49 | H69: =H47 -> 1492.55 | I69: =I47 -> 2378.51 | J69: =J47 -> 2536.17 | K69: =K47 -> 2708.02
B70: =B58 -> Average Total Asset | C70: =C58 -> 4460.42 | D70: =D58 -> 5733.75 | E70: =E58 -> 6326.86 | F70: =F58 -> 9540.83 | G70: =G58 -> 12865.605 | H70: =H58 -> 14563.015 | I70: =I58 -> 16787.75 | ... K70: =K58 -> 22742.63
B71: Return On Asset | C71: =C69/C70 -> 0.10733294 | D71: =D69/D70 -> 0.14061652 | E71: =E69/E70 -> 0.14265212 | F71: =F69/F70 -> 0.13636969 | G71: =G69/G70 -> 0.085459642 | H71: =H69/H70 -> 0.10248908 | I71: =I69/I70 -> 0.14168129 | J71: =J69/J70 -> 0.12914276 | K71: =K69/K70 -> 0.11907242
B73: ROA - Dupond Analysis
C74: =C68 -> 42795 | D74: =D68 -> 43160 | E74: =E68 -> 43525 | F74: =F68 -> 43891 | G74: =G68 -> 44256 | H74: =H68 -> 44621 | I74: =I68 -> 44986 | J74: =J68 -> 45352 | K74: =K68 -> 45717
B75: Net Profit | C75: 658.75 | D75: 623.56 | E75: 690.61 | F75: 563.25 | G75: 773.82 | H75: 659.58 | I75: 723.72 | J75: 550.9 | K75: 772.97
B76: Reserve | C76: =C54 -> 11897.7 | D76: =D54 -> 15033.2 | E76: =E54 -> 20004.52 | F76: =F54 -> 24870.2 | G76: =G54 -> 24143.06 | H76: =H54 -> 30976.27 | I76: =I54 -> 42839.56 | J76: =J54 -> 50788.83 | K76: =K54 -> 59358.05
B77: Net Profit Margine(A) | C77: =C75/C76 -> 0.055367844 | D77: =D75/D76 -> 0.04147886 | E77: =E75/E76 -> 0.034522698 | F77: =F75/F76 -> 0.022647586 | G77: =G75/G76 -> 0.032051447 | H77: =H75/H76 -> 0.021293074 | I77: =I75/I76 -> 0.016893731 | J77: =J75/J76 -> 0.010846873 | K77: =K75/K76 -> 0.01302216
B79: Reserves | C79: =C76 -> 11897.7 | D79: =D76 -> 15033.2 | E79: =E76 -> 20004.52 | F79: =F76 -> 24870.2 | G79: =G76 -> 24143.06 | H79: =H76 -> 30976.27 | I79: =I76 -> 42839.56 | J79: =J76 -> 50788.83 | K79: =K76 -> 59358.05
B80: Average Total Asset | C80: =C58 -> 4460.42 | D80: =D58 -> 5733.75 | E80: =E58 -> 6326.86 | F80: =F58 -> 9540.83 | G80: =G58 -> 12865.605 | H80: =H58 -> 14563.015 | I80: =I58 -> 16787.75 | J80: =J58 -> 19638.5 | K80: =K58 -> 22742.63
B81: Asset Turnover Ratio (B) | C81: =C79/C80 -> 2.6673946 | D81: =D79/D80 -> 2.6218792 | E81: =E79/E80 -> 3.1618402 | F81: =F79/F80 -> 2.6067124 | G81: =G79/G80 -> 1.8765585 | H81: =H79/H80 -> 2.1270506 | I81: =I79/I80 -> 2.5518345 | J81: =J79/J80 -> 2.5861868 | K81: =K79/K80 -> 2.6099906
B83: Return On Asset (A*B) | C83: =C77*C81 -> 0.14768789 | D83: =D77*D81 -> 0.10875256 | E83: =E77*E81 -> 0.10915525 | F83: =F77*F81 -> 0.059035744 | G83: =G77*G81 -> 0.060146414 | H83: =H77*H81 -> 0.045291445 | I83: =I77*I81 -> 0.043110006 | J83: =J77*J81 -> 0.028052041 | K83: =K77*K81 -> 0.033987714
